Workbook

Sheet OCT
A1: Tipo de documento | B1: CUFE/CUDE | C1: Folio | D1: Prefijo | E1: Fecha Emisión | F1: Fecha Recepción | G1: NIT Emisor | H1: Nombre Emisor | I1: Subtotal | J1: IVA | K1: Total | L1: Responsable | M1: FECHA DE ENTREGA | N1: RANGO DE ENTREGA DIAS | O1: QUIEN ENTREGA | P1: NOMBRE A QUIEN SE DEVUELVE | Q1: FECHA DEVOLUCION | R1: REINTEGRO | S1: FECHA ENTREGA TESORERIA
N3: =IF(-_xlfn.DAYS(E3,M3)<0,0,-_xlfn.DAYS(E3,M3)) -> 0

Sheet NOV
A1: Tipo de documento | B1: CUFE/CUDE | C1: Folio | D1: Prefijo | E1: Fecha Emisión | F1: Fecha Recepción | G1: NIT Emisor | H1: Nombre Emisor | I1: Subtotal | J1: IVA | K1: Total | L1: Responsable | M1: FECHA DE ENTREGA | N1: RANGO DE ENTREGA DIAS | O1: QUIEN ENTREGA | P1: NOMBRE A QUIEN SE DEVUELVE | Q1: FECHA DEVOLUCION | R1: REINTEGRO | S1: FECHA ENTREGA TESORERIA
N3: =IF(-_xlfn.DAYS(E3,M3)<0,0,-_xlfn.DAYS(E3,M3)) -> 0

Sheet DIC
A1: Tipo de documento | B1: CUFE/CUDE | C1: Folio | D1: Prefijo | E1: Fecha Emisión | F1: Fecha Recepción | G1: NIT Emisor | H1: Nombre Emisor | I1: Subtotal | J1: IVA | K1: Total | L1: Responsable | M1: FECHA DE ENTREGA | N1: RANGO DE ENTREGA DIAS | O1: QUIEN ENTREGA | P1: NOMBRE A QUIEN SE DEVUELVE | Q1: FECHA DEVOLUCION | R1: REINTEGRO | S1: FECHA ENTREGA TESORERIA
N3: =IF(-_xlfn.DAYS(E3,M3)<0,0,-_xlfn.DAYS(E3,M3)) -> 0

Sheet ENERO
A1: Tipo documento | B1: CUFE/CUDE | C1: Folio | D1: Prefijo | E1: Fecha Emisión | F1: Fecha Recepción | G1: NIT | H1: Nombre Emisor | I1: Subtotal | J1: IVA | K1: Total | L1: Responsable | M1: FECHA DE ENTREGA | N1: DÍAS DE ENTREGA A CONTABILIDAD | O1: QUIEN ENTREGA | P1: NOMBRE A QUIEN SE DEVUELVE | Q1: FECHA DEVOLUCION | R1: REINTEGRO | S1: RANGO DE ENTREGA A TESORERIA DIAS | T1: FECHA ENTREGA TESORERIA | U1: REQUIERE FIRMA DE GERENCIA | V1: FIRMADAS | W1: RANGO DÍAS DE ENTREGA
A2: Factura electrónica | B2: 87ddcf5ecab4c8d8a9db5393ab38442822d2b08ab664baac6a2caf9e6a22d5de7dcc5dfc73bc6b5517f0b8683f56c939 | C2: 3512 | D2: FE | E2: 46044 | F2: 46044.457 | G2: 811027589 | H2: Zonalogística S.A.S ZLG | I2: =K2-J2 -> 12048400 | J2: 2289196 | K2: 14337596 | L2: GERENCIA | M2: 46051 | N2: =IFERROR(IF(-_xlfn.DAYS(E2,M2)<0,0,-_xlfn.DAYS(E2,M2)), " - ") -> 7 | O2: ANGELA SEPULVEDA | T2: 46057 | U2: SI | W2: 6 a 10
A3: Factura electrónica | B3: e19a155a90b793b91be3542d9a010f3420db282ee75f7584134eb96bd29690d21824eb3cc144c81bb0a1a913216ddf7f | C3: 485 | D3: WC | E3: 46028 | F3: 46028.845 | G3: 901741749 | H3: WORLD CRANES SAS | I3: =K3-J3 -> 8450000 | J3: 1605500 | K3: 10055500 | L3: MANTENIMIENTO | M3: 46030 | N3: =IFERROR(IF(-_xlfn.DAYS(E3,M3)<0,0,-_xlfn.DAYS(E3,M3)), " - ") -> 2 | O3: YENIFER PARRA | T3: 46044 | U3: NO | W3: 0 a 5
A4: Factura electrónica | B4: 04a2398fe369568a1352ac79a927d7de329dc854fa6f340ed9a6c5fd12ef5cd56708eb4eef5e87218816d347f2f74369 | C4: 488 | D4: WC | E4: 46030 | F4: 46030.491 | G4: 901741749 | H4: WORLD CRANES SAS | I4: =K4-J4 -> 800000 | J4: 152000 | K4: 952000 | L4: MANTENIMIENTO | M4: 46030 | N4: =IFERROR(IF(-_xlfn.DAYS(E4,M4)<0,0,-_xlfn.DAYS(E4,M4)), " - ") -> 0 | O4: YENIFER PARRA | T4: 46044 | U4: NO | W4: 0 a 5
A5: Factura electrónica | B5: 045077b960eea26c79b2996fce29de61548aab3f3700f5c7abaf377db39c7fd37152003449b458bf8145845a785adb41 | C5: 498 | D5: WC | E5: 46037 | F5: 46037.79 | G5: 901741749 | H5: WORLD CRANES SAS | I5: =K5-J5 -> 150000 | J5: 28500 | K5: 178500 | L5: MANTENIMIENTO | M5: 46042 | N5: =IFERROR(IF(-_xlfn.DAYS(E5,M5)<0,0,-_xlfn.DAYS(E5,M5)), " - ") -> 5 | O5: YENIFER PARRA | T5: 46044 | U5: no | W5: 0 a 5
A6: Factura electrónica | B6: f99e39cec77c247d93fc9f99a2db9cb09dcfc6f4e64288e59d2351554d874f43dbfe406ea41d4d372d48f0241328cac8 | C6: 497 | D6: WC | E6: 46037 | F6: 46037.779 | G6: 901741749 | H6: WORLD CRANES SAS | I6: =K6-J6 -> 3600000 | J6: 684000 | K6: 4284000 | L6: MANTENIMIENTO | M6: 46042 | N6: =IFERROR(IF(-_xlfn.DAYS(E6,M6)<0,0,-_xlfn.DAYS(E6,M6)), " - ") -> 5 | O6: YENIFER PARRA | T6: 46065 | U6: NO | W6: 0 a 5
A7: Factura electrónica | B7: 71e2920798ae794d2e481dc362b006e33bfd7ae63b22bf9851998071c2897e9a421de1b63e29fd3f2a495f16b94d8760 | C7: 503 | D7: WC | E7: 46044 | F7: 46044.817 | G7: 901741749 | H7: WORLD CRANES SAS | I7: =K7-J7 -> 1600000 | J7: 304000 | K7: 1904000 | L7: MANTENIMIENTO | M7: 46048 | N7: =IFERROR(IF(-_xlfn.DAYS(E7,M7)<0,0,-_xlfn.DAYS(E7,M7)), " - ") -> 4 | O7: YENIFER PARRA | T7: 46063 | U7: NO | W7: 0 a 5
A8: Factura electrónica | B8: 0ea2237f5d6eb476d3ca358aa03319e9c1ed16a7e760cb1da1e9c5ca5da8ec5b1ef537947a3be90402f18903ec5776e6 | C8: 507 | D8: WC | E8: 46046 | F8: 46046.465 | G8: 901741749 | H8: WORLD CRANES SAS | I8: =K8-J8 -> 4600000 | J8: 874000 | K8: 5474000 | L8: MANTENIMIENTO | M8: 46049 | N8: =IFERROR(IF(-_xlfn.DAYS(E8,M8)<0,0,-_xlfn.DAYS(E8,M8)), " - ") -> 3 | O8: YENIFER PARRA | T8: 46065 | U8: NO | W8: 0 a 5
A9: Factura electrónica | B9: eed87bf76288b3850294da00aaa166da031877072c21d09e2ed8b6bb87e47c88cdc92e58abf3ab1994972a063116e61e | C9: 637 | D9: WME | E9: 46038 | F9: 46038.602 | G9: 900618518 | H9: WIRE MACHINE S A S | I9: =K9-J9 -> 54881267 | J9: 10427441 | K9: 65308708 | L9: MANTENIMIENTO | M9: 46059 | N9: =IFERROR(IF(-_xlfn.DAYS(E9,M9)<0,0,-_xlfn.DAYS(E9,M9)), " - ") -> 21 | O9: YENIFER PARRA | T9: 46065 | U9: NO | W9: Más de 10
A10: Factura electrónica | B10: 177166b32fe40e7929fac9f1ef4632be7101b736c8e11d4c6dcc007a93238101d0b7431152a355b5469a056df985d150 | C10: 3397 | D10: FDR | E10: 46028 | F10: 46028.697 | G10: 70907060 | H10: WILINTON DUQUE GONZALEZ | I10: =K10-J10 -> 123100 | J10: 0 | K10: 123100 | L10: CAJA MENOR | N10: =IFERROR(IF(-_xlfn.DAYS(E10,M10)<0,0,-_xlfn.DAYS(E10,M10)), " - ") -> 0
A11: Factura electrónica | B11: 5dd4b0f8183b2ed9b34e3d80ca18f0fb5eb6cd855505e6c6af3b50650a842cc10dc90216225f828795d4f40ef0959040 | C11: 8985 | D11: FEVV | E11: 46050 | F11: 46050.688 | G11: 901242715 | H11: VIANCO TE TRANSPORTA SAS | I11: =K11-J11 -> 1470000 | J11: 0 | K11: 1470000 | L11: OPERACIONES | M11: 46056 | N11: =IFERROR(IF(-_xlfn.DAYS(E11,M11)<0,0,-_xlfn.DAYS(E11,M11)), " - ") -> 6 | O11: YENIFER PARRA | T11: 46058 | U11: NO | W11: 6 a 10
A12: Factura electrónica | B12: 7e447ce310a7a5a2fcde31c65f23fb50b1cecce2daa2e37ab0528a40460c28ecead8bcc544f5dfc89101ffdf7bd0af7a | C12: 18449 | D12: 033 | E12: 46035 | F12: 46035.377 | G12: 890901389 | H12: UNIVERSIDAD EAFIT | I12: =K12-J12 -> 3014783 | J12: 0 | K12: 3014783 | L12: BIENESTAR | M12: 46035 | N12: =IFERROR(IF(-_xlfn.DAYS(E12,M12)<0,0,-_xlfn.DAYS(E12,M12)), " - ") -> 0 | O12: ANGELA SEPULVEDA | T12: 46037 | U12: NO | W12: 0 a 5
A13: Factura electrónica | B13: 0e7931ad3560f20bd514088cc1cbb780bdc318b13d20ceb4a98e65c8946fe62553688cc5011d8b5c28facfcc5036e94e | C13: 296930 | D13: FE | E13: 46030 | F13: 46030.587 | G13: 811021363 | H13: UNIPLES S.A.S. | I13: =K13-J13 -> 371184 | J13: 70524.96 | K13: 441708.96 | L13: TI | M13: 46035 | N13: =IFERROR(IF(-_xlfn.DAYS(E13,M13)<0,0,-_xlfn.DAYS(E13,M13)), " - ") -> 5 | O13: FRANCY SALAS | T13: 46036 | U13: NO | W13: 0 a 5
A14: Factura electrónica | B14: bd1c26409c6a8e4dd3711fd6bf85e51a60c6ed98522afc01ad2a478007302589c57094c825acfeaf297023a6675efe32 | C14: 7265 | D14: U | E14: 46037 | F14: 46037.635 | G14: 901233261 | H14: UNIFORMAR ORIENTE S.A.S | I14: =K14-J14 -> 25212 | J14: 4790.28 | K14: 30002.28 | L14: COMPRAS | M14: 46052 | N14: =IFERROR(IF(-_xlfn.DAYS(E14,M14)<0,0,-_xlfn.DAYS(E14,M14)), " - ") -> 15 | O14: YENIFER PARRA | T14: 46062 | W14: Más de 10
A15: Factura electrónica | B15: da433de26906494786888503b13cba4d9a41975983cc338308956235f3f08f2029503a97837726d0bb1d57b71d5c1f60 | C15: 2874 | D15: FE | E15: 46030 | F15: 46030.463 | G15: 900144364 | H15: UNIDOTAMOS SAS | I15: =K15-J15 -> 14101800 | J15: 2679342 | K15: 16781142 | L15: COMPRAS | M15: 46042 | N15: =IFERROR(IF(-_xlfn.DAYS(E15,M15)<0,0,-_xlfn.DAYS(E15,M15)), " - ") -> 12 | O15: YENIFER PARRA | T15: 46045 | U15: SI | W15: Más de 10
A16: Factura electrónica | B16: 6dfa51d5ca1b744c065b3b3d64994e5c3d0be325e6567257754be51e152df24b0fd77138505475aa6ff20c48fbea2f75 | C16: 2880 | D16: FE | E16: 46038 | F16: 46038.617 | G16: 900144364 | H16: UNIDOTAMOS SAS | I16: =K16-J16 -> 30000 | J16: 5700 | K16: 35700 | L16: COMPRAS | M16: 46041 | N16: =IFERROR(IF(-_xlfn.DAYS(E16,M16)<0,0,-_xlfn.DAYS(E16,M16)), " - ") -> 3 | O16: YENIFER PARRA | T16: 46042 | U16: NO | W16: 0 a 5
A17: Factura electrónica | B17: 45101e4f8639c51804e55b58cabc89ce3c957410b848643232bd2a0a3e481fbb9a8b1fe4c709951b4d31f260e9d7656a | C17: 2879 | D17: FE | E17: 46038 | F17: 46038.376 | G17: 900144364 | H17: UNIDOTAMOS SAS | I17: =K17-J17 -> 1794500 | J17: 340955 | K17: 2135455 | L17: COMPRAS | M17: 46041 | N17: =IFERROR(IF(-_xlfn.DAYS(E17,M17)<0,0,-_xlfn.DAYS(E17,M17)), " - ") -> 3 | O17: YENIFER PARRA | T17: 46042 | U17: NO | W17: 0 a 5
A18: Factura electrónica | B18: f70dfc90f596f0ab14b6aa306dd0ce0d120f69b31f7340622efb0b684398b49eb75833422879104ffc0888f758d2335d | C18: 2878 | D18: FE | E18: 46038 | F18: 46038.366 | G18: 900144364 | H18: UNIDOTAMOS SAS | I18: =K18-J18 -> 8747800 | J18: 1662082 | K18: 10409882 | L18: COMPRAS | M18: 46042 | N18: =IFERROR(IF(-_xlfn.DAYS(E18,M18)<0,0,-_xlfn.DAYS(E18,M18)), " - ") -> 4 | O18: YENIFER PARRA | T18: 46045 | U18: SI | W18: 0 a 5
A19: Factura electrónica | B19: 111840da2e41132c62bf77bb9fec297ed9926273075d6f7530f41ef480101143d5cc71afc01be097d6246bf703da6532 | C19: 2891 | D19: FE | E19: 46043 | F19: 46043.589 | G19: 900144364 | H19: UNIDOTAMOS SAS | I19: =K19-J19 -> 1089000 | J19: 206910 | K19: 1295910 | L19: COMPRAS | M19: 46045 | N19: =IFERROR(IF(-_xlfn.DAYS(E19,M19)<0,0,-_xlfn.DAYS(E19,M19)), " - ") -> 2 | O19: FRANCY SALAS | T19: 46048 | U19: NO | W19: 0 a 5
A20: Factura electrónica | B20: c2f630fc67f892b5818009c3cc6acab892eb98ae81845235fba3375c64e4cec5e6d3bd581c8ea69178ca7fe462770c50 | C20: 2890 | D20: FE | E20: 46043 | F20: 46043.539 | G20: 900144364 | H20: UNIDOTAMOS SAS | I20: =K20-J20 -> 332950 | J20: 63260.5 | K20: 396210.5 | L20: COMPRAS | M20: 46045 | N20: =IFERROR(IF(-_xlfn.DAYS(E20,M20)<0,0,-_xlfn.DAYS(E20,M20)), " - ") -> 2 | O20: FRANCY SALAS | T20: 46048 | U20: NO | W20: 0 a 5
A21: Factura electrónica | B21: 3b5623790c7d54546ba985f5ea24dda565744a3a8dda580b3ed671a46eb2d37d73c3bbabb89e9fd5c7698dcb18de45ec | C21: 2889 | D21: FE | E21: 46043 | F21: 46043.532 | G21: 900144364 | H21: UNIDOTAMOS SAS | I21: =K21-J21 -> 1478700 | J21: 280953 | K21: 1759653 | L21: COMPRAS | M21: 46045 | N21: =IFERROR(IF(-_xlfn.DAYS(E21,M21)<0,0,-_xlfn.DAYS(E21,M21)), " - ") -> 2 | O21: FRANCY SALAS | T21: 46048 | U21: NO | W21: 0 a 5
A22: Factura electrónica | B22: bf2b2e78d923fe2b54c7cf6316edfd75442216a5bba7de33a38cdeebcd6811477c4258105b18b958475986062dacb53b | C22: 2888 | D22: FE | E22: 46043 | F22: 46043.525 | G22: 900144364 | H22: UNIDOTAMOS SAS | I22: =K22-J22 -> 1224300 | J22: 232617 | K22: 1456917 | L22: CRUZA | M22: N/A | N22: =IFERROR(IF(-_xlfn.DAYS(E22,M22)<0,0,-_xlfn.DAYS(E22,M22)), " - ") -> -
A23: Nota de crédito electrónica | B23: afb8ced3d655ed16dc3912c045dbdfc9bafa49b4feec01121f1a76f4a4be430c83f0d9751ce8514298351a12a4590bff | C23: 222 | D23: DV | E23: 46043 | F23: 46043.528 | G23: 900144364 | H23: UNIDOTAMOS SAS | I23: =K23-J23 -> 1224300 | J23: 232617 | K23: 1456917 | L23: CRUZA | M23: N/A | N23: =IFERROR(IF(-_xlfn.DAYS(E23,M23)<0,0,-_xlfn.DAYS(E23,M23)), " - ") -> -
A24: Factura electrónica | B24: 0ae6caba569fd68845dc2b8ddffaf4cf3d9fa3d676261dd260326f2900e31a3f8dece8454a01aaa4453747e763c6677e | C24: 2894 | D24: FE | E24: 46044 | F24: 46044.473 | G24: 900144364 | H24: UNIDOTAMOS SAS | I24: =K24-J24 -> 426600 | J24: 81054 | K24: 507654 | L24: COMPRAS | M24: 46045 | N24: =IFERROR(IF(-_xlfn.DAYS(E24,M24)<0,0,-_xlfn.DAYS(E24,M24)), " - ") -> 1 | O24: FRANCY SALAS | T24: 46048 | U24: NO | W24: 0 a 5
A25: Factura electrónica | B25: a87be2aff47fa9b5810238973bd14b12eea6a93df0ede9f2f321b1283dbf3eff2db88448ed9751e77ed11f6616d2feab | C25: 2893 | D25: FE | E25: 46044 | F25: 46044.472 | G25: 900144364 | H25: UNIDOTAMOS SAS | I25: =K25-J25 -> 2001500 | J25: 380285 | K25: 2381785 | L25: COMPRAS | M25: 46045 | N25: =IFERROR(IF(-_xlfn.DAYS(E25,M25)<0,0,-_xlfn.DAYS(E25,M25)), " - ") -> 1 | O25: FRANCY SALAS | T25: 46048 | U25: NO | W25: 0 a 5
A26: Factura electrónica | B26: c91eb22e20820d032dace3e2dbf0b3a272ad893774ede531d4a82b8790d351d47de09416e111c21a8a36f6981ea8234e | C26: 130189358 | D26: BOPU | E26: 46040 | F26: 46040.63 | G26: 900092385 | H26: UNE EPM TELECOMUNICACIONES S.A | I26: =K26-J26 -> 537968.89 | J26: 102214.11 | K26: 640183 | L26: TI | M26: 46044 | N26: =IFERROR(IF(-_xlfn.DAYS(E26,M26)<0,0,-_xlfn.DAYS(E26,M26)), " - ") -> 4 | O26: JAIME GARCIA | T26: 46045 | U26: NO | W26: 0 a 5
A27: Factura electrónica | B27: 258a8c4351a08e73264804adf1c180639711b03a82c708b91da6a590ccd199c95b89118737b28fe46fdf1ce648470364 | C27: 130131606 | D27: BOPU | E27: 46040 | F27: 46040.554 | G27: 900092385 | H27: UNE EPM TELECOMUNICACIONES S.A | I27: =K27-J27 -> 277962.4 | J27: 49206.6 | K27: 327169 | L27: TI | M27: 46044 | N27: =IFERROR(IF(-_xlfn.DAYS(E27,M27)<0,0,-_xlfn.DAYS(E27,M27)), " - ") -> 4 | O27: JAIME GARCIA | T27: 46045 | U27: NO | W27: 0 a 5
A28: Factura electrónica | B28: e57ba40dfe11031a4408406ef0a534f623e6b187e457033d3503889de1a0cad413c04da18b5d45f9f25201555bd690ff | C28: 130189824 | D28: BOPU | E28: 46040 | F28: 46040.446 | G28: 900092385 | H28: UNE EPM TELECOMUNICACIONES S.A | I28: =K28-J28 -> 537968.89 | J28: 102214.11 | K28: 640183 | L28: TI | M28: 46044 | N28: =IFERROR(IF(-_xlfn.DAYS(E28,M28)<0,0,-_xlfn.DAYS(E28,M28)), " - ") -> 4 | O28: JAIME GARCIA | T28: 46045 | U28: NO | W28: 0 a 5
A29: Factura electrónica | B29: 44c33ba0bd64e4f978603945a6ad98c9620a6c7d712ba0c13f6c4b7a55d44eb811d12fb542b193fd6aac4a91ea32a8eb | C29: 130238404 | D29: BOPU | E29: 46044 | F29: 46044.627 | G29: 900092385 | H29: UNE EPM TELECOMUNICACIONES S.A | I29: =K29-J29 -> 22984.04 | J29: 4366.96 | K29: 27351 | L29: TI | M29: 46048 | N29: =IFERROR(IF(-_xlfn.DAYS(E29,M29)<0,0,-_xlfn.DAYS(E29,M29)), " - ") -> 4 | O29: JAIME GARCIA | T29: 46049 | U29: NO | W29: 0 a 5
A30: Factura electrónica | B30: 363c2a4575972f7aef623b0ac082a60a9b806f65fb5fde195212192dc233baf0c3d1303be6671326fd6121a6385b007a | C30: 6856 | D30: RGRO | E30: 46037 | F30: 46037.601 | G30: 811006418 | H30: TRULY NOLEN SOLUCIONES S.A.S | I30: =K30-J30 -> 295766 | J30: 56195.54 | K30: 351961.54 | L30: CALIDAD | M30: 46042 | N30: =IFERROR(IF(-_xlfn.DAYS(E30,M30)<0,0,-_xlfn.DAYS(E30,M30)), " - ") -> 5 | O30: YENIFER PARRA | T30: 46042 | U30: NO | W30: 0 a 5
A31: Factura electrónica | B31: 945895c2157bbc6c9c043b127ea7dad32d7ecc589cdce9bfb55c1ea8b19616f3307791c3ca70ef47c045bdb7d1b61720 | C31: 6855 | D31: RGRO | E31: 46037 | F31: 46037.596 | G31: 811006418 | H31: TRULY NOLEN SOLUCIONES S.A.S | I31: =K31-J31 -> 517045 | J31: 98238.55 | K31: 615283.55 | L31: CALIDAD | M31: 46042 | N31: =IFERROR(IF(-_xlfn.DAYS(E31,M31)<0,0,-_xlfn.DAYS(E31,M31)), " - ") -> 5 | O31: YENIFER PARRA | T31: 46042 | U31: NO | W31: 0 a 5
A32: Factura electrónica | B32: 6bcee3a69612e911bfe5cbaf9280712d902d8d10b25936c2b34afb7a62df1c4ade537ad1c7e0428c02eb176ce1b1b615 | C32: 6854 | D32: RGRO | E32: 46037 | F32: 46037.594 | G32: 811006418 | H32: TRULY NOLEN SOLUCIONES S.A.S | I32: =K32-J32 -> 130000 | J32: 24700 | K32: 154700 | L32: CALIDAD | M32: 46042 | N32: =IFERROR(IF(-_xlfn.DAYS(E32,M32)<0,0,-_xlfn.DAYS(E32,M32)), " - ") -> 5 | O32: YENIFER PARRA | T32: 46044 | U32: NO | W32: 0 a 5
A33: Factura electrónica | B33: 836d97511a2f671fcad83dc427dcc60de97ba31f1845a4eddd1023e255780c75cf78945853949eaeb5edb32065f1f872 | C33: 30884 | D33: MEDN | E33: 46042 | F33: 46042.683 | G33: 811006418 | H33: TRULY NOLEN SOLUCIONES S.A.S | I33: =K33-J33 -> 290500 | J33: 55195 | K33: 345695 | L33: CALIDAD | M33: 46045 | N33: =IFERROR(IF(-_xlfn.DAYS(E33,M33)<0,0,-_xlfn.DAYS(E33,M33)), " - ") -> 3 | O33: FRANCY SALAS | T33: 46065 | U33: NO | W33: 0 a 5
A34: Factura electrónica | B34: cc1f16ca45b90325b0de78b9cdca079cb0e9bf32dfec7e5c12e6f10ed867ede5925d2a79fe45fc6d36b19627702c03ae | C34: 7788 | D34: PERE | E34: 46042 | F34: 46042.61 | G34: 811006418 | H34: TRULY NOLEN SOLUCIONES S.A.S | I34: =K34-J34 -> 320787 | J34: 60949.53 | K34: 381736.53 | L34: CALIDAD | M34: 46045 | N34: =IFERROR(IF(-_xlfn.DAYS(E34,M34)<0,0,-_xlfn.DAYS(E34,M34)), " - ") -> 3 | O34: FRANCY SALAS | T34: 46063 | U34: NO | W34: 0 a 5
A35: Factura electrónica | B35: 295411022c206b07c5f77cf5ef8dd8304c879dfd96fa48a0436908c451dae00a96e28977079e033f4807953c972a7771 | C35: 587 | D35: TEC | E35: 46048 | F35: 46048.938 | G35: 901161036 | H35: TRANSPORTES ESPECIALES DEL CAUCA S.A.S. | I35: =K35-J35 -> 13216000 | J35: 2511040 | K35: 15727040 | L35: OPERACIONES | M35: 46057 | N35: =IFERROR(IF(-_xlfn.DAYS(E35,M35)<0,0,-_xlfn.DAYS(E35,M35)), " - ") -> 9 | O35: YENIFER PARRA | T35: 46065 | U35: SI | W35: 6 a 10
A36: Factura electrónica | B36: 636076945bf077ee9c21f01ebd30eaa98781d759d0692d1f87f5a81817855d4163a0ca34cd37c77d9229a58e9be78e30 | C36: 586 | D36: TEC | E36: 46048 | F36: 46048.929 | G36: 901161036 | H36: TRANSPORTES ESPECIALES DEL CAUCA S.A.S. | I36: =K36-J36 -> 44030000 | J36: 8365700 | K36: 52395700 | L36: OPERACIONES | M36: 46057 | N36: =IFERROR(IF(-_xlfn.DAYS(E36,M36)<0,0,-_xlfn.DAYS(E36,M36)), " - ") -> 9 | O36: YENIFER PARRA | T36: 46065 | U36: SI | W36: 6 a 10
A37: Factura electrónica | B37: 2d2325d218c892809b2bd01632a36d5870de81323f40dce15a04bdc1c1a2486246ca2366e67e648afffdc038e02d98ae | C37: 585 | D37: TEC | E37: 46048 | F37: 46048.922 | G37: 901161036 | H37: TRANSPORTES ESPECIALES DEL CAUCA S.A.S. | I37: =K37-J37 -> 905000 | J37: 171950 | K37: 1076950 | L37: CRUZA | M37: N/A | N37: =IFERROR(IF(-_xlfn.DAYS(E37,M37)<0,0,-_xlfn.DAYS(E37,M37)), " - ") -> - | O37: YENIFER PARRA
A38: Factura electrónica | B38: 855e30eb0d277a2c88f7798681807f82369b822c5e62971604179852975acb16bfd80fb71a4c8a9a54bed4b72c6e0659 | C38: 194973 | D38: FETN | E38: 46027 | F38: 46027.323 | G38: 890903229 | H38: TRANSPORTES CHACHAFRUTO S.A. | I38: =K38-J38 -> 23000 | J38: 0 | K38: 23000 | L38: CAJA MENOR | N38: =IFERROR(IF(-_xlfn.DAYS(E38,M38)<0,0,-_xlfn.DAYS(E38,M38)), " - ") -> 0
A39: Factura electrónica | B39: 6f76d7286ffecbb8c4801bdb5beb26f287fe4c9b86b4148a0ac9595d2aa3f321de2275e2ad31397334c9928eb2cfc94a | C39: 6199 | D39: TL | E39: 46029 | F39: 46029.581 | G39: 900036588 | H39: TRAMAS LITOGRAFIA SAS | I39: =K39-J39 -> 584550 | J39: 111064.5 | K39: 695614.5 | L39: COMPRAS | M39: 46030 | N39: =IFERROR(IF(-_xlfn.DAYS(E39,M39)<0,0,-_xlfn.DAYS(E39,M39)), " - ") -> 1 | O39: YENIFER PARRA | T39: 46044 | U39: NO | W39: 0 a 5
A40: Factura electrónica | B40: bcfdb983d2d4bd24acdf0484ba70176cf169980ced16224958736781b921853d9cf3ccb43b70303cc3790f933ee420d4 | C40: 6198 | D40: TL | E40: 46029 | F40: 46029.58 | G40: 900036588 | H40: TRAMAS LITOGRAFIA SAS | I40: =K40-J40 -> 33183 | J40: 6304.77 | K40: 39487.77 | L40: COMPRAS | M40: 46030 | N40: =IFERROR(IF(-_xlfn.DAYS(E40,M40)<0,0,-_xlfn.DAYS(E40,M40)), " - ") -> 1 | O40: YENIFER PARRA | T40: 46044 | U40: NO | W40: 0 a 5
A41: Nota de crédito electrónica | B41: 8da501dd806733979bde4d6976246f8edcf7317d0782ec9c481990969a64575976421dd88622287de4a7481f50212b59 | C41: 2217 | D41: NC | E41: 46029 | F41: 46029.571 | G41: 900036588 | H41: TRAMAS LITOGRAFIA SAS | I41: =K41-J41 -> 584550 | J41: 111064.5 | K41: 695614.5 | L41: CRUZA | M41: N/A | N41: =IFERROR(IF(-_xlfn.DAYS(E41,M41)<0,0,-_xlfn.DAYS(E41,M41)), " - ") -> -
A42: Nota de crédito electrónica | B42: 6a724e4eee4f3cff322dccef3c38a60d7ad2f3fe21e39792e5cef29a114962c41a6a199d6ccc94d2d08ffcbeb7c88cb8 | C42: 2216 | D42: NC | E42: 46029 | F42: 46029.57 | G42: 900036588 | H42: TRAMAS LITOGRAFIA SAS | I42: =K42-J42 -> 33183 | J42: 6304.77 | K42: 39487.77 | L42: CRUZA | M42: N/A | N42: =IFERROR(IF(-_xlfn.DAYS(E42,M42)<0,0,-_xlfn.DAYS(E42,M42)), " - ") -> -
A43: Factura electrónica | B43: 0226a098bf50529b1cd3db46239815d54f3b12615c91128661dba823f5aedcc2f178ccd1a87dafc64e847e050e16efe4 | C43: 2694 | D43: FVE | E43: 46035 | F43: 46035.495 | G43: 900667734 | H43: TORNO PARTES S.A.S | I43: =K43-J43 -> 735000 | J43: 139650 | K43: 874650 | L43: MANTENIMIENTO | M43: 46036 | N43: =IFERROR(IF(-_xlfn.DAYS(E43,M43)<0,0,-_xlfn.DAYS(E43,M43)), " - ") -> 1 | O43: YENIFER PARRA | T43: 46044 | U43: NO | W43: 0 a 5
A44: Factura electrónica | B44: 9281c73183ac30035a8d422f46673a6c6598c7aa36bdc59b88224e35980168be08e3df6528b7a5f832db4f083bf50564 | C44: 2697 | D44: FVE | E44: 46045 | F44: 46045.372 | G44: 900667734 | H44: TORNO PARTES S.A.S | I44: =K44-J44 -> 276000 | J44: 52440 | K44: 328440 | L44: MANTENIMIENTO | M44: 46048 | N44: =IFERROR(IF(-_xlfn.DAYS(E44,M44)<0,0,-_xlfn.DAYS(E44,M44)), " - ") -> 3 | O44: YENIFER PARRA | T44: 46063 | U44: NO | W44: 0 a 5
A45: Factura electrónica | B45: 4f1e34ae30f5197809e8865659d7faf9cb4276ad723bb05f2badef8a11943241786078e82836ef7f7ca5d6fc6f7d07ce | C45: 2696 | D45: FVE | E45: 46045 | F45: 46045.372 | G45: 900667734 | H45: TORNO PARTES S.A.S | I45: =K45-J45 -> 425000 | J45: 80750 | K45: 505750 | L45: MANTENIMIENTO | M45: 46048 | N45: =IFERROR(IF(-_xlfn.DAYS(E45,M45)<0,0,-_xlfn.DAYS(E45,M45)), " - ") -> 3 | O45: YENIFER PARRA | T45: 46063 | U45: NO | W45: 0 a 5
A46: Factura electrónica | B46: 9ddaab4bdbcc6537f7960d2ab2404bcd144dc155cb27672ead93a95189c5a4f69a0757141ea6cb8d3cf850c0785aeff2 | C46: 226919 | D46: FE | E46: 46028 | F46: 46028.399 | G46: 890937070 | H46: TIEMPOS S.A.S. | I46: =K46-J46 -> 9595380 | J46: 182312 | K46: 9777692 | L46: NOMINA | M46: 46029 | N46: =IFERROR(IF(-_xlfn.DAYS(E46,M46)<0,0,-_xlfn.DAYS(E46,M46)), " - ") -> 1 | O46: MAURICIO ARBOOLEDA | T46: 46036 | U46: NO | W46: 0 a 5
A47: Nota de crédito electrónica | B47: e90e7c75ea22d343336d66618be3e4956c2fb205e5a3f8420cbf547d03fb552f02fd3ac0c9d5180ad1b0e407fd6a328c | C47: 13399 | D47: NCE | E47: 46028 | F47: 46028.421 | G47: 890937070 | H47: TIEMPOS S.A.S. | I47: =K47-J47 -> 50772 | J47: 965 | K47: 51737 | L47: NOMINA | M47: 46029 | N47: =IFERROR(IF(-_xlfn.DAYS(E47,M47)<0,0,-_xlfn.DAYS(E47,M47)), " - ") -> 1 | O47: MAURICIO ARBOOLEDA | T47: 46035 | U47: NO | W47: 0 a 5
A48: Factura electrónica | B48: 49983aa1785121cff2f66ce2ee87761cb96f444f0e2d7d69dbc67e9bf2573720c7d06a46048661d0047d836c40bdffff | C48: 226987 | D48: FE | E48: 46036 | F48: 46036.353 | G48: 890937070 | H48: TIEMPOS S.A.S. | I48: =K48-J48 -> 725781 | J48: 13790 | K48: 739571 | L48: NOMINA | M48: 46045 | N48: =IFERROR(IF(-_xlfn.DAYS(E48,M48)<0,0,-_xlfn.DAYS(E48,M48)), " - ") -> 9 | T48: 46049 | U48: NO | W48: 6 a 10
A49: Factura electrónica | B49: ac63787cfbff46a4afda2c452ad2260e3b6a3c92a4c9b0033e5d9650639d94dbc34c26a80b58b490300bb203832faa4e | C49: 227226 | D49: FE | E49: 46042 | F49: 46042.648 | G49: 890937070 | H49: TIEMPOS S.A.S. | I49: =K49-J49 -> 4701899 | J49: 89336 | K49: 4791235 | L49: NOMINA | M49: 46045 | N49: =IFERROR(IF(-_xlfn.DAYS(E49,M49)<0,0,-_xlfn.DAYS(E49,M49)), " - ") -> 3 | O49: MAURICIO ARBOLEDA | T49: 46049 | U49: NO | W49: 0 a 5
A50: Nota de crédito electrónica | B50: b7325f4733077dee87ff2241ea8d8399fac14ad2437cabf41f73cd1a7c9678bdcfa460f3e4c7d4be83795b9920078a83 | C50: 13463 | D50: NCE | E50: 46042 | F50: 46042.663 | G50: 890937070 | H50: TIEMPOS S.A.S. | I50: =K50-J50 -> 124898 | J50: 2373 | K50: 127271 | L50: NOMINA | M50: 46063 | N50: =IFERROR(IF(-_xlfn.DAYS(E50,M50)<0,0,-_xlfn.DAYS(E50,M50)), " - ") -> 21 | O50: Sandra Paniagua | T50: 46065 | U50: NO
A51: Factura electrónica | B51: 317853a5047b2518d9297f3f91cda3f79f3a92e3bde43e557a125158b39c7dcbf9a00648430e13d0e4f75d360f054094 | C51: 1008835 | D51: PABF | E51: 46027 | F51: 46027.627 | G51: 860016640 | H51: TCC S.A.S. | I51: =K51-J51 -> 3023165 | J51: 0 | K51: 3023165 | L51: COMPRAS | M51: 46028 | N51: =IFERROR(IF(-_xlfn.DAYS(E51,M51)<0,0,-_xlfn.DAYS(E51,M51)), " - ") -> 1 | O51: YENIFER PARRA | T51: 46037 | U51: NO | W51: 0 a 5
A52: Factura electrónica | B52: 6a8bb8944c0d3c9c8005f1a2a5ffe3b3c005f05207e61be3d6da6dc9bb2716b3070ddba701f5c23f621bcc68fe1da909 | C52: 1009436 | D52: PABF | E52: 46036 | F52: 46036.496 | G52: 860016640 | H52: TCC S.A.S. | I52: =K52-J52 -> 3182256 | J52: 0 | K52: 3182256 | L52: COMPRAS | M52: 46037 | N52: =IFERROR(IF(-_xlfn.DAYS(E52,M52)<0,0,-_xlfn.DAYS(E52,M52)), " - ") -> 1 | O52: YENIFER PARRA | T52: 46041 | U52: NO | W52: 0 a 5
A53: Factura electrónica | B53: a0a751e81619bfeaf23ffd700c39f0cb8cd7782a6120907bbbeebfdde25156c7df08bbf836ef396e1928cade9eda9870 | C53: 1009515 | D53: PABF | E53: 46037 | F53: 46037.373 | G53: 860016640 | H53: TCC S.A.S. | I53: =K53-J53 -> 21391 | J53: 0 | K53: 21391 | L53: COMPRAS | M53: 46042 | N53: =IFERROR(IF(-_xlfn.DAYS(E53,M53)<0,0,-_xlfn.DAYS(E53,M53)), " - ") -> 5 | O53: YENIFER PARRA | T53: 46042 | U53: NO | W53: 0 a 5
A54: Factura electrónica | B54: 74b964b75f1954e19222cc441c3457a1a1f0f714415bf7dd0b70f6d516d2b1f4566e8809057ce906d1dfcc9f691d5182 | C54: 1009776 | D54: PABF | E54: 46041 | F54: 46041.739 | G54: 860016640 | H54: TCC S.A.S. | I54: =K54-J54 -> 848026 | J54: 0 | K54: 848026 | L54: COMPRAS | M54: 46043 | N54: =IFERROR(IF(-_xlfn.DAYS(E54,M54)<0,0,-_xlfn.DAYS(E54,M54)), " - ") -> 2 | O54: FRANCY SALAS | T54: 46044 | U54: NO | W54: 0 a 5
A55: Factura electrónica | B55: 5848d7411523d4bf15b84d62fb19e5fa4ad909a15487f80c804807db518c18125012784f684ff375bc883cf6a277cccf | C55: 1039 | D55: MD | E55: 46043 | F55: 46043.393 | G55: 29844067 | H55: TAMAYO LOPEZ GLORIA ISABEL | I55: =K55-J55 -> 18000 | J55: 0 | K55: 18000 | L55: CAJA MENOR | N55: =IFERROR(IF(-_xlfn.DAYS(E55,M55)<0,0,-_xlfn.DAYS(E55,M55)), " - ") -> 0
A56: Factura electrónica | B56: 7ee8f358f66f19e0aea0a6a3720fa1ba1bce4b433eb0520bb5d54427b634142e196b67f48d869ddc10bc371edecd4980 | C56: 13725 | D56: FEPF | E56: 46028 | F56: 46028.323 | G56: 71951636 | H56: TABORDA GONZALEZ JESUS ANIBAL | I56: =K56-J56 -> 30336.13 | J56: 5763.87 | K56: 36100 | L56: CAJA MENOR | N56: =IFERROR(IF(-_xlfn.DAYS(E56,M56)<0,0,-_xlfn.DAYS(E56,M56)), " - ") -> 0
A57: Factura electrónica | B57: d6d4271fbb2fdc25b59ab010a894e997b365578f5338c094d9039061c8e8158d7e324db90633465c247bfef59694392f | C57: 13805 | D57: FEPF | E57: 46045 | F57: 46045.314 | G57: 71951636 | H57: TABORDA GONZALEZ JESUS ANIBAL | I57: =K57-J57 -> 26050.42 | J57: 4949.58 | K57: 31000 | L57: CAJA MENOR | N57: =IFERROR(IF(-_xlfn.DAYS(E57,M57)<0,0,-_xlfn.DAYS(E57,M57)), " - ") -> 0
A58: Factura electrónica | B58: 4fde243d0b6ca68d592bf3b6ae040bc2ebd293a3921e39b14faf5ef950201593e9a3fc063880cbaf67aa213eeeb2f15b | C58: 1251 | D58: SM | E58: 46027 | F58: 46027.662 | G58: 901561580 | H58: SUMINISTRO MATERIALES Y DOTACIONES SUMADO S.A.S | I58: =K58-J58 -> 4627494 | J58: 879223.86 | K58: 5506717.9 | L58: MANTENIMIENTO | M58: 46029 | N58: =IFERROR(IF(-_xlfn.DAYS(E58,M58)<0,0,-_xlfn.DAYS(E58,M58)), " - ") -> 2 | O58: YENIFER PARRA | T58: 46044 | U58: NO | W58: 0 a 5
A59: Factura electrónica | B59: b85ae31cbc3c3e39a809503a55c4df10423067348eb060f437d5a03730296fe708ac8c01b8cefec9e778e31779502060 | C59: 1267 | D59: SM | E59: 46043 | F59: 46043.495 | G59: 901561580 | H59: SUMINISTRO MATERIALES Y DOTACIONES SUMADO S.A.S | I59: =K59-J59 -> 240000 | J59: 45600 | K59: 285600 | L59: MANTENIMIENTO | M59: 46049 | N59: =IFERROR(IF(-_xlfn.DAYS(E59,M59)<0,0,-_xlfn.DAYS(E59,M59)), " - ") -> 6 | O59: YENIFER PARRA | T59: 46051 | U59: NO | W59: 6 a 10
A60: Factura electrónica | B60: 16f0b8acad4d8ec1dfce9b7aaf26cff6df39ebd6ad283e180660103ebf201b378bcf0cbc899095da90f3169cf07e5b1a | C60: 1274 | D60: SM | E60: 46045 | F60: 46045.622 | G60: 901561580 | H60: SUMINISTRO MATERIALES Y DOTACIONES SUMADO S.A.S | I60: =K60-J60 -> 3935544.1 | J60: 747753.37 | K60: 4683297.4 | L60: MANTENIMIENTO | M60: 46049 | N60: =IFERROR(IF(-_xlfn.DAYS(E60,M60)<0,0,-_xlfn.DAYS(E60,M60)), " - ") -> 4 | O60: YENIFER PARRA | T60: 46051 | U60: NO | W60: 0 a 5
A61: Factura electrónica | B61: dc07b2a86ed84e7f21aa90c57559a212a59116237e57dd1f752fee1776249b9b28e3c69068c5755ca2d46d1780ac6853 | C61: 1271 | D61: SM | E61: 46045 | F61: 46045.606 | G61: 901561580 | H61: SUMINISTRO MATERIALES Y DOTACIONES SUMADO S.A.S | I61: =K61-J61 -> 284999 | J61: 54149.81 | K61: 339148.81 | L61: MANTENIMIENTO | M61: 46049 | N61: =IFERROR(IF(-_xlfn.DAYS(E61,M61)<0,0,-_xlfn.DAYS(E61,M61)), " - ") -> 4 | O61: YENIFER PARRA | T61: 46051 | U61: NO | W61: 0 a 5
A62: Factura electrónica | B62: ff2ddaa22d5d0d8d47b5e94800d16c6713be8f83074b99e5749054abc0996ec198c1b17fc38ae0a97a2da537bea42453 | C62: 1272 | D62: SM | E62: 46045 | F62: 46045.615 | G62: 901561580 | H62: SUMINISTRO MATERIALES Y DOTACIONES SUMADO S.A.S | I62: =K62-J62 -> 526152 | J62: 99968.88 | K62: 626120.88 | L62: MANTENIMIENTO | M62: 46049 | N62: =IFERROR(IF(-_xlfn.DAYS(E62,M62)<0,0,-_xlfn.DAYS(E62,M62)), " - ") -> 4 | O62: YENIFER PARRA | T62: 46051 | U62: NO | W62: 0 a 5
A63: Factura electrónica | B63: 25c2c2b08c1f2e497798c082b44d400dbcc2737b70725738fd53d0b67591269691a14e93f07628b4e64d8ecfbeafda7d | C63: 1273 | D63: SM | E63: 46045 | F63: 46045.616 | G63: 901561580 | H63: SUMINISTRO MATERIALES Y DOTACIONES SUMADO S.A.S | I63: =K63-J63 -> 120000 | J63: 22800 | K63: 142800 | L63: MANTENIMIENTO | M63: 46049 | N63: =IFERROR(IF(-_xlfn.DAYS(E63,M63)<0,0,-_xlfn.DAYS(E63,M63)), " - ") -> 4 | O63: YENIFER PARRA | T63: 46051 | U63: NO | W63: 0 a 5
A64: Factura electrónica | B64: 805ed1715ce29da77f76103bb881483d101febfedb3dfd95043170e98b6452d053b1dd70004c1f688a86c618413c09c9 | C64: 562702 | D64: AH | E64: 46028 | F64: 46028.311 | G64: 890800788 | H64: SUMATEC S.A.S BIC | I64: =K64-J64 -> 69000 | J64: 13110 | K64: 82110 | L64: COMPRAS | M64: 46028 | N64: =IFERROR(IF(-_xlfn.DAYS(E64,M64)<0,0,-_xlfn.DAYS(E64,M64)), " - ") -> 0 | O64: YENIFER PARRA | T64: 46037 | U64: NO | W64: 0 a 5
A65: Factura electrónica | B65: 1ec6b1eafd783d3419355d76b8bcbaece27fd06d3b846d2940e6ed4d1984ee624d6175925a16dd3f81224277cb8483d0 | C65: 562942 | D65: AH | E65: 46036 | F65: 46036.455 | G65: 890800788 | H65: SUMATEC S.A.S BIC | I65: =K65-J65 -> 166095 | J65: 31558 | K65: 197653 | L65: COMPRAS | M65: 46042 | N65: =IFERROR(IF(-_xlfn.DAYS(E65,M65)<0,0,-_xlfn.DAYS(E65,M65)), " - ") -> 6 | O65: YENIFER PARRA | T65: 46042 | U65: NO | W65: 6 a 10
A66: Factura electrónica | B66: ec6264ad5ba8f2c19843740a3ca9042eb5064d14d5b35d0261232e8668f6ac54e4319ce9b6879f95cb2e7980999ec150 | C66: 562985 | D66: AH | E66: 46037 | F66: 46037.472 | G66: 890800788 | H66: SUMATEC S.A.S BIC | I66: =K66-J66 -> 218340 | J66: 41485 | K66: 259825 | L66: COMPRAS | M66: 46042 | N66: =IFERROR(IF(-_xlfn.DAYS(E66,M66)<0,0,-_xlfn.DAYS(E66,M66)), " - ") -> 5 | O66: YENIFER PARRA | T66: 46042 | U66: NO | W66: 0 a 5
A67: Factura electrónica | B67: 495ccef5ab0e5f36d670f231d58476f447a0d387637ed4e19183b8e4449c906c7333b90ebcf2298979efff27db7fa870 | C67: 562986 | D67: AH | E67: 46037 | F67: 46037.461 | G67: 890800788 | H67: SUMATEC S.A.S BIC | I67: =K67-J67 -> 494340 | J67: 93925 | K67: 588265 | L67: COMPRAS | M67: 46050 | N67: =IFERROR(IF(-_xlfn.DAYS(E67,M67)<0,0,-_xlfn.DAYS(E67,M67)), " - ") -> 13 | O67: YENIFER PARRA | T67: 46065 | U67: NO | W67: Más de 10
A68: Factura electrónica | B68: f0789f0e887f57ad6cadd98804ed3ffa09a206268f1cee95f76e48fc234d930c5b67f4dd2b258739cc4f2fe317cf09a1 | C68: 563267 | D68: AH | E68: 46043 | F68: 46043.303 | G68: 890800788 | H68: SUMATEC S.A.S BIC | I68: =K68-J68 -> 446964 | J68: 84923 | K68: 531887 | L68: COMPRAS | M68: 46048 | N68: =IFERROR(IF(-_xlfn.DAYS(E68,M68)<0,0,-_xlfn.DAYS(E68,M68)), " - ") -> 5 | O68: YENIFER PARRA | T68: 46065 | U68: NO | W68: 0 a 5
A69: Factura electrónica | B69: cf942b13d681fadf9c45cea1e98c7f340a8bf1063c2b0518d992df4b5bd79ceed91db633e43cf5a736151252006344c1 | C69: 563266 | D69: AH | E69: 46043 | F69: 46043.301 | G69: 890800788 | H69: SUMATEC S.A.S BIC | I69: =K69-J69 -> 374660 | J69: 71185 | K69: 445845 | L69: COMPRAS | M69: 46044 | N69: =IFERROR(IF(-_xlfn.DAYS(E69,M69)<0,0,-_xlfn.DAYS(E69,M69)), " - ") -> 1 | O69: FRANCY SALAS | T69: 46063 | U69: NO | W69: 0 a 5
... A84: Factura electrónica | B84: 9f9d5aeb205196e37c234bfe19697bcde78fd0b1645602a0363793846f886e550805f9ecad0d6f68e7ab6ef60ad7b3eb | C84: 376 | D84: MD | E84: 46026 | F84: 46026.765 | G84: 900484392 | H84: Sigfrido SAS | I84: =K84-J84 -> 27859250 | J84: 5293257.5 | K84: 33152508 | L84: CONTABILIDAD | M84: 46027 | N84: =IFERROR(IF(-_xlfn.DAYS(E84,M84)<0,0,-_xlfn.DAYS(E84,M84)), " - ") -> 1 | O84: ANGELA FRANCO | T84: 46028 | U84: SI | W84: 0 a 5
A85: Factura electrónica | B85: ec69536c885d39d1eab15406f657376a25df1269f9a8f3d8e0356fdddc76e8d35b7e9f022bc1ca0ebb2fc78bc8daab0c | C85: 3629 | D85: FE | E85: 46038 | F85: 46038.628 | G85: 900667384 | H85: SGR ASOCIADOS SAS | I85: =K85-J85 -> 1750905 | J85: 332671.95 | K85: 2083576.9 | L85: GESTION HUMANA | M85: 46041 | N85: =IFERROR(IF(-_xlfn.DAYS(E85,M85)<0,0,-_xlfn.DAYS(E85,M85)), " - ") -> 3 | T85: 46044 | U85: NO | W85: 0 a 5
A86: Factura electrónica | B86: 65e2ebf9c29ad3ac559bd09c90e241a43ddba3ede59ff48ffe9ff7e8dff82e48b017c815bbfb2958060b642561c8f824 | C86: 11821 | D86: FACT | E86: 46024 | F86: 46024.685 | G86: 800192047 | H86: SERVIRUTAS SAS | I86: =K86-J86 -> 850000 | J86: 0 | K86: 850000 | L86: COMPRAS | M86: 46037 | N86: =IFERROR(IF(-_xlfn.DAYS(E86,M86)<0,0,-_xlfn.DAYS(E86,M86)), " - ") -> 13 | O86: YENIFER PARRA | T86: 46030 | U86: NO | W86: Más de 10
A87: Factura electrónica | B87: cc8f767c5542712e3920894882718c829dca516f46ca34c8f3f8b8347d773d049046da45089f411d597b6102bb07cc00 | C87: 11820 | D87: FACT | E87: 46024 | F87: 46024.683 | G87: 800192047 | H87: SERVIRUTAS SAS | I87: =K87-J87 -> 1300000 | J87: 0 | K87: 1300000 | L87: COMPRAS | M87: 46037 | N87: =IFERROR(IF(-_xlfn.DAYS(E87,M87)<0,0,-_xlfn.DAYS(E87,M87)), " - ") -> 13 | O87: YENIFER PARRA | T87: 46030 | U87: NO | W87: Más de 10
A88: Factura electrónica | B88: 6ea179dd9dd6ad59a02a1a35a51ab2b084f7cdcdde78cc70886f9ebb28f18763b1ab8878c06a4957535e55be895e83ad | C88: 22606 | D88: F4 | E88: 46045 | F88: 46045.391 | G88: 800079603 | H88: SERVICIOS DE ALIMENTACION NP S.A.S. | I88: =K88-J88 -> 79248 | J88: 15057.12 | K88: 94305.12 | L88: OPERACIONES | M88: 46057 | N88: =IFERROR(IF(-_xlfn.DAYS(E88,M88)<0,0,-_xlfn.DAYS(E88,M88)), " - ") -> 12 | O88: YENIFER PARRA | T88: 46058 | U88: NO | W88: Más de 10
A89: Factura electrónica | B89: bc8a21d48eade9e5f9bd5b24cd4114161ab02302ee02851fa657479b0bb37d819644e5929293d8e781299768e2bd5a84 | C89: 22652 | D89: F4 | E89: 46050 | F89: 46050.71 | G89: 800079603 | H89: SERVICIOS DE ALIMENTACION NP S.A.S. | I89: =K89-J89 -> 101880 | J89: 19357.2 | K89: 121237.2 | L89: OPERACIONES | M89: 46057 | N89: =IFERROR(IF(-_xlfn.DAYS(E89,M89)<0,0,-_xlfn.DAYS(E89,M89)), " - ") -> 7 | O89: YENIFER PARRA | T89: 46058 | U89: NO | W89: 6 a 10
A90: Factura electrónica | B90: 3bf5d8c7ea7f37f94dd46099bca5535e79d809e88ff29f3ba5d8f50c783d807450eda6988517ce77c1d37dffb9f9838c | C90: 1312 | D90: E | E90: 46050 | F90: 46050.361 | G90: 900949189 | H90: SERVI ESPECIALES GACHANCIPA Y TURISMO SAS | I90: =K90-J90 -> 12713720 | J90: 0 | K90: 12713720 | L90: OPERACIONES | M90: 46050 | N90: =IFERROR(IF(-_xlfn.DAYS(E90,M90)<0,0,-_xlfn.DAYS(E90,M90)), " - ") -> 0 | O90: YENIFER PARRA | T90: 46056 | U90: NO | W90: 0 a 5
A91: Factura electrónica | B91: 0e518cb9bad6063067cf48b4ddc3acb90f6d4a2fa59cd1be329924e0adfa9e638fb0323e3e8da6677802d3f903129bd8 | C91: 14094708 | D91: 1040 | E91: 46052 | F91: 46052.169 | G91: 890903407 | H91: SEGUROS GENERALES SURAMERICANA S.A | I91: =K91-J91 -> 3463087 | J91: 657986.53 | K91: 4121073.5 | L91: FINANCIERA | M91: 46062 | N91: =IFERROR(IF(-_xlfn.DAYS(E91,M91)<0,0,-_xlfn.DAYS(E91,M91)), " - ") -> 10 | O91: JAIME ARISMENDI | T91: 46062 | U91: NO | W91: 6 a 10
A92: Factura electrónica | B92: d34baf94ce1e0e60d9018e680f6b1794d38ed6df72f72bd46baba67cf7e955d9690eda0ab6bb26fecb6bdb525e6ac2f3 | C92: 1207940 | D92: 2091 | E92: 46023 | F92: 46023.577 | G92: 890903790 | H92: SEGUROS DE VIDA SURAMERICANA S.A | I92: =K92-J92 -> 1643587 | J92: 82179.35 | K92: 1725766.4 | L92: GESTION HUMANA | M92: 46037 | N92: =IFERROR(IF(-_xlfn.DAYS(E92,M92)<0,0,-_xlfn.DAYS(E92,M92)), " - ") -> 14 | O92: YENIFER PARRA | T92: 46042 | U92: NO | W92: Más de 10
A93: Factura electrónica | B93: 04d9b7f8d212e9f75afb79da1f5c8426b0baea281412984142daa7afbae7f72080c74bdeb6922be668418b046d020ec8 | C93: 3383981 | D93: 2083 | E93: 46047 | F93: 46047.502 | G93: 890903790 | H93: SEGUROS DE VIDA SURAMERICANA S.A | I93: =K93-J93 -> 83866 | J93: 0 | K93: 83866 | L93: GESTION HUMANA | M93: 46055 | N93: =IFERROR(IF(-_xlfn.DAYS(E93,M93)<0,0,-_xlfn.DAYS(E93,M93)), " - ") -> 8 | O93: VALERIA GUEVARA | T93: 46058 | U93: NO | W93: 6 a 10
A94: Factura electrónica | B94: 3ffeb9c058ad18523697f5e24acfd945c02da53d064b8876f42eb69fb370bb8bd37805e5c649f6ae26e532e9b615b0f3 | C94: 3386959 | D94: 2083 | E94: 46049 | F94: 46049.741 | G94: 890903790 | H94: SEGUROS DE VIDA SURAMERICANA S.A | I94: =K94-J94 -> 7832626 | J94: 0 | K94: 7832626 | L94: GESTION HUMANA | M94: 46052 | N94: =IFERROR(IF(-_xlfn.DAYS(E94,M94)<0,0,-_xlfn.DAYS(E94,M94)), " - ") -> 3 | O94: VALERIA GUEVARA | T94: 46058 | U94: NO | W94: 0 a 5
A95: Factura electrónica | B95: f94e9634014b2fae9e1f2a2f089b37bbc2e0658d647647291acea0b426dde23d8f32a4a06ae3b9339cad23c108388556 | C95: 91096 | D95: PEP2 | E95: 46025 | F95: 46025.661 | G95: 900443098 | H95: SAUL ZULUAGA SAS | I95: =K95-J95 -> 150210.08 | J95: 28539.92 | K95: 178750 | L95: CAJA MENOR | N95: =IFERROR(IF(-_xlfn.DAYS(E95,M95)<0,0,-_xlfn.DAYS(E95,M95)), " - ") -> 0
A96: Factura electrónica | B96: f8b2e05881710c91dadcc7923ae8f4f2bc725e2a42129d48f0119ff192c61523aa8c457c700bf951eeec92868268bbe6 | C96: 11792 | D96: FV | E96: 46043 | F96: 46043.569 | G96: 1036929757 | H96: SANDRA MILENA MORALES OSPINA | I96: =K96-J96 -> 44000 | J96: 0 | K96: 44000 | L96: CAJA MENOR | N96: =IFERROR(IF(-_xlfn.DAYS(E96,M96)<0,0,-_xlfn.DAYS(E96,M96)), " - ") -> 0
A97: Factura electrónica | B97: ac45f422b19aad2d1431791448e711f2011649f711525c8b26ca361364e4e128512d657ebda5ae9e119259074a127c77 | C97: 11816 | D97: FV | E97: 46048 | F97: 46048.567 | G97: 1036929757 | H97: SANDRA MILENA MORALES OSPINA | I97: =K97-J97 -> 19000 | J97: 0 | K97: 19000 | L97: CAJA MENOR | N97: =IFERROR(IF(-_xlfn.DAYS(E97,M97)<0,0,-_xlfn.DAYS(E97,M97)), " - ") -> 0
A98: Factura electrónica | B98: 734f05c622c4842ceaa28ff69c1d47448baaea5e2637c21bfad87ab32223aed9fe24a83be94515a98fcf33c6550fd6e7 | C98: 11840 | D98: FV | E98: 46051 | F98: 46051.581 | G98: 1036929757 | H98: SANDRA MILENA MORALES OSPINA | I98: =K98-J98 -> 19000 | J98: 0 | K98: 19000 | L98: CAJA MENOR | N98: =IFERROR(IF(-_xlfn.DAYS(E98,M98)<0,0,-_xlfn.DAYS(E98,M98)), " - ") -> 0
A99: Factura electrónica | B99: f7b096fe737cb2aee05fbebb48e9663fee9d53346285487477cef3554cf9390a8b37fcaea5e04b4ec238fda7ae3c0996 | C99: 11839 | D99: FV | E99: 46051 | F99: 46051.581 | G99: 1036929757 | H99: SANDRA MILENA MORALES OSPINA | I99: =K99-J99 -> 38000 | J99: 0 | K99: 38000 | L99: CAJA MENOR | N99: =IFERROR(IF(-_xlfn.DAYS(E99,M99)<0,0,-_xlfn.DAYS(E99,M99)), " - ") -> 0
A100: Factura electrónica | B100: 26d44f9d370b38645d7641af9ba09aecd25967de70b54ca2161c64dd07e41dc3bb8d920b467d9572b922d124c0ed0d13 | C100: 11715 | D100: FV | E100: 46027 | F100: 46027.588 | G100: 1036929757 | H100: SANDRA MILENA MORALES OSPINA | I100: =K100-J100 -> 44000 | J100: 0 | K100: 44000 | L100: CAJA MENOR | N100: =IFERROR(IF(-_xlfn.DAYS(E100,M100)<0,0,-_xlfn.DAYS(E100,M100)), " - ") -> 0
A101: Factura electrónica | B101: b1efae41bbd63439a3057dda077e5f848b8c5efbf8c6778b5b6187c487afe09100ae3abee5fc13c3e0d776b86e68cd87 | C101: 11752 | D101: FV | E101: 46036 | F101: 46036.585 | G101: 1036929757 | H101: SANDRA MILENA MORALES OSPINA | I101: =K101-J101 -> 19000 | J101: 0 | K101: 19000 | L101: CAJA MENOR | N101: =IFERROR(IF(-_xlfn.DAYS(E101,M101)<0,0,-_xlfn.DAYS(E101,M101)), " - ") -> 0
A102: Factura electrónica | B102: 6c4665fedfc31fde9c123800bacbbe4d6b11981a7707554c3bc8f8e0789f819375405fa93bb90a189c3e12b37620954c | C102: 41188 | D102: FESA | E102: 46029 | F102: 46029.711 | G102: 890938952 | H102: SALAMANCA ALIMENTACION INDUSTRIAL S.A.S. | I102: =K102-J102 -> 13016250 | J102: 2473087.5 | K102: 15489338 | L102: OPERACIONES | M102: 46035 | N102: =IFERROR(IF(-_xlfn.DAYS(E102,M102)<0,0,-_xlfn.DAYS(E102,M102)), " - ") -> 6 | O102: FRANCY SALAS | T102: 46036 | U102: NO | W102: 6 a 10
A103: Factura electrónica | B103: afa3108c565c567100dd5c4b037b06363be7d5623b65a89ad891a064058eb97ea6632d3a4f03301412212782dfaa3c19 | C103: 41217 | D103: FESA | E103: 46031 | F103: 46031.628 | G103: 890938952 | H103: SALAMANCA ALIMENTACION INDUSTRIAL S.A.S. | I103: =K103-J103 -> 355500 | J103: 67545 | K103: 423045 | L103: OPERACIONES | M103: 46035 | N103: =IFERROR(IF(-_xlfn.DAYS(E103,M103)<0,0,-_xlfn.DAYS(E103,M103)), " - ") -> 4 | O103: CARLOS TABARES | T103: 46036 | U103: NO | W103: 0 a 5
A104: Factura electrónica | B104: 0992b1481508bbc6b47457e3cc7dd0127f4e3d1134603565efe2d568c60243543ba23129c33f34cb6bbc353e583566c4 | C104: 41216 | D104: FESA | E104: 46031 | F104: 46031.628 | G104: 890938952 | H104: SALAMANCA ALIMENTACION INDUSTRIAL S.A.S. | I104: =K104-J104 -> 355500 | J104: 67545 | K104: 423045 | L104: OPERACIONES | M104: 46035 | N104: =IFERROR(IF(-_xlfn.DAYS(E104,M104)<0,0,-_xlfn.DAYS(E104,M104)), " - ") -> 4 | O104: CARLOS TABARES | T104: 46036 | U104: NO | W104: 0 a 5
A105: Factura electrónica | B105: eb4c6cdc5964e313869faeff71136b75a2198fbe613878e15bc408dc0d4a0a68eb267330e02bdb23616770430368060c | C105: 41452 | D105: FESA | E105: 46050 | F105: 46050.378 | G105: 890938952 | H105: SALAMANCA ALIMENTACION INDUSTRIAL S.A.S. | I105: =K105-J105 -> 355500 | J105: 67545 | K105: 423045 | L105: OPERACIONES | M105: 46056 | N105: =IFERROR(IF(-_xlfn.DAYS(E105,M105)<0,0,-_xlfn.DAYS(E105,M105)), " - ") -> 6 | O105: YENIFER PARRA | T105: 46058 | U105: NO | W105: 6 a 10
A106: Factura electrónica | B106: 9024c5b9c6c3d90506d3421f5e1afe5d5394e82ad990905f9874f71a8a71c0cdbd82cff9b6e2fce1bc4522127f3ccdd7 | C106: 105 | D106: FEPR | E106: 46048 | F106: 46048.868 | G106: 4179102 | H106: ROJAS RINCON PEDRO | I106: =K106-J106 -> 16362000 | J106: 3108780 | K106: 19470780 | L106: OPERACIONES | M106: 46050 | N106: =IFERROR(IF(-_xlfn.DAYS(E106,M106)<0,0,-_xlfn.DAYS(E106,M106)), " - ") -> 2 | O106: YENIFER PARRA | T106: 46057 | U106: SI | W106: 0 a 5
A107: Factura electrónica | B107: 194c7373fb40685d6ed80b32a52bc4c1365388bb20d830b989d25dc1053d9cedd7495e96a95b00712bbcc90f046a3dc8 | C107: 3472 | D107: RIND | E107: 46023 | F107: 46023.156 | G107: 901609691 | H107: RINDEGASTOS COLOMBIA S.A.S. | I107: =K107-J107 -> 696000 | J107: 132240 | K107: 828240 | L107: CONTABILIDAD | M107: 46037 | N107: =IFERROR(IF(-_xlfn.DAYS(E107,M107)<0,0,-_xlfn.DAYS(E107,M107)), " - ") -> 14 | O107: ANGELA FRANCO | T107: 46028 | U107: SI | W107: Más de 10
A108: Factura electrónica | B108: c0ef330af18a84666380653c43f28106d99f8208a2b8d14833ceff4ca5153e60aef96af84297b7e9b20277586423f56f | C108: 8119 | D108: POSM | E108: 46029 | F108: 46029.636 | G108: 901793615 | H108: RESTAURANTE EL MANANTIAL HERNAN GARCIA S.A.S. | I108: =K108-J108 -> 50000 | J108: 0 | K108: 50000 | L108: CAJA MENOR | N108: =IFERROR(IF(-_xlfn.DAYS(E108,M108)<0,0,-_xlfn.DAYS(E108,M108)), " - ") -> 0
A109: Factura electrónica | B109: 00bec9158c2fb29bddf79cc02e124742841901bd4b4b1b252df886e74850356fa1bdcccb7ffd7172866820948e0d05b2 | C109: 631948 | D109: BG | E109: 46032 | F109: 46032.348 | G109: 800192105 | H109: RECORDAR PREVISION EXEQUIAL TOTAL S. A.S | I109: =K109-J109 -> 1095800 | J109: 0 | K109: 1095800 | L109: NOMINA | M109: 46048 | N109: =IFERROR(IF(-_xlfn.DAYS(E109,M109)<0,0,-_xlfn.DAYS(E109,M109)), " - ") -> 16 | T109: 46048 | U109: NO | W109: Más de 10
A110: Factura electrónica | B110: 5b1c9d8483bfcbdd90730678fc9c23fcb9ea92ab667ae8a1a4f52cb5e4f3726481aa2a35f4bb7336d2a242d8121fb1fd | C110: 69855990 | D110: SFEE | E110: 46023 | F110: 46023.087 | G110: 900843898 | H110: RAPPI S.A.S | I110: =K110-J110 -> 9453.77 | J110: 1796.23 | K110: 11250 | L110: CAJA MENOR | N110: =IFERROR(IF(-_xlfn.DAYS(E110,M110)<0,0,-_xlfn.DAYS(E110,M110)), " - ") -> 0 | O110: YENIFER PARRA | W110: Más de 10
A111: Factura electrónica | B111: 1fa3dd2916332ddd1cc950207759dce016b23fb2b20869c0b6c4407c15d924325cb9862c696f6dc363677b3ccaedff2c | C111: 9006615 | D111: SPRM | E111: 46026 | F111: 46026.394 | G111: 900843898 | H111: RAPPI S.A.S | I111: =K111-J111 -> 25126.05 | J111: 4773.95 | K111: 29900 | L111: CAJA MENOR | N111: =IFERROR(IF(-_xlfn.DAYS(E111,M111)<0,0,-_xlfn.DAYS(E111,M111)), " - ") -> 0
A112: Factura electrónica | B112: 509596324b3a3482a988a22acadbce2a0413735d157ba6cf317cd796fc403938070009cea79346cc08030039f7b70050 | C112: 72184932 | D112: SFEE | E112: 46044 | F112: 46044.126 | G112: 900843898 | H112: RAPPI S.A.S | I112: =K112-J112 -> 28067.24 | J112: 5332.76 | K112: 33400 | L112: CAJA MENOR | N112: =IFERROR(IF(-_xlfn.DAYS(E112,M112)<0,0,-_xlfn.DAYS(E112,M112)), " - ") -> 0
A113: Factura electrónica | B113: 4f96d554f353d67e6d295274e84e90b7aff576006d656b470e19c2ee40f518d564e1fea1e890c77d3e531da4fb09b424 | C113: 72697550 | D113: SFEE | E113: 46050 | F113: 46050.273 | G113: 900843898 | H113: RAPPI S.A.S | I113: =K113-J113 -> 20168.07 | J113: 3831.93 | K113: 24000 | L113: CAJA MENOR | N113: =IFERROR(IF(-_xlfn.DAYS(E113,M113)<0,0,-_xlfn.DAYS(E113,M113)), " - ") -> 0
A114: Factura electrónica | B114: eb0b6c479c3695e2123e0824d14f56c7b346e92528855d0c786fa301133a32c9b6d59278046f47aa42c926e9b63299f9 | C114: 4848 | D114: FEL | E114: 46024 | F114: 46024.382 | G114: 10103705 | H114: RAMIREZ LOPEZ LUIS FERNANDO | I114: =K114-J114 -> 798319.28 | J114: 151680.66 | K114: 949999.94 | L114: SSTA | M114: 46028 | N114: =IFERROR(IF(-_xlfn.DAYS(E114,M114)<0,0,-_xlfn.DAYS(E114,M114)), " - ") -> 4 | O114: YENIFER PARRA | T114: 46044 | U114: NO | W114: 0 a 5
...

Sheet FEBRERO
B1: CUFE/CUDE | C1: Folio | D1: Prefijo | E1: Fecha Emisión | F1: Fecha Recepción | G1: NIT | H1: Nombre Emisor | I1: Subtotal | J1: IVA | K1: Total | L1: Responsable | M1: FECHA DE ENTREGA | N1: DÍAS DE ENTREGA A CONTABILIDAD | O1: QUIEN ENTREGA | P1: NOMBRE A QUIEN SE DEVUELVE | Q1: FECHA DEVOLUCION | R1: REINTEGRO | S1: RANGO DE ENTREGA A TESORERIA DIAS | T1: FECHA ENTREGA TESORERIA | U1: REQUIERE FIRMA DE GERENCIA | V1: FIRMADAS | W1: RANGO DÍAS DE ENTREGA | X1: MES DEL SERVICIO
A2: Factura electrónica | B2: 4de1d08c12bff4f13d87fc5f171cf87347f63e11472aba726cde2d27513f26ea8d4e1d06fc7447e8e6ef3af720112231 | C2: 452889 | D2: IFXC | E2: 46054 | F2: 46054.758 | G2: 830058677 | H2: IFX NETWORKS COLOMBIA S.A.S. | I2: =K2-J2 -> 13180561 | J2: 2504306.6 | K2: 15684868 | L2: =VLOOKUP(G2,ENERO!G2:L631,6,0) -> TI | M2: 46056 | N2: =IFERROR(IF(-_xlfn.DAYS(E2,M2)<0,0,-_xlfn.DAYS(E2,M2)), " - ") -> 2 | O2: ALEXANDER TABORDA | T2: 46058 | U2: NO | W2: 0 A 5
A3: Factura electrónica | B3: 022ce6b7e6e5d89fa427fd96d78e2a96471a07717f72ca4e53cfd826dbe1277624885ca8266df6cf34e683591c908e30 | C3: 4920 | D3: FEIT | E3: 46054 | F3: 46054.92 | G3: 901042685 | H3: ITTERACTIVO S.A.S. | I3: =K3-J3 -> 1990452 | J3: 0 | K3: 1990452 | L3: =VLOOKUP(G3,ENERO!G3:L632,6,0) -> TI | M3: 46055 | N3: =IFERROR(IF(-_xlfn.DAYS(E3,M3)<0,0,-_xlfn.DAYS(E3,M3)), " - ") -> 1 | O3: ALEXANDER TABORDA | T3: 46058 | U3: NO | W3: 0 A 5
A4: Factura electrónica | B4: 251d206c3b842cde617bdb08ee00c5c31bb13b2db16fd1196196b0037dd40078b1d75797b4cd5cbbd666e1b3749246eb | C4: 36026 | D4: AEZY | E4: 46054 | F4: 46054.186 | G4: 900610585 | H4: Easytaxi Colombia SAS | I4: =K4-J4 -> 3927701 | J4: 102933 | K4: 4030634 | L4: =VLOOKUP(G4,ENERO!G4:L633,6,0) -> COMPRAS | M4: 46056 | N4: =IFERROR(IF(-_xlfn.DAYS(E4,M4)<0,0,-_xlfn.DAYS(E4,M4)), " - ") -> 2 | O4: YENIFER PARRA | T4: 46063 | U4: NO | W4: 0 A 5
A5: Factura electrónica | B5: 9c115d0562effa71779e797d1e2e8efca2f66d7e0e3a9b8b8385cec8a8dff4c790c1c6012c3df3ae2de8b8868b3dd5c9 | C5: 634908 | D5: ECCO | E5: 46054 | F5: 46054.41 | G5: 811009788 | H5: DISTRACOM S.A. | I5: =K5-J5 -> 85030 | J5: 0 | K5: 85030 | L5: =VLOOKUP(G5,ENERO!G5:L634,6,0) -> COMPRAS | M5: 46056 | N5: =IFERROR(IF(-_xlfn.DAYS(E5,M5)<0,0,-_xlfn.DAYS(E5,M5)), " - ") -> 2 | O5: YENIFER PARRA | T5: 46062 | U5: NO | W5: 0 A 5
A6: Factura electrónica | B6: b1cdb399e51e6df685d41c2317d9ab32f3c0c96e367a1f1b9abc1d0f8683e5a5f8e99b533170477464b9468b4beea4cf | C6: 37677 | D6: VFGA | E6: 46054 | F6: 46054.803 | G6: 1088263697 | H6: VALENTINA FERNANDEZ VALENCIA | I6: =K6-J6 -> 31700 | J6: 0 | K6: 31700 | L6: CAJA MENOR | N6: =IFERROR(IF(-_xlfn.DAYS(E6,M6)<0,0,-_xlfn.DAYS(E6,M6)), " - ") -> 0
A7: Factura electrónica | B7: 552243f34aca81451f8cad9f632aeef4650ea2e952b6c9f3a95c78428390b21e629d0da9ce7c4618bddc70470f20c416 | C7: 4892 | D7: FEIT | E7: 46054 | F7: 46054.709 | G7: 901042685 | H7: ITTERACTIVO S.A.S. | I7: =K7-J7 -> 8849107 | J7: 0 | K7: 8849107 | L7: =VLOOKUP(G7,ENERO!G7:L636,6,0) -> TI | M7: 46076 | N7: =IFERROR(IF(-_xlfn.DAYS(E7,M7)<0,0,-_xlfn.DAYS(E7,M7)), " - ") -> 22 | O7: JAIME GARCIA | T7: 46069 | U7: NO | W7: MAS 10
A8: Factura electrónica | B8: feeee341d506c4b0f1d50df0f5979ca4db497e2a7ff214c457614357ae6c32818e7051c7de64bc5c516318b20de00dbb | C8: 19088 | D8: FET | E8: 46054 | F8: 46054.63 | G8: 71656465 | H8: JUAN DAVID FERRER BERNAL | I8: =K8-J8 -> 141100 | J8: 0 | K8: 141100 | L8: CAJA MENOR | N8: =IFERROR(IF(-_xlfn.DAYS(E8,M8)<0,0,-_xlfn.DAYS(E8,M8)), " - ") -> 0
A9: Factura electrónica | B9: f1c518e75af10e54eee6c56f8713f0b205866afbbf1e25ab4671a250bced4e0ee286dcd37a6bd412b5c9ece7da54919d | C9: 292509059 | D9: 3 | E9: 46054 | F9: 46058.724 | G9: 800153993 | H9: COMUNICACION CELULAR S A COMCEL S A | I9: =K9-J9 -> 1967321 | J9: 44197.99 | K9: 2011519 | L9: TI | M9: 46076 | N9: =IFERROR(IF(-_xlfn.DAYS(E9,M9)<0,0,-_xlfn.DAYS(E9,M9)), " - ") -> 22 | O9: JAIME GARCIA | T9: 46071 | U9: NO | W9: MAS 10
A10: Factura electrónica | B10: 2d56d828236951a3feb7ef771598af592cd6048ab817e93780bc1787020f56d8b2a96abb68007484220061a939c7b646 | C10: 1724 | D10: FE | E10: 46055 | F10: 46055.358 | G10: 900609164 | H10: VIREL SAS | I10: =K10-J10 -> 650000 | J10: 123500 | K10: 773500 | L10: CRUZA | M10: N/A | N10: =IFERROR(IF(-_xlfn.DAYS(E10,M10)<0,0,-_xlfn.DAYS(E10,M10)), " - ") -> - | O10: FRANCY SALAS
A11: Factura electrónica | B11: dd0011eb4b5647395d5a5a8781955be804153b53cd90b6990c73b1dee24c124375c6d3b03add393fa3333425aacb6575 | C11: 1213609 | D11: 2091 | E11: 46055 | F11: 46055.912 | G11: 890903790 | H11: SEGUROS DE VIDA SURAMERICANA S.A | I11: =K11-J11 -> 1643587 | J11: 82179.35 | K11: 1725766.4 | L11: GESTION HUMANA | M11: 46076 | N11: =IFERROR(IF(-_xlfn.DAYS(E11,M11)<0,0,-_xlfn.DAYS(E11,M11)), " - ") -> 21 | W11: MAS 10
A12: Factura electrónica | B12: 5a59de4888820535220d847370d5c335afbffa2e042d66f739e329ffa5889cf8b5c5ff90f8603c372e8eb76eb75eafc5 | C12: 1896 | D12: SGKE | E12: 46055 | F12: 46055.783 | G12: 901068561 | H12: SUGEEK SAS | I12: =K12-J12 -> 199000 | J12: 0 | K12: 199000 | L12: TI | M12: 46076 | N12: =IFERROR(IF(-_xlfn.DAYS(E12,M12)<0,0,-_xlfn.DAYS(E12,M12)), " - ") -> 21 | O12: ALEXANDER TABORDA | T12: 46058 | U12: NO | W12: MAS 10
A13: Factura electrónica | B13: 2d8a77cc4dd5467b27f1e519d499ddf6a53bda457bb188f8f833b5fc3d06b27dbe97b53aab88224f7532382cb351cfdb | C13: 122 | D13: JA | E13: 46055 | F13: 46055.725 | G13: 15442838 | H13: GOMEZ JHON ARLEY | I13: =K13-J13 -> 1518400 | J13: 288496 | K13: 1806896 | L13: OPERACIONES | M13: 46076 | N13: =IFERROR(IF(-_xlfn.DAYS(E13,M13)<0,0,-_xlfn.DAYS(E13,M13)), " - ") -> 21 | O13: CARLOS RENDON | T13: 46058 | U13: NO | W13: MAS 10
A14: Factura electrónica | B14: 8bbfc0b04e26ba57b3b6112ae1a0d8fb7d2e56f5259a7bb3ba6d382abc982c38c4c958164530c8b5582cbdf0298d9734 | C14: 55735 | D14: FVE | E14: 46055 | F14: 46055.712 | G14: 900650486 | H14: DISTRIBUIDORA DE SOFTWARE Y MOVILIDAD S.A.S | I14: =K14-J14 -> 1936974.8 | J14: 368025.22 | K14: 2305000 | L14: TI | M14: 46076 | N14: =IFERROR(IF(-_xlfn.DAYS(E14,M14)<0,0,-_xlfn.DAYS(E14,M14)), " - ") -> 21 | O14: YENIFER PARRA | T14: 46059 | U14: NO | W14: MAS 10
A15: Factura electrónica | B15: b1f9399bfb0ecf8188513131d6732d09defba12c231cf936381ed5f9ad85aefc7bf7c6857190de9a3f1c3022885d4c36 | C15: 1288 | D15: SM | E15: 46055 | F15: 46055.703 | G15: 901561580 | H15: SUMINISTRO MATERIALES Y DOTACIONES SUMADO S.A.S | I15: =K15-J15 -> 2964947.8 | J15: 563340.08 | K15: 3528287.9 | L15: COMPRAS | M15: 46076 | N15: =IFERROR(IF(-_xlfn.DAYS(E15,M15)<0,0,-_xlfn.DAYS(E15,M15)), " - ") -> 21 | O15: YENIFER PARRA | T15: 46065 | U15: NO | W15: MAS 10
A16: Factura electrónica | B16: 44b4f27598c1cef4dd66f35816e205063021a4bff0f356b046323ff40d5059c1d11af8f529ccf18ce308316ac67b2187 | C16: 5913 | E16: 46055 | F16: 46055.913 | G16: 32150739 | H16: NATALIA ANDREA ACOSTA COLORADO | I16: =K16-J16 -> 637500 | J16: 0 | K16: 637500 | L16: GESTION HUMANA | M16: 46076 | N16: =IFERROR(IF(-_xlfn.DAYS(E16,M16)<0,0,-_xlfn.DAYS(E16,M16)), " - ") -> 21 | O16: YENIFER PARRA | T16: 46059 | U16: NO | W16: MAS 10
A17: Factura electrónica | B17: 21e25254a25bd088c4b4f00f45d867aa728f895fc3fb38cb109b7989193fdfdf1b0e9a0c95050ad921802ac7d1a73f03 | C17: 100115489 | D17: 9944 | E17: 46055 | F17: 46055.877 | G17: 800242106 | H17: SODIMAC COLOMBIA S.A. | I17: =K17-J17 -> 24900 | J17: 0 | K17: 24900 | L17: COMPRAS | M17: 46076 | N17: =IFERROR(IF(-_xlfn.DAYS(E17,M17)<0,0,-_xlfn.DAYS(E17,M17)), " - ") -> 21 | O17: YENIFER PARRA | T17: 46062 | U17: NO | W17: MAS 10
A18: Factura electrónica | B18: db3dc9aefab95f1c6cf7258be6929c762abd2eb232117f2cf2b14cf102439a556c8492290f8f729907d9f11f11692d18 | C18: 378 | D18: MD | E18: 46055 | F18: 46055.869 | G18: 900484392 | H18: Sigfrido SAS | I18: =K18-J18 -> 27859250 | J18: 5293257.5 | K18: 33152508 | L18: CONTABILIDAD | M18: 46076 | N18: =IFERROR(IF(-_xlfn.DAYS(E18,M18)<0,0,-_xlfn.DAYS(E18,M18)), " - ") -> 21 | O18: NATALIA BERNAZA | T18: 46057 | U18: NO | W18: MAS 10
A19: Factura electrónica | B19: 92df2cc88099e9c3beccdcaa90acbfcaef27114abea65267170a45cb8b562546f0e3584b339e2a229454e64b5cce3516 | C19: 1341 | D19: FE | E19: 46055 | F19: 46055.672 | G19: 901950863 | H19: INVERSIONES TORNILLOS Y MANGUERAS S.A.S | I19: =K19-J19 -> 800000 | J19: 152000 | K19: 952000 | L19: MANTENIMIENTO | M19: 46076 | N19: =IFERROR(IF(-_xlfn.DAYS(E19,M19)<0,0,-_xlfn.DAYS(E19,M19)), " - ") -> 21 | O19: YENIFER PARRA | T19: 46066 | U19: NO | W19: MAS 10
A20: Factura electrónica | B20: fdfcaa6bca603e97207781e56533a04f7ea4a6aa64b89d6a480dc28bedd3fab32e75fdaebc0bc9652eec363baf19d037 | C20: 7649 | D20: SM | E20: 46055 | F20: 46055.624 | G20: 800205419 | H20: S.M. EMPAQUES S.A.S. | I20: =K20-J20 -> 1125390 | J20: 213824.1 | K20: 1339214.1 | L20: COMPRAS | M20: 46076 | N20: =IFERROR(IF(-_xlfn.DAYS(E20,M20)<0,0,-_xlfn.DAYS(E20,M20)), " - ") -> 21 | O20: YENIFER PARRA | T20: 46059 | U20: NO | W20: MAS 10
A21: Factura electrónica | B21: b91a07ba9f007a0febf333f555ac6d42ad2c86314f70e795847690cab90f5294aa42cefb81b50dc3161d49917de499c9 | C21: 342402 | D21: FFEE | E21: 46055 | F21: 46055.653 | G21: 800049074 | H21: PAPELERIA Y SERVICIOS SAS | I21: =K21-J21 -> 486221 | J21: 73180 | K21: 559401 | L21: COMPRAS | M21: 46076 | N21: =IFERROR(IF(-_xlfn.DAYS(E21,M21)<0,0,-_xlfn.DAYS(E21,M21)), " - ") -> 21 | O21: YENIFER PARRA | T21: 46066 | U21: NO | W21: MAS 10
A22: Factura electrónica | B22: 087f005f0025cb19cce8a1ac4fbd1d038dcd8334d8ad9ddaec1ab011106da6d40dedd3f920e5d62316d3eca0c70fae65 | C22: 342328 | D22: FFEE | E22: 46055 | F22: 46055.538 | G22: 800049074 | H22: PAPELERIA Y SERVICIOS SAS | I22: =K22-J22 -> 76086 | J22: 3804 | K22: 79890 | L22: COMPRAS | M22: 46076 | N22: =IFERROR(IF(-_xlfn.DAYS(E22,M22)<0,0,-_xlfn.DAYS(E22,M22)), " - ") -> 21 | O22: YENIFER PARRA | T22: 46062 | U22: NO | W22: MAS 10
A23: Factura electrónica | B23: 6e7f4eacacccb4f4b10acc1f3f72a41fb5ab16fe1946b332a979d812e7eca6b1fdc22319194895fde0ccdc70ac9d2fd5 | C23: 5857 | D23: REST | E23: 46055 | F23: 46055.709 | G23: 890903388 | H23: CLUB UNION S.A. | I23: =K23-J23 -> 253050 | J23: 0 | K23: 253050 | L23: CAJA MENOR | N23: =IFERROR(IF(-_xlfn.DAYS(E23,M23)<0,0,-_xlfn.DAYS(E23,M23)), " - ") -> 0 | T23: 46066 | U23: N
A24: Factura electrónica | B24: 5e71acb723fc9db5e14b9372400cda1fa0b78358ce59f221f5353dbdedfe436cf7f2866d97a5338c58989dab12208492 | C24: 564006 | D24: AH | E24: 46055 | F24: 46055.374 | G24: 890800788 | H24: SUMATEC S.A.S BIC | I24: =K24-J24 -> 319550 | J24: 60715 | K24: 380265 | L24: COMPRAS | M24: 46076 | N24: =IFERROR(IF(-_xlfn.DAYS(E24,M24)<0,0,-_xlfn.DAYS(E24,M24)), " - ") -> 21 | O24: YENIFER PARRA | T24: 46059 | U24: NO | W24: MAS 10
A25: Factura electrónica | B25: 9eb29bcfc66c363017b2bb20e96b978a2798cb8dce064707a02d3a1ccb5e5663bbfb7af3571a730b0049f8fbb0d28c26 | C25: 7650 | D25: SM | E25: 46055 | F25: 46055.624 | G25: 800205419 | H25: S.M. EMPAQUES S.A.S. | I25: =K25-J25 -> 397080 | J25: 75445.2 | K25: 472525.2 | L25: COMPRAS | M25: 46076 | N25: =IFERROR(IF(-_xlfn.DAYS(E25,M25)<0,0,-_xlfn.DAYS(E25,M25)), " - ") -> 21 | O25: YENIFER PARRA | T25: 46059 | U25: NO | W25: MAS 10
A26: Factura electrónica | B26: 84c11647634126cf5dcb33fa3af5a027c669c2e8df5090b7cd418d19b0e7ce4e65e034f22d5677e4292f9280c8181146 | C26: 2711 | D26: FVE | E26: 46055 | F26: 46055.445 | G26: 900667734 | H26: TORNO PARTES S.A.S | I26: =K26-J26 -> 1120000 | J26: 212800 | K26: 1332800 | L26: MANTENIMIENTO | M26: 46076 | N26: =IFERROR(IF(-_xlfn.DAYS(E26,M26)<0,0,-_xlfn.DAYS(E26,M26)), " - ") -> 21 | O26: YENIFER PARRA | T26: 46066 | U26: NO | W26: MAS 10
A27: Factura electrónica | B27: 16c966286b1f44bf21115accef363ad564cce1ffd93b55e7f7475c236eed58254be83d6cacc94d9abd827f2f8d820c5e | C27: 151096 | D27: LA | E27: 46055 | F27: 46055.691 | G27: 811013715 | H27: LINEA ADHESIVA S.A.S. BIC. | I27: =K27-J27 -> 4110926.1 | J27: 781076.02 | K27: 4892002.2 | L27: COMPRAS | M27: 46076 | N27: =IFERROR(IF(-_xlfn.DAYS(E27,M27)<0,0,-_xlfn.DAYS(E27,M27)), " - ") -> 21 | O27: FRANCY SALAS | T27: 46071 | U27: NO | W27: MAS 10
A28: Factura electrónica | B28: ef9efb90ab44ad63f11f91bc5acf840e3ed912b2e76277b7b9c5f9aa34db343b939ed4948ae4a0910c7120d4f6d4692d | C28: 18403 | D28: INIM | E28: 46055 | F28: 46055.532 | G28: 900237741 | H28: INVERSIONES IMPRIMA SAS | I28: =K28-J28 -> 135000 | J28: 25650 | K28: 160650 | L28: COMPRAS | M28: 46076 | N28: =IFERROR(IF(-_xlfn.DAYS(E28,M28)<0,0,-_xlfn.DAYS(E28,M28)), " - ") -> 21 | O28: YENIFER PARRA | T28: 46059 | U28: NO | W28: MAS 10
A29: Factura electrónica | B29: b6ecd6a2d554e408507ed92f3544ba0328f2a6e9b4c479921f679a3019860f129b2711a2eab854f7d7a245eaba0f22f9 | C29: 18402 | D29: INIM | E29: 46055 | F29: 46055.532 | G29: 900237741 | H29: INVERSIONES IMPRIMA SAS | I29: =K29-J29 -> 150000 | J29: 28500 | K29: 178500 | L29: COMPRAS | M29: 46076 | N29: =IFERROR(IF(-_xlfn.DAYS(E29,M29)<0,0,-_xlfn.DAYS(E29,M29)), " - ") -> 21 | O29: YENIFER PARRA | T29: 46059 | U29: NO | W29: MAS 10
A30: Factura electrónica | B30: 854e29821dbde59a525562c19ae26fb765ec91bc1f2ce031a5d4c949d3614333829f9236e3ecf5da73081bf9809fd01d | C30: 21735 | D30: FE | E30: 46055 | F30: 46055.412 | G30: 900083323 | H30: AGENCIA DE INVERSIONES PROSPERAR S.A.S. | I30: =K30-J30 -> 10499723 | J30: 1774638 | K30: 12274361 | L30: CONTABILIDAD | M30: 46076 | N30: =IFERROR(IF(-_xlfn.DAYS(E30,M30)<0,0,-_xlfn.DAYS(E30,M30)), " - ") -> 21 | O30: NATALIA BERNAZA | T30: 46057 | U30: SI | W30: MAS 10
A31: Factura electrónica | B31: a64bd6a41d1f0758930e03652d4d3c895edb53f9fd8824176508d5643307ef7ce14667d46cbc98a0d64d699db8570c59 | C31: 1139 | D31: FE | E31: 46055 | F31: 46055.656 | G31: 811007030 | H31: CREACIONES POSADA & JARAMILLO S.A.S. | I31: =K31-J31 -> 2101400 | J31: 399266 | K31: 2500666 | L31: COMPRAS | M31: 46076 | N31: =IFERROR(IF(-_xlfn.DAYS(E31,M31)<0,0,-_xlfn.DAYS(E31,M31)), " - ") -> 21 | O31: YENIFER PARRA | T31: 46059 | U31: NO | W31: MAS 10
A32: Factura electrónica | B32: a7e9842e4b7784ae2a488ba3229a0ac23cb16d8fe05be8ac9e9dcb5302385561ec9cab785adcd68dcd2810b189c7ee40 | C32: 564020 | D32: AH | E32: 46055 | F32: 46055.442 | G32: 890800788 | H32: SUMATEC S.A.S BIC | I32: =K32-J32 -> 107335 | J32: 20394 | K32: 127729 | L32: COMPRAS | M32: 46076 | N32: =IFERROR(IF(-_xlfn.DAYS(E32,M32)<0,0,-_xlfn.DAYS(E32,M32)), " - ") -> 21 | O32: YENIFER PARRA | T32: 46066 | U32: NO | W32: MAS 10
A33: Factura electrónica | B33: a24682aa6bc32ab3af1bebf7f5a75b80ae2b852971ae01c690382f2ce4b74a9f911fea246686625e1f8072bf88cda2bc | C33: 104244 | D33: FAE | E33: 46055 | F33: 46055.503 | G33: 830120839 | H33: MULTISUMINISTROS INDUSTRIALES S A S | I33: =K33-J33 -> 78668 | J33: 14947 | K33: 93615 | L33: COMPRAS | M33: 46076 | N33: =IFERROR(IF(-_xlfn.DAYS(E33,M33)<0,0,-_xlfn.DAYS(E33,M33)), " - ") -> 21 | O33: YENIFER PARRA | T33: 46059 | U33: NO | W33: MAS 10
A34: Factura electrónica | B34: b93fb3bde363cf1b437d6cca3855c1858c39f2aca7a020321b5e6a34224054e551e008b72af5eb8cf1a20f9088e5cc64 | C34: 342331 | D34: FFEE | E34: 46055 | F34: 46055.538 | G34: 800049074 | H34: PAPELERIA Y SERVICIOS SAS | I34: =K34-J34 -> 13335 | J34: 2534 | K34: 15869 | L34: COMPRAS | M34: 46076 | N34: =IFERROR(IF(-_xlfn.DAYS(E34,M34)<0,0,-_xlfn.DAYS(E34,M34)), " - ") -> 21 | O34: YENIFER PARRA | T34: 46062 | U34: NO | W34: MAS 10
A35: Factura electrónica | B35: 937a0f8a3bc8ffad396c0609ff62a5f79d4a9d021962f6fb19e0e950e117ba47927c86cebb4f997211ba03ac2f9ccd03 | C35: 21627 | D35: FE | E35: 46055 | F35: 46055.386 | G35: 900083323 | H35: AGENCIA DE INVERSIONES PROSPERAR S.A.S. | I35: =K35-J35 -> 9632900 | J35: 1830251 | K35: 11463151 | L35: CONTABILIDAD | M35: 46056 | N35: =IFERROR(IF(-_xlfn.DAYS(E35,M35)<0,0,-_xlfn.DAYS(E35,M35)), " - ") -> 1 | O35: NATALIA BERNAZA | T35: 46057 | U35: SI | W35: 0 A 5
A36: Factura electrónica | B36: 1d8dca1213d161c1f724ab3bacb17a9b096d56a459af52673b45e8104db2fa8a38d16dfb404621f1555f151472acf044 | C36: 564003 | D36: AH | E36: 46055 | F36: 46055.368 | G36: 890800788 | H36: SUMATEC S.A.S BIC | I36: =K36-J36 -> 276000 | J36: 52440 | K36: 328440 | L36: COMPRAS | M36: 46057 | N36: =IFERROR(IF(-_xlfn.DAYS(E36,M36)<0,0,-_xlfn.DAYS(E36,M36)), " - ") -> 2 | O36: YENIFER PARRA | T36: 46062 | U36: NO | W36: 0 A 5
A37: Factura electrónica | B37: d4e5bec6099b844cbccba0db6c598872f3bb16fa53416266716c3990971e7f65a3b3aac2d42a81a1b2cd0a9acb6f583c | C37: 91852 | D37: 1PQE | E37: 46055 | F37: 46055.712 | G37: 900125852 | H37: CI SAN FERNANDO PLAZA PH. | I37: =K37-J37 -> 19327.39 | J37: 3672.61 | K37: 23000 | L37: CAJA MENOR | N37: =IFERROR(IF(-_xlfn.DAYS(E37,M37)<0,0,-_xlfn.DAYS(E37,M37)), " - ") -> 0
A38: Factura electrónica | B38: a9c4e39224d0454af3be7d4f8157de3803f7e3be73e4cc96003c1be8b632f9e5f49f566d8150b12e4c86ecbfcdc277fd | C38: 1340 | D38: FE | E38: 46055 | F38: 46055.665 | G38: 901950863 | H38: INVERSIONES TORNILLOS Y MANGUERAS S.A.S | I38: =K38-J38 -> 72000 | J38: 13680 | K38: 85680 | L38: MANTENIMIENTO | M38: 46057 | N38: =IFERROR(IF(-_xlfn.DAYS(E38,M38)<0,0,-_xlfn.DAYS(E38,M38)), " - ") -> 2 | O38: YENIFER PARRA | T38: 46066 | U38: NO | W38: 0 A 5
A39: Factura electrónica | B39: 2a6c47bc6d7641ce1298190edfc7ac84febd05a6a8785a25fef8fb1b2c317505244320f61f1262b158dcd9547ca9da9d | C39: 7648 | D39: SM | E39: 46055 | F39: 46055.62 | G39: 800205419 | H39: S.M. EMPAQUES S.A.S. | I39: =K39-J39 -> 375130 | J39: 71274.7 | K39: 446404.7 | L39: COMPRAS | M39: 46057 | N39: =IFERROR(IF(-_xlfn.DAYS(E39,M39)<0,0,-_xlfn.DAYS(E39,M39)), " - ") -> 2 | O39: YENIFER PARRA | T39: 46059 | U39: NO | W39: 0 A 5
A40: Factura electrónica | B40: 3ec7c0fdedf9fb927d884e20aac526c929606e21e3bba11ceaadfc4acb7c7bbea24e4a6dd57132e80b9fba797a35dabe | C40: 2712 | D40: FVE | E40: 46055 | F40: 46055.459 | G40: 900667734 | H40: TORNO PARTES S.A.S | I40: =K40-J40 -> 178680 | J40: 33949.2 | K40: 212629.2 | L40: MANTENIMIENTO | M40: 46057 | N40: =IFERROR(IF(-_xlfn.DAYS(E40,M40)<0,0,-_xlfn.DAYS(E40,M40)), " - ") -> 2 | O40: YENIFER PARRA | T40: 46066 | U40: NO | W40: 0 A 5
A41: Factura electrónica | B41: 297db88dd48f80263deb4e940f6ef069bfa46a94881dae9ae913a2c86f00511cc4ed5269327b9471d4e2ac14d015263b | C41: 8098 | E41: 46055 | F41: 46055.665 | G41: 901360705 | H41: DELTA TAGS SAS | I41: =K41-J41 -> 258360 | J41: 49088.4 | K41: 307448.4 | L41: COMPRAS | M41: 46057 | N41: =IFERROR(IF(-_xlfn.DAYS(E41,M41)<0,0,-_xlfn.DAYS(E41,M41)), " - ") -> 2 | O41: YENIFER PARRA | T41: 46062 | U41: NO | W41: 0 A 5
A42: Factura electrónica | B42: 823f5d78c72446328cf7326ca19b9b61006179f9a392b1c3ff203de45ffaa7633509cb2c5b073c7987c7ea51b6f184a1 | C42: 226 | D42: ARB | E42: 46055 | F42: 46055.605 | G42: 900654063 | H42: ARBELAEZ ASOCIADOS SAS | I42: =K42-J42 -> 2627500 | J42: 499225 | K42: 3126725 | L42: CONTABILIDAD | M42: 46056 | N42: =IFERROR(IF(-_xlfn.DAYS(E42,M42)<0,0,-_xlfn.DAYS(E42,M42)), " - ") -> 1 | O42: NATALIA BERNAZA | T42: 46058 | U42: NO | W42: 0 A 5
A43: Factura electrónica | B43: 3b54e134c34897a02b753b2bbd74e143b4c5021b1bd1a22646ca207ceefe9ea441d7ba4da2649fcbd51b8a62f75db5e5 | C43: 728 | D43: FE | E43: 46055 | F43: 46055.436 | G43: 71660004 | H43: RAMIREZ CADAVID JUAN PABLO | I43: =K43-J43 -> 160000 | J43: 0 | K43: 160000 | L43: COMPRAS | M43: 46057 | N43: =IFERROR(IF(-_xlfn.DAYS(E43,M43)<0,0,-_xlfn.DAYS(E43,M43)), " - ") -> 2 | O43: YENIFER PARRA | T43: 46062 | U43: NO | W43: 0 A 5
A44: Factura electrónica | B44: a92094ca6b19fdd9d3ee77711ed569e541d1c1a8837e8cc8de4f3922aa799e343438a6ba157f00dc7b027736fadd244b | C44: 33410 | D44: FEN | E44: 46055 | F44: 46055.669 | G44: 9522660 | H44: OCTAVIANO TORRES GUEVARA | I44: =K44-J44 -> 5959663.8 | J44: 1132336.1 | K44: 7091999.9 | L44: MANTENIMIENTO | M44: 46057 | N44: =IFERROR(IF(-_xlfn.DAYS(E44,M44)<0,0,-_xlfn.DAYS(E44,M44)), " - ") -> 2 | O44: YENIFER PARRA | T44: 46066 | U44: NO | W44: 0 A 5
A45: Factura electrónica | B45: a8df5dc070a27a0cb787210d96c014d5b0c068051fe4c96205d1f7d055531187a79dfea0e4cfcb94e997b8737ca182b6 | C45: 21670 | D45: FE | E45: 46055 | F45: 46055.396 | G45: 900083323 | H45: AGENCIA DE INVERSIONES PROSPERAR S.A.S. | I45: =K45-J45 -> 9173737 | J45: 1540482 | K45: 10714219 | L45: CONTABILIDAD | M45: 46056 | N45: =IFERROR(IF(-_xlfn.DAYS(E45,M45)<0,0,-_xlfn.DAYS(E45,M45)), " - ") -> 1 | O45: NATALIA BERNAZA | T45: 46057 | U45: SI | W45: 0 A 5
A46: Factura electrónica | B46: d9e5128d014a4a0cef8b16264f061c7326b0cbb5dab3882d995afc9b44142a0d56694ab364c03f5c5211c5430017afb2 | C46: 342202 | D46: FFEE | E46: 46055 | F46: 46055.406 | G46: 800049074 | H46: PAPELERIA Y SERVICIOS SAS | I46: =K46-J46 -> 200576 | J46: 38109 | K46: 238685 | L46: COMPRAS | M46: 46057 | N46: =IFERROR(IF(-_xlfn.DAYS(E46,M46)<0,0,-_xlfn.DAYS(E46,M46)), " - ") -> 2 | O46: YENIFER PARRA | T46: 46059 | U46: NO | W46: 0 A 5
A47: Factura electrónica | B47: 3df41e6512a4caa1e6966086961909172430ffd77f476ca728051227cc7fcc7e21d53d32b0fe815b6344246a648ef0e1 | C47: 7647 | D47: SM | E47: 46055 | F47: 46055.619 | G47: 800205419 | H47: S.M. EMPAQUES S.A.S. | I47: =K47-J47 -> 1125390 | J47: 213824.1 | K47: 1339214.1 | L47: COMPRAS | M47: 46057 | N47: =IFERROR(IF(-_xlfn.DAYS(E47,M47)<0,0,-_xlfn.DAYS(E47,M47)), " - ") -> 2 | O47: YENIFER PARRA | T47: 46059 | U47: NO | W47: 0 A 5
A48: Factura electrónica | B48: 147db103c93b6ea3e90564eab9b282c0b123250388d9d370da88ff1761ca5cb4d7269f4e5c08e68a769ad99031d2fa70 | C48: 43396 | D48: G832 | E48: 46055 | F48: 46055.669 | G48: 891408584 | H48: FRISBY S.A. BIC | I48: =K48-J48 -> 44900 | J48: 0 | K48: 44900 | L48: CAJA MENOR | N48: =IFERROR(IF(-_xlfn.DAYS(E48,M48)<0,0,-_xlfn.DAYS(E48,M48)), " - ") -> 0
A49: Factura electrónica | B49: 7264b76d7f152fbd42aacbdb9b43c34a1f0cd5e7e5007431b8d292f064dc7e1111c273214ea45bbbe0ce2ef50d4be586 | C49: 18405 | D49: INIM | E49: 46055 | F49: 46055.533 | G49: 900237741 | H49: INVERSIONES IMPRIMA SAS | I49: =K49-J49 -> 828800 | J49: 157472 | K49: 986272 | L49: COMPRAS | M49: 46057 | N49: =IFERROR(IF(-_xlfn.DAYS(E49,M49)<0,0,-_xlfn.DAYS(E49,M49)), " - ") -> 2 | O49: YENIFER PARRA | T49: 46059 | U49: NO | W49: 0 A 5
A50: Factura electrónica de contingencia | B50: 3b790b6ad57ae858a8bcc5e890c05f14c2c55559e981e007827d503e6968fa8c16e741bfeb8e3a1a6d7ed0a9d6fcb00d | C50: 3603 | D50: G83B | E50: 46055 | F50: 46055.674 | G50: 891408584 | H50: FRISBY S.A. BIC | I50: =K50-J50 -> 44900 | J50: 0 | K50: 44900 | L50: CAJA MENOR | N50: =IFERROR(IF(-_xlfn.DAYS(E50,M50)<0,0,-_xlfn.DAYS(E50,M50)), " - ") -> 0 | T50: 46073 | U50: NO
A51: Factura electrónica | B51: 7c91e52f01fb4386ff70ee9325b8d84916d0fcad53da3a2f702b302064bca85b631f270bd290b7ef6c26d0d06834d603 | C51: 21671 | D51: FE | E51: 46055 | F51: 46055.396 | G51: 900083323 | H51: AGENCIA DE INVERSIONES PROSPERAR S.A.S. | I51: =K51-J51 -> 9173737 | J51: 1540482 | K51: 10714219 | L51: CONTABILIDAD | M51: 46056 | N51: =IFERROR(IF(-_xlfn.DAYS(E51,M51)<0,0,-_xlfn.DAYS(E51,M51)), " - ") -> 1 | O51: NATALIA BERNAZA | T51: 46057 | U51: SI | W51: 0 A 5
A52: Factura electrónica | B52: 656662afd6cf015bfdddee7b924541e5f3328ada205a5a73e670cc390bf84490160dec14691ffee3215cae407dae73c6 | C52: 342192 | D52: FFEE | E52: 46055 | F52: 46055.387 | G52: 800049074 | H52: PAPELERIA Y SERVICIOS SAS | I52: =K52-J52 -> 121897 | J52: 12508 | K52: 134405 | L52: COMPRAS | M52: 46057 | N52: =IFERROR(IF(-_xlfn.DAYS(E52,M52)<0,0,-_xlfn.DAYS(E52,M52)), " - ") -> 2 | O52: YENIFER PARRA | T52: 46066 | U52: NO | W52: 0 A 5
A53: Factura electrónica | B53: af4377f3e9fb7606390e9837b5b903bd7a2b08398fa36734e4a49abdda968c09f9831d4099e6974887b39e3041627ab1 | C53: 5300 | D53: SETT | E53: 46055 | F53: 46055.402 | G53: 900611187 | H53: SERMOTOR INGENIERIA S.A.S | I53: =K53-J53 -> 420000 | J53: 79800 | K53: 499800 | L53: MANTENIMIENTO | M53: 46057 | N53: =IFERROR(IF(-_xlfn.DAYS(E53,M53)<0,0,-_xlfn.DAYS(E53,M53)), " - ") -> 2 | O53: YENIFER PARRA | T53: 46066 | U53: NO | W53: 0 A 5
A54: Factura electrónica | B54: e7c1b6794d0c5f6031233e542de290d463fcc2768aa0de3da8d54d7e2aa04606edd5814846b3d93b8e42d4632aff3f93 | C54: 21622 | D54: FE | E54: 46055 | F54: 46055.385 | G54: 900083323 | H54: AGENCIA DE INVERSIONES PROSPERAR S.A.S. | I54: =K54-J54 -> 18800819 | J54: 2943005 | K54: 21743824 | L54: CONTABILIDAD | M54: 46056 | N54: =IFERROR(IF(-_xlfn.DAYS(E54,M54)<0,0,-_xlfn.DAYS(E54,M54)), " - ") -> 1 | O54: NATALIA BERNAZA | W54: 0 A 5
A55: Factura electrónica | B55: 3f9c63e716beec7e11528ac54c14c01ed4a4fab1fcfc1646a10d77945398b0c906a5ada08e7a4e93c9a81fa817e1cd55 | C55: 342330 | D55: FFEE | E55: 46055 | F55: 46055.538 | G55: 800049074 | H55: PAPELERIA Y SERVICIOS SAS | I55: =K55-J55 -> 37300 | J55: 7087 | K55: 44387 | L55: COMPRAS | M55: 46057 | N55: =IFERROR(IF(-_xlfn.DAYS(E55,M55)<0,0,-_xlfn.DAYS(E55,M55)), " - ") -> 2 | O55: YENIFER PARRA | T55: 46062 | U55: NO | W55: 0 A 5
A56: Nota de crédito electrónica | B56: 4d4d38b824ecce4eec28734272c19dbf830e64e018a6a295f5545fdd6d6796094d55370d4409dbcfb21873d053c48ad8 | C56: 704041 | D56: NCF | E56: 46055 | F56: 46055.691 | G56: 891408584 | H56: FRISBY S.A. BIC | I56: =K56-J56 -> 44900 | J56: 0 | K56: 44900 | L56: CAJA MENOR | N56: =IFERROR(IF(-_xlfn.DAYS(E56,M56)<0,0,-_xlfn.DAYS(E56,M56)), " - ") -> 0
A57: Factura electrónica | B57: face88e9a4d705f493267a2cd1e3a9dc86e1930a93cf35bedbac82d6e2888669030dddce7155c882c90199dbf4abcb3e | C57: 8096 | E57: 46055 | F57: 46055.604 | G57: 901360705 | H57: DELTA TAGS SAS | I57: =K57-J57 -> 245840 | J57: 46709.6 | K57: 292549.6 | L57: COMPRAS | M57: 46057 | N57: =IFERROR(IF(-_xlfn.DAYS(E57,M57)<0,0,-_xlfn.DAYS(E57,M57)), " - ") -> 2 | O57: YENIFER PARRA | T57: 46066 | U57: NO | W57: 0 A 5
A58: Factura electrónica | B58: 04ba817ff0d02c79ec77ec3d30495838aae70d35befee0e5ff686b2139d514f88b6653f192f22e667959e675a456d8fa | C58: 3235 | D58: FE | E58: 46055 | F58: 46055.61 | G58: 900563128 | H58: SOLUCIONES SIMMAC S.A.S. | I58: =K58-J58 -> 498600 | J58: 94734 | K58: 593334 | L58: MANTENIMIENTO | M58: 46057 | N58: =IFERROR(IF(-_xlfn.DAYS(E58,M58)<0,0,-_xlfn.DAYS(E58,M58)), " - ") -> 2 | O58: YENIFER PARRA | T58: 46058 | U58: NO | W58: 0 A 5
A59: Factura electrónica | B59: efd568228a269d6f7f0bdddc7e803b5f012c95d1f088ea7d3c1dd2a61d2faea568136631628d7b1fba9ca4503ac10598 | C59: 342332 | D59: FFEE | E59: 46055 | F59: 46055.538 | G59: 800049074 | H59: PAPELERIA Y SERVICIOS SAS | I59: =K59-J59 -> 24264 | J59: 4610 | K59: 28874 | L59: COMPRAS | M59: 46057 | N59: =IFERROR(IF(-_xlfn.DAYS(E59,M59)<0,0,-_xlfn.DAYS(E59,M59)), " - ") -> 2 | O59: YENIFER PARRA | T59: 46062 | U59: NO | W59: 0 A 5
A60: Factura electrónica | B60: df06ae774b3c30ea10e8ced9ec28cfcb333079ca30e02a30cb2d7a441b33b453ab9b3d850731c6c3d93339808ef4e7fd | C60: 166543 | D60: 392 | E60: 46055 | F60: 46055.631 | G60: 860000018 | H60: AGENCIA DE VIAJES Y TURISMO AVIATUR S.A.S | I60: =K60-J60 -> 761300 | J60: 135660 | K60: 896960 | L60: COMPRAS | M60: 46057 | N60: =IFERROR(IF(-_xlfn.DAYS(E60,M60)<0,0,-_xlfn.DAYS(E60,M60)), " - ") -> 2 | O60: YENIFER PARRA | T60: 46066 | U60: NO | W60: 0 A 5
A61: Factura electrónica | B61: 205c520cbb79c4fbf27cc58d2cbecbdb714cbb8ac82366c0a1589ab22bb3c9760e1cb53b30f3a99114f04a1778daa2a9 | C61: 21626 | D61: FE | E61: 46055 | F61: 46055.386 | G61: 900083323 | H61: AGENCIA DE INVERSIONES PROSPERAR S.A.S. | I61: =K61-J61 -> 9632900 | J61: 1830251 | K61: 11463151 | L61: CONTABILIDAD | M61: 46056 | N61: =IFERROR(IF(-_xlfn.DAYS(E61,M61)<0,0,-_xlfn.DAYS(E61,M61)), " - ") -> 1 | O61: NATALIA BERNAZA | T61: 46057 | U61: SI | W61: 0 A 5
A62: Factura electrónica | B62: 5de64bd9094be9f85eb619cea1ffd9bc0f7b2a67ec323d36c1d54257b1230c66ac0b8519a6d015f2586b684c9e5f98fa | C62: 18404 | D62: INIM | E62: 46055 | F62: 46055.533 | G62: 900237741 | H62: INVERSIONES IMPRIMA SAS | I62: =K62-J62 -> 105000 | J62: 19950 | K62: 124950 | L62: COMPRAS | M62: 46057 | N62: =IFERROR(IF(-_xlfn.DAYS(E62,M62)<0,0,-_xlfn.DAYS(E62,M62)), " - ") -> 2 | O62: YENIFER PARRA | T62: 46059 | U62: NO | W62: 0 A 5
A63: Factura electrónica | B63: ccfa6642b29cd8efb8b943051a0a7ffb2594542c5f1e31ad609fd35679d461920f108a8db055c68f7ed8ec2869bf63c6 | C63: 151097 | D63: LA | E63: 46055 | F63: 46055.692 | G63: 811013715 | H63: LINEA ADHESIVA S.A.S. BIC. | I63: =K63-J63 -> 330000 | J63: 62700 | K63: 392700 | L63: COMPRAS | M63: 46070 | N63: =IFERROR(IF(-_xlfn.DAYS(E63,M63)<0,0,-_xlfn.DAYS(E63,M63)), " - ") -> 15 | O63: FRANCY SALAS | T63: 46071 | U63: NO | W63: MAS 10
A64: Factura electrónica | B64: 8c30ce53be30eece446796590f2a6bd161d41e2ef73eb67e374336a88aba00d85788db9a63915559619efe9781f0571d | C64: 8099 | E64: 46055 | F64: 46055.679 | G64: 901360705 | H64: DELTA TAGS SAS | I64: =K64-J64 -> 432000 | J64: 82080 | K64: 514080 | L64: COMPRAS | M64: 46057 | N64: =IFERROR(IF(-_xlfn.DAYS(E64,M64)<0,0,-_xlfn.DAYS(E64,M64)), " - ") -> 2 | O64: YENIFER PARRA | T64: 46066 | U64: NO | W64: 0 A 5
A65: Factura electrónica | B65: cd9e133162c892bf194494d7050eee8f194ebbd559c899e9a4523be00b79195131b38d38afd952369b1ebda5a891a08d | C65: 3234 | D65: FE | E65: 46055 | F65: 46055.594 | G65: 900563128 | H65: SOLUCIONES SIMMAC S.A.S. | I65: =K65-J65 -> 2116600 | J65: 402154 | K65: 2518754 | L65: COMPRAS | M65: 46057 | N65: =IFERROR(IF(-_xlfn.DAYS(E65,M65)<0,0,-_xlfn.DAYS(E65,M65)), " - ") -> 2 | O65: YENIFER PARRA | T65: 46066 | U65: NO | W65: 0 A 5
A66: Factura electrónica | B66: 896cbc699a77b6eb7d59d464421c726b216a010fe1d8354b451659a9518f94143f3321af6e3230401b53c5752858c206 | C66: 342329 | D66: FFEE | E66: 46055 | F66: 46055.538 | G66: 800049074 | H66: PAPELERIA Y SERVICIOS SAS | I66: =K66-J66 -> 57091 | J66: 10847 | K66: 67938 | L66: COMPRAS | M66: 46057 | N66: =IFERROR(IF(-_xlfn.DAYS(E66,M66)<0,0,-_xlfn.DAYS(E66,M66)), " - ") -> 2 | O66: YENIFER PARRA | T66: 46062 | U66: NO | W66: 0 A 5
A67: Factura electrónica | B67: ccf2409adb9e9eddf6e7ab198623437078936fa1a7d82e38ade03b7408ef2408910cf2b2470c9df9d19a54d5289359e0 | C67: 2773 | D67: EV | E67: 46055 | F67: 46055.595 | G67: 901101232 | H67: INGEVER ASOCIADOS S.A.S. | I67: =K67-J67 -> 3102900 | J67: 589551 | K67: 3692451 | L67: MANTENIMIENTO | M67: 46057 | N67: =IFERROR(IF(-_xlfn.DAYS(E67,M67)<0,0,-_xlfn.DAYS(E67,M67)), " - ") -> 2 | O67: YENIFER PARRA | T67: 46066 | U67: NO | W67: 0 A 5
A68: Factura electrónica | B68: a1f5d659c963a9021045831a660daf77a867c5d7eb35c47aaedc798c740eb289653cf293127944800d7a86128f297895 | C68: 62757 | D68: 475F | E68: 46055 | F68: 46055.646 | G68: 860533413 | H68: IRCC SAS | I68: =K68-J68 -> 77800 | J68: 0 | K68: 77800 | L68: CAJA MENOR | N68: =IFERROR(IF(-_xlfn.DAYS(E68,M68)<0,0,-_xlfn.DAYS(E68,M68)), " - ") -> 0
A69: Factura electrónica | B69: d8eac03e3d12b5a72818d3f01df52a1c27f50c3d0969d90baecd69f13b201d540d9ee1ac25bd9015fd0e8f21a73bf67b | C69: 33450 | D69: FEN | E69: 46055 | F69: 46055.66 | G69: 9522660 | H69: OCTAVIANO TORRES GUEVARA | I69: =K69-J69 -> 1295798.3 | J69: 246201.67 | K69: 1542000 | L69: MANTENIMIENTO | M69: 46057 | N69: =IFERROR(IF(-_xlfn.DAYS(E69,M69)<0,0,-_xlfn.DAYS(E69,M69)), " - ") -> 2 | O69: YENIFER PARRA | T69: 46066 | U69: NO | W69: 0 A 5
A70: Factura electrónica | B70: 734accc4f86e1799e10a85ba864b16a3c8946cca59e2a7baee730a6ef9739c613d7697971a00ee6f1b31cc81c77a30dd | C70: 166544 | D70: 392 | E70: 46055 | F70: 46055.641 | G70: 860000018 | H70: AGENCIA DE VIAJES Y TURISMO AVIATUR S.A.S | I70: =K70-J70 -> 761300 | J70: 135660 | K70: 896960 | L70: COMPRAS | M70: 46057 | N70: =IFERROR(IF(-_xlfn.DAYS(E70,M70)<0,0,-_xlfn.DAYS(E70,M70)), " - ") -> 2 | O70: YENIFER PARRA | T70: 46066 | U70: NO | W70: 0 A 5
A71: Factura electrónica | B71: 69da6efa1822e14763e7d3686e2a8650ca8b4fe7c936756d9a7877b7879fd823b44f9d8cb0459ccc51a7465f879b24a7 | C71: 21736 | D71: FE | E71: 46055 | F71: 46055.412 | G71: 900083323 | H71: AGENCIA DE INVERSIONES PROSPERAR S.A.S. | I71: =K71-J71 -> 10499723 | J71: 1774638 | K71: 12274361 | L71: CONTABILIDAD | M71: 46056 | N71: =IFERROR(IF(-_xlfn.DAYS(E71,M71)<0,0,-_xlfn.DAYS(E71,M71)), " - ") -> 1 | O71: NATALIA BERNAZA | T71: 46057 | U71: SI | W71: 0 A 5
A72: Factura electrónica | B72: 3e14e6903b0cfd7de9a385453e72b54777c1e128bd043768cd7028e1218d5c746403c6fff2958da9c16a4c8b1d483f2b | C72: 342403 | D72: FFEE | E72: 46055 | F72: 46055.653 | G72: 800049074 | H72: PAPELERIA Y SERVICIOS SAS | I72: =K72-J72 -> 15373 | J72: 2921 | K72: 18294 | L72: COMPRAS | M72: 46058 | N72: =IFERROR(IF(-_xlfn.DAYS(E72,M72)<0,0,-_xlfn.DAYS(E72,M72)), " - ") -> 3 | O72: YENIFER PARRA | T72: 46066 | U72: NO | W72: 0 A 5
A73: Factura electrónica | B73: 67c3c723f54836fcaa9d26bdc05a6849d8302d58d93130fdb55b1a83d9bf6c56e954ca5b6309474f6c830577b7df3792 | C73: 19591 | D73: FE | E73: 46055 | F73: 46055.65 | G73: 890903388 | H73: CLUB UNION SA | I73: =K73-J73 -> 1699072 | J73: 322823.68 | K73: 2021895.7 | L73: CAJA MENOR | N73: =IFERROR(IF(-_xlfn.DAYS(E73,M73)<0,0,-_xlfn.DAYS(E73,M73)), " - ") -> 0 | T73: 46057 | U73: NO
A74: Factura electrónica | B74: bd17e1cedd7df5b8241f7d7fb05e951c4ff59f34ab038d45c294ebe0585cc1e001390ecd150ac630d0c27d28aecf8452 | C74: 1107568 | D74: A203 | E74: 46055 | F74: 46055.677 | G74: 900155107 | H74: Cencosud Colombia S.A. | I74: =K74-J74 -> 9600 | J74: 0 | K74: 9600 | L74: CAJA MENOR | N74: =IFERROR(IF(-_xlfn.DAYS(E74,M74)<0,0,-_xlfn.DAYS(E74,M74)), " - ") -> 0
A75: Factura electrónica | B75: f8122b24127270e9d56842c26c87f43ab60d3c4805300a3eb170ef7d53e7c444bc8bbca7aa7da320e718633d05da29ea | C75: 227 | D75: ARB | E75: 46055 | F75: 46055.609 | G75: 900654063 | H75: ARBELAEZ ASOCIADOS SAS | I75: =K75-J75 -> 2627500 | J75: 499225 | K75: 3126725 | L75: CONTABILIDAD | M75: 46056 | N75: =IFERROR(IF(-_xlfn.DAYS(E75,M75)<0,0,-_xlfn.DAYS(E75,M75)), " - ") -> 1 | O75: NATALIA BERNAZA | T75: 46057 | U75: NO | W75: 0 A 5
A76: Factura electrónica | B76: fd1130745099d661b580615e503e2833cb3962c295db31149ef666dba5ca102eadc27332765b1350b31fd0b26b08f1ee | C76: 29937 | D76: FE | E76: 46055 | F76: 46055.604 | G76: 901356289 | H76: COCINARIO CATERING S.A.S | I76: =K76-J76 -> 432000 | J76: 5130 | K76: 437130 | L76: GERENCIA | M76: 46055 | N76: =IFERROR(IF(-_xlfn.DAYS(E76,M76)<0,0,-_xlfn.DAYS(E76,M76)), " - ") -> 0 | O76: ELIANA GOMEZ | W76: 0 A 5
A77: Nota de crédito electrónica | B77: 38c8bbf789abe069c5a1a96d7f502ee4ce11c338fc0c00a1f6507585faa26b932956cc1abde202011983f66e76bddf86 | C77: 536380 | D77: NC01 | E77: 46055 | F77: 46055.542 | G77: 800185306 | H77: COLVANES S.A.S | I77: =K77-J77 -> 17500 | J77: 0 | K77: 17500 | L77: CAJA MENOR | N77: =IFERROR(IF(-_xlfn.DAYS(E77,M77)<0,0,-_xlfn.DAYS(E77,M77)), " - ") -> 0
A78: Factura electrónica | B78: 8765bec3dcfabf3e25b1c28130f7ca30dd982b8b503ba3382571a0f08b702d9e2d52672255488e0886db430205501a66 | C78: 139334 | D78: F4P0 | E78: 46055 | F78: 46055.55 | G78: 900276962 | H78: D1 S A S | I78: =K78-J78 -> 40606.61 | J78: 5193.39 | K78: 45800 | L78: CAJA MENOR | N78: =IFERROR(IF(-_xlfn.DAYS(E78,M78)<0,0,-_xlfn.DAYS(E78,M78)), " - ") -> 0
A79: Factura electrónica | B79: 20f63dfd6a52799f9b821262f3ff3b90145f654234bd11a422ff164fbf1b6834150e5bc222988686bd5757c2248f5bce | C79: 104236 | D79: FAE | E79: 46055 | F79: 46055.491 | G79: 830120839 | H79: MULTISUMINISTROS INDUSTRIALES S A S | I79: =K79-J79 -> 118002 | J79: 22420 | K79: 140422 | L79: COMPRAS | M79: 46059 | N79: =IFERROR(IF(-_xlfn.DAYS(E79,M79)<0,0,-_xlfn.DAYS(E79,M79)), " - ") -> 4 | O79: YENIFER PARRA | T79: 46062 | U79: NO | W79: 0 A 5
A80: Factura electrónica | B80: 093dbe59938a78b56fe10ec160c14b71e3abe1d58c236bd4a60a6fa1377b411ccd462371edf999b93e57de227ec254ed | C80: 100 | D80: FEDV | E80: 46055 | F80: 46055.484 | G80: 42790604 | H80: MARY LUZ JARAMILLO DIEZ | I80: =K80-J80 -> 16479495 | J80: 3131104 | K80: 19610599 | L80: CONTABILIDAD | M80: 46056 | N80: =IFERROR(IF(-_xlfn.DAYS(E80,M80)<0,0,-_xlfn.DAYS(E80,M80)), " - ") -> 1 | O80: NATALIA BERNAZA | T80: 46057 | U80: NO | W80: 0 A 5
A81: Factura electrónica | B81: 770d76928d42f49d0798b57c9c3befb5b44ceaa96b9123c7a6bc925f820fea69a7baf24e49b3c4ec61f6dfad97ad4a70 | C81: 3542 | D81: FE | E81: 46055 | F81: 46055.47 | G81: 811027589 | H81: Zonalogística S.A.S ZLG | I81: =K81-J81 -> 18072600 | J81: 3433794 | K81: 21506394 | L81: GERENCIA | M81: 46056 | N81: =IFERROR(IF(-_xlfn.DAYS(E81,M81)<0,0,-_xlfn.DAYS(E81,M81)), " - ") -> 1 | O81: ANGELA SEPULVEDA | T81: 46057 | U81: SI | W81: 0 A 5
A82: Factura electrónica | B82: b77773ea2268cf6e1658ee6556324e003294a8f05d79c7bca2beb4acb3179f2384ebbfe3f0e79dcdc804e82d12f20e9d | C82: 17612898 | D82: 014F | E82: 46055 | F82: 46055.455 | G82: 860037013 | H82: COMPAÑÍA MUNDIAL DE SEGUROS S.A. | I82: =K82-J82 -> 256200 | J82: 0 | K82: 256200 | L82: COMPRAS | M82: 46056 | N82: =IFERROR(IF(-_xlfn.DAYS(E82,M82)<0,0,-_xlfn.DAYS(E82,M82)), " - ") -> 1 | O82: YENIFER PARRA | T82: 46062 | U82: NO | W82: 0 A 5
A83: Factura electrónica | B83: 87fbb8b225cb83d2531212cfe1ef201c4e5db182a3b1510db6a6b2bf94442523a2e90a4c83fbb6210ef7b21931007636 | C83: 102 | D83: FEKE | E83: 46055 | F83: 46055.454 | G83: 901693444 | H83: KEYSTONE INVERSIONES SAS | I83: =K83-J83 -> 33661928 | J83: 6395766.3 | K83: 40057694 | L83: CONTABILIDAD | M83: 46056 | N83: =IFERROR(IF(-_xlfn.DAYS(E83,M83)<0,0,-_xlfn.DAYS(E83,M83)), " - ") -> 1 | O83: NATALIA BERNAZA | T83: 46057 | U83: SI | W83: 0 A 5
A84: Factura electrónica | B84: 6304788b78ec3e94757ac24b6057f6cc0f124e7c41df0fe6275d42b923810558c9aa6c06f859955147e7d7d8d8b25339 | C84: 93727 | D84: ES | E84: 46055 | F84: 46055.444 | G84: 800128989 | H84: GUIMAR SEGURIDAD INDUSTRIAL S.A.S | I84: =K84-J84 -> 196014 | J84: 37242.66 | K84: 233256.66 | L84: SSTA | M84: 46057 | N84: =IFERROR(IF(-_xlfn.DAYS(E84,M84)<0,0,-_xlfn.DAYS(E84,M84)), " - ") -> 2 | O84: YENIFER PARRA | T84: 46059 | U84: NO | W84: 0 A 5
A85: Factura electrónica | B85: 42a8222119b3e65599eb59edddef34aa1a727bc4a2c41cd64799dfd37f438a654ddbaa8fe94fa652c534d2e1c09a822d | C85: 166428 | D85: 392 | E85: 46055 | F85: 46055.394 | G85: 860000018 | H85: AGENCIA DE VIAJES Y TURISMO AVIATUR S.A.S | I85: =K85-J85 -> 1603248 | J85: 264480 | K85: 1867728 | L85: COMPRAS | M85: 46056 | N85: =IFERROR(IF(-_xlfn.DAYS(E85,M85)<0,0,-_xlfn.DAYS(E85,M85)), " - ") -> 1 | O85: YENIFER PARRA | T85: 46066 | U85: NO | W85: 0 A 5
A86: Factura electrónica | B86: 93854d021de212b450f0866e2aaef2f07524271d8da1c7840633fe834f24fd95fbd1d789efdead3cb6791631c0af5e61 | C86: 194925 | D86: FE | E86: 46055 | F86: 46055.368 | G86: 800180675 | H86: INMOBILIARIA RENTAR SAS | I86: =K86-J86 -> 1965813 | J86: 0 | K86: 1965813 | L86: CONTABILIDAD | M86: 46056 | N86: =IFERROR(IF(-_xlfn.DAYS(E86,M86)<0,0,-_xlfn.DAYS(E86,M86)), " - ") -> 1 | O86: NATALIA BERNAZA | T86: 46057 | U86: NO | W86: 0 A 5
A87: Factura electrónica | B87: eb6853afaf843e5c573413e231549e4af58459cf7fe726ccbc1c9fa096091970121116fd26e1b537ca6ee60e8d24e227 | C87: 722068 | D87: FMED | E87: 46055 | F87: 46055.343 | G87: 890915475 | H87: EMPAQUETADURAS Y EMPAQUES S.A. | I87: =K87-J87 -> 1565085 | J87: 297366.15 | K87: 1862451.1 | L87: COMPRAS | M87: 46058 | N87: =IFERROR(IF(-_xlfn.DAYS(E87,M87)<0,0,-_xlfn.DAYS(E87,M87)), " - ") -> 3 | O87: YENIFER PARRA | T87: 46066 | U87: NO | W87: 0 A 5
A88: Factura electrónica | B88: 38051e67e805a6c6c1f519d518db418da6c879583999e3f79d284a3b6c273d5fd9c7bca7b28b4cf43469e9745a11cfc1 | C88: 722052 | D88: FMED | E88: 46055 | F88: 46055.323 | G88: 890915475 | H88: EMPAQUETADURAS Y EMPAQUES S.A. | I88: =K88-J88 -> 787130 | J88: 149554.7 | K88: 936684.7 | L88: COMPRAS | M88: 46058 | N88: =IFERROR(IF(-_xlfn.DAYS(E88,M88)<0,0,-_xlfn.DAYS(E88,M88)), " - ") -> 3 | O88: YENIFER PARRA | T88: 46066 | U88: NO | W88: 0 A 5
A89: Factura electrónica | B89: 1e979bb750a3792eee0a41fb0d85d2f6d7e5a6efa35fb142b7170c63c734bc7190ef6d357589aac3fb6f8b96bce08a07 | C89: 512 | D89: WC | E89: 46055 | F89: 46055.306 | G89: 901741749 | H89: WORLD CRANES SAS | I89: =K89-J89 -> 2500000 | J89: 475000 | K89: 2975000 | L89: MANTENIMIENTO | M89: 46056 | N89: =IFERROR(IF(-_xlfn.DAYS(E89,M89)<0,0,-_xlfn.DAYS(E89,M89)), " - ") -> 1 | O89: YENIFER PARRA | T89: 46066 | U89: NO | W89: 0 A 5
A90: Factura electrónica | B90: 69757092c39f894e645437099eccbab18a9bd79d92b89968738ce9cd5c87c8f8d374b5ad5304d5349afa545048ae701f | C90: 563988 | D90: AH | E90: 46055 | F90: 46055.303 | G90: 890800788 | H90: SUMATEC S.A.S BIC | I90: =K90-J90 -> 165740 | J90: 31491 | K90: 197231 | L90: COMPRAS | M90: 46056 | N90: =IFERROR(IF(-_xlfn.DAYS(E90,M90)<0,0,-_xlfn.DAYS(E90,M90)), " - ") -> 1 | O90: YENIFER PARRA | T90: 46066 | U90: NO | W90: 0 A 5
... A97: Factura electrónica | B97: cb9eb6f1a85ad96cbb6434d53c490ff0957789a688b4da3daf49388ec66e8fbc05f4def3da3c4853cb35c0b04a74ed55 | C97: 331 | D97: FEFL | E97: 46055 | F97: 46055.347 | G97: 900484386 | H97: FLOSILDA S.A.S | I97: =K97-J97 -> 27859250 | J97: 5293257.5 | K97: 33152508 | L97: CONTABILIDAD | M97: 46056 | N97: =IFERROR(IF(-_xlfn.DAYS(E97,M97)<0,0,-_xlfn.DAYS(E97,M97)), " - ") -> 1 | O97: NATALIA BERNAZA | T97: 46057 | U97: NO | W97: 0 A 5
A98: Factura electrónica | B98: c66f5c42410d884d3b847f8a493147564cc2b2a0097a3e7786c58fe5935c003d1ca7d04f41f839065840302460531020 | C98: 206 | D98: POS | E98: 46055 | F98: 46055.343 | G98: 901643359 | H98: JM Y GF CAFE SAS | I98: =K98-J98 -> 40000 | J98: 0 | K98: 40000 | L98: CAJA MENOR | N98: =IFERROR(IF(-_xlfn.DAYS(E98,M98)<0,0,-_xlfn.DAYS(E98,M98)), " - ") -> 0 | T98: 46073 | U98: NO
A99: Factura electrónica | B99: 496e68f256196bdf1f4cd4ef096742b1ec8613972d55bef223b26204bda7955171d2d362cef32739b6555f4a4ef2ad37 | C99: 3678 | D99: RIND | E99: 46055 | F99: 46055.259 | G99: 901609691 | H99: RINDEGASTOS COLOMBIA S.A.S. | I99: =K99-J99 -> 719200 | J99: 136648 | K99: 855848 | L99: CONTABILIDAD | M99: 46056 | N99: =IFERROR(IF(-_xlfn.DAYS(E99,M99)<0,0,-_xlfn.DAYS(E99,M99)), " - ") -> 1 | O99: NATALIA BERNAZA | T99: 46057 | U99: NO | W99: 0 A 5
A100: Factura electrónica | B100: 8f7e15cae46d0ef920d5eacadc8f804350b1ca485d8a19dba1182452d8d8f654d45c3025bed8e16e3b589a5ac518bcee | C100: 75703 | D100: FEUN | E100: 46055 | F100: 46057.408 | G100: 816005306 | H100: SAYONARA SAS | I100: =K100-J100 -> 68400 | K100: 68400 | L100: CAJA MENOR | N100: =IFERROR(IF(-_xlfn.DAYS(E100,M100)<0,0,-_xlfn.DAYS(E100,M100)), " - ") -> 0
A101: Factura electrónica | B101: 261136844465ef29849c3f38e7282d1088ef0a2e8f816e9058f709f37fda510523d92dfbc6a62398f30da2132e1f663f | C101: 419762 | D101: MABF | E101: 46056 | F101: 46056.774 | G101: 900053978 | H101: GLOBAL MENSAJERIA S.A.S. | I101: =K101-J101 -> 38900 | J101: 0 | K101: 38900 | L101: COMPRAS | M101: 46066 | N101: =IFERROR(IF(-_xlfn.DAYS(E101,M101)<0,0,-_xlfn.DAYS(E101,M101)), " - ") -> 10 | O101: FRANCY SALAS | T101: 46071 | U101: NO | W101: 6 A 10
A102: Factura electrónica | B102: 3f8e59b4d48188854aca358f41c20308e5bd6d5ca03de3dbd70be6633f44518e3995ed140b3e904665ccfa1d51a43497 | C102: 55803 | D102: FVE | E102: 46056 | F102: 46056.717 | G102: 900650486 | H102: DISTRIBUIDORA DE SOFTWARE Y MOVILIDAD S.A.S | I102: =K102-J102 -> 2016806.7 | J102: 383193.28 | K102: 2400000 | L102: TI | M102: 46058 | N102: =IFERROR(IF(-_xlfn.DAYS(E102,M102)<0,0,-_xlfn.DAYS(E102,M102)), " - ") -> 2 | O102: YENIFER PARRA | T102: 46059 | U102: NO | W102: 0 A 5
A103: Factura electrónica | B103: ed22494a7dacea5d9fad7a41357b5f1e1ed42a45d7eb087d71c958dd6846687c39094aa31bb807ca5d20f88b80c001f6 | C103: 1351 | D103: FE | E103: 46056 | F103: 46056.705 | G103: 901950863 | H103: INVERSIONES TORNILLOS Y MANGUERAS S.A.S | I103: =K103-J103 -> 1092000 | J103: 207480 | K103: 1299480 | L103: MANTENIMIENTO | M103: 46057 | N103: =IFERROR(IF(-_xlfn.DAYS(E103,M103)<0,0,-_xlfn.DAYS(E103,M103)), " - ") -> 1 | O103: YENIFER PARRA | T103: 46066 | U103: NO | W103: 0 A 5
A104: Factura electrónica | B104: e5647a6f9a8acb1fc39005e6fdcd0e2381e255f9b92860969f07dd346afb6410eea6c5f8f186cb8e0f4fd7ff15b69d1f | C104: 1353 | D104: FE | E104: 46056 | F104: 46056.709 | G104: 901950863 | H104: INVERSIONES TORNILLOS Y MANGUERAS S.A.S | I104: =K104-J104 -> 130000 | J104: 24700 | K104: 154700 | L104: MANTENIMIENTO | M104: 46057 | N104: =IFERROR(IF(-_xlfn.DAYS(E104,M104)<0,0,-_xlfn.DAYS(E104,M104)), " - ") -> 1 | O104: YENIFER PARRA | T104: 46066 | U104: NO | W104: 0 A 5
A105: Factura electrónica | B105: 3caf743f93f4bb22b966362d4de31a8aa27be9c60b9b2b1d3d6073f6206aeba3325cbf30e985c33da9b0ff2a6e50db8b | C105: 1352 | D105: FE | E105: 46056 | F105: 46056.706 | G105: 901950863 | H105: INVERSIONES TORNILLOS Y MANGUERAS S.A.S | I105: =K105-J105 -> 1092000 | J105: 207480 | K105: 1299480 | L105: MANTENIMIENTO | M105: 46057 | N105: =IFERROR(IF(-_xlfn.DAYS(E105,M105)<0,0,-_xlfn.DAYS(E105,M105)), " - ") -> 1 | O105: YENIFER PARRA | T105: 46066 | U105: NO | W105: 0 A 5
A106: Factura electrónica | B106: 9e727e23f9de2c5b0f9207993e0e40840e0258ae8642eaa8a3a69574075db8c1d65d42c7f87998f1b8e2492885fad7aa | C106: 722510 | D106: FMED | E106: 46056 | F106: 46056.676 | G106: 890915475 | H106: EMPAQUETADURAS Y EMPAQUES S.A. | I106: =K106-J106 -> 146700 | J106: 27873 | K106: 174573 | L106: COMPRAS | M106: 46058 | N106: =IFERROR(IF(-_xlfn.DAYS(E106,M106)<0,0,-_xlfn.DAYS(E106,M106)), " - ") -> 2 | O106: YENIFER PARRA | T106: 46059 | U106: NO | W106: 0 A 5
...

Sheet MARZO
B1: CUFE/CUDE | C1: Folio | D1: Prefijo | E1: Fecha Emisión | F1: Fecha Recepción | G1: NIT | H1: Nombre Emisor | I1: Subtotal | J1: IVA | K1: Total | L1: Responsable | M1: FECHA DE ENTREGA | N1: DÍAS DE ENTREGA A CONTABILIDAD | O1: QUIEN ENTREGA | P1: NOMBRE A QUIEN SE DEVUELVE | Q1: FECHA DEVOLUCION | R1: REINTEGRO | S1: RANGO DE ENTREGA A TESORERIA DIAS | T1: FECHA ENTREGA TESORERIA | U1: REQUIERE FIRMA DE GERENCIA | V1: FIRMADAS | W1: RANGO DÍAS DE ENTREGA | X1: MES DEL SERVICIO
A2: Factura electrónica | B2: 6e1893a7f6ca082c1b22dd31c7963fa37f52cf635ef77130a325891a0742c51fd33b4b469f5d1286b6fae2635841075e | C2: 3900 | D2: RIND | E2: 46082 | F2: 46082.689 | G2: 901609691 | H2: RINDEGASTOS COLOMBIA S.A.S. | I2: =K2-J2 -> 742400 | J2: 141056 | K2: 883456 | L2: CONTABILIDAD | M2: 46084 | N2: =IFERROR(IF(-_xlfn.DAYS(E2,M2)<0,0,-_xlfn.DAYS(E2,M2)), " - ") -> 2 | O2: NATALIA BERNAZA | T2: 46085 | U2: NO | W2: 0 A 5
A3: Factura electrónica | B3: f166054df051ee247b3b6dfae09e7a85ace4193591c228425ef96fabe0ab147f7ea10d79d351b27df5bc946e82d5905d | C3: 292542251 | D3: 3 | E3: 46082 | F3: 46086.879 | G3: 800153993 | H3: COMUNICACION CELULAR S A COMCEL S A | I3: =K3-J3 -> 1967321 | J3: 44197.99 | K3: 2011519 | L3: TI | M3: 46097 | N3: =IFERROR(IF(-_xlfn.DAYS(E3,M3)<0,0,-_xlfn.DAYS(E3,M3)), " - ") -> 15 | O3: JAIME GARCIA | T3: 46099 | U3: NO | W3: MAS DE 10
A4: Factura electrónica | B4: e2a472c6b736117ab460068855dd61885fe01f72645739bf9c300bb14ec2b29517c0ca4ca3f0e0825c0cd8afd5f9b1af | C4: 41146 | D4: AEZY | E4: 46082 | F4: 46082.335 | G4: 900610585 | H4: Easytaxi Colombia SAS | I4: =K4-J4 -> 2793209 | J4: 73201 | K4: 2866410 | L4: COMPRAS | M4: 46083 | N4: =IFERROR(IF(-_xlfn.DAYS(E4,M4)<0,0,-_xlfn.DAYS(E4,M4)), " - ") -> 1 | O4: FRANCY SALAS | T4: 46086 | U4: NO | W4: 0 A 5
A5: Factura electrónica | B5: e1c5da3d561d703cd18cccc12e450474712a5dd55badff33633a96edad1a582168613ca775df12f49224c4b1adee664a | C5: 657001 | D5: ECCO | E5: 46083 | F5: 46083.834 | G5: 811009788 | H5: DISTRACOM S.A. | I5: =K5-J5 -> 111368 | J5: 0 | K5: 111368 | L5: COMPRAS | M5: 46086 | N5: =IFERROR(IF(-_xlfn.DAYS(E5,M5)<0,0,-_xlfn.DAYS(E5,M5)), " - ") -> 3 | O5: FRANCY SALAS | T5: 46087 | W5: 0 A 5
A6: Factura electrónica | B6: 4ce8e965d2ef76e7155ed377a6e69559b716067475957f760e01b642d5d3ad38c158941749b1d34a9ace50e20cc794e1 | C6: 18 | D6: FVE | E6: 46083 | F6: 46083.588 | G6: 902020620 | H6: REDECILLAS POLI SAS | I6: =K6-J6 -> 144450 | J6: 27445.5 | K6: 171895.5 | L6: COMPRAS | M6: 46097 | N6: =IFERROR(IF(-_xlfn.DAYS(E6,M6)<0,0,-_xlfn.DAYS(E6,M6)), " - ") -> 14 | O6: FRANCY SALAS | T6: 46098 | U6: NO | W6: MAS DE 10
A7: Factura electrónica | B7: 7c5dc27a64658decb9aab7b66087c5d7f4d9553fd4e8520450a2fc5a3dc5f5068ec657328686dc6717723fd22470faaf | C7: 244 | D7: ESAB | E7: 46083 | F7: 46083.994 | G7: 901200557 | H7: AFAT SAS | I7: =K7-J7 -> 36050.42 | J7: 6849.58 | K7: 42900 | L7: CAJA MENOR | N7: =IFERROR(IF(-_xlfn.DAYS(E7,M7)<0,0,-_xlfn.DAYS(E7,M7)), " - ") -> 0
A8: Factura electrónica | B8: 465e5db436a1b6cc640e9df3830635796e7620d1bc23458f346b836eb9da499830a8e7c2c9ec2e0faf8b41dfc9aaa4eb | C8: 6457 | E8: 46083 | F8: 46083.915 | G8: 32150739 | H8: NATALIA ANDREA ACOSTA COLORADO | I8: =K8-J8 -> 707400 | J8: 0 | K8: 707400 | L8: GESTION HUMANA | M8: 46087 | N8: =IFERROR(IF(-_xlfn.DAYS(E8,M8)<0,0,-_xlfn.DAYS(E8,M8)), " - ") -> 4 | O8: FRANCY SALAS | T8: 46091 | U8: NO | W8: 0 A 5
A9: Factura electrónica | B9: 5a24050e65952960150ac5d122c6f91b464036e090878d202f3430c1bbcbf237803f094f4421d3a5ef51730176e28a79 | C9: 51569 | D9: 321F | E9: 46083 | F9: 46083.757 | G9: 860533413 | H9: IRCC SAS | I9: =K9-J9 -> 30900 | J9: 0 | K9: 30900 | L9: CAJA MENOR | N9: =IFERROR(IF(-_xlfn.DAYS(E9,M9)<0,0,-_xlfn.DAYS(E9,M9)), " - ") -> 0
A10: Factura electrónica | B10: 7b3fd961227b66183d04e55ce2d52b37ef311aab02d5dbe8f63f4b87c378bfde922428c624efd6e59cabaec74b3579a9 | C10: 51568 | D10: 321F | E10: 46083 | F10: 46083.756 | G10: 860533413 | H10: IRCC SAS | I10: =K10-J10 -> 33900 | J10: 0 | K10: 33900 | L10: CAJA MENOR | N10: =IFERROR(IF(-_xlfn.DAYS(E10,M10)<0,0,-_xlfn.DAYS(E10,M10)), " - ") -> 0
A11: Factura electrónica | B11: 71f36e3301797da4a504eec51cc92fe3c382a663b5f5856133dfaf4f500ff45f4e908fed77cb5e1e2373d3595607e5e8 | C11: 51567 | D11: 321F | E11: 46083 | F11: 46083.754 | G11: 860533413 | H11: IRCC SAS | I11: =K11-J11 -> 35900 | J11: 0 | K11: 35900 | L11: CAJA MENOR | N11: =IFERROR(IF(-_xlfn.DAYS(E11,M11)<0,0,-_xlfn.DAYS(E11,M11)), " - ") -> 0
A12: Factura electrónica | B12: 93e70c1c1082515055f57bcf7f0bc55e36c6a65f1819d68b96e8baeba726273f4ce47077f7233ce305dacccbc64525f4 | C12: 5025 | D12: FEIT | E12: 46083 | F12: 46083.74 | G12: 901042685 | H12: ITTERACTIVO S.A.S. | I12: =K12-J12 -> 1593963 | J12: 0 | K12: 1593963 | L12: TI | M12: 46084 | N12: =IFERROR(IF(-_xlfn.DAYS(E12,M12)<0,0,-_xlfn.DAYS(E12,M12)), " - ") -> 1 | O12: JACOBO GARCIA | T12: 46087 | W12: 0 A 5
A13: Factura electrónica | B13: bff9d38813428cec2887ad76b5058c2f80b72b0c149594702ba9fb172d5c75d7bf62a79e6ee22c3b40ce1eef4a02ab0b | C13: 19773 | D13: FE | E13: 46083 | F13: 46083.673 | G13: 890903388 | H13: CLUB UNION SA | I13: =K13-J13 -> 1699072 | J13: 322823.68 | K13: 2021895.7 | L13: CONTABILIDAD | M13: 46084 | N13: =IFERROR(IF(-_xlfn.DAYS(E13,M13)<0,0,-_xlfn.DAYS(E13,M13)), " - ") -> 1 | O13: NATALIA BERNAZA | T13: 46085 | U13: NO | W13: 0 A 5
A14: Factura electrónica | B14: bff40a367d86a9ed600d35b908a2c2fef7f5ea52f3cb31c29d6cb291963e2ae41eb5d75e51057cd581aefd945f148379 | C14: 18982 | D14: INIM | E14: 46083 | F14: 46083.649 | G14: 900237741 | H14: INVERSIONES IMPRIMA SAS | I14: =K14-J14 -> 110000 | J14: 20900 | K14: 130900 | L14: COMPRAS | M14: 46084 | N14: =IFERROR(IF(-_xlfn.DAYS(E14,M14)<0,0,-_xlfn.DAYS(E14,M14)), " - ") -> 1 | O14: FRANCY SALAS | T14: 46086 | W14: 0 A 5
A15: Factura electrónica | B15: 69b894515016dd0e63c6712d1a5650c714fcdecf39847f7ebe57b10ff99185b45d450799857ffad43af781994b947a47 | C15: 18981 | D15: INIM | E15: 46083 | F15: 46083.648 | G15: 900237741 | H15: INVERSIONES IMPRIMA SAS | I15: =K15-J15 -> 82500 | J15: 15675 | K15: 98175 | L15: COMPRAS | M15: 46084 | N15: =IFERROR(IF(-_xlfn.DAYS(E15,M15)<0,0,-_xlfn.DAYS(E15,M15)), " - ") -> 1 | O15: FRANCY SALAS | T15: 46086 | U15: NO | W15: 0 A 5
A16: Factura electrónica | B16: 2311d5d462e93d5d6f62f30e9d33e07be610ee4d5f01fdcb826c0ea7e6e20a55ca6503441dd5f6c24b0bf36d6c6e82b0 | C16: 18980 | D16: INIM | E16: 46083 | F16: 46083.648 | G16: 900237741 | H16: INVERSIONES IMPRIMA SAS | I16: =K16-J16 -> 270000 | J16: 51300 | K16: 321300 | L16: COMPRAS | M16: 46084 | N16: =IFERROR(IF(-_xlfn.DAYS(E16,M16)<0,0,-_xlfn.DAYS(E16,M16)), " - ") -> 1 | O16: FRANCY SALAS | T16: 46086 | U16: NO | W16: 0 A 5
A17: Factura electrónica | B17: bf60885df9014d1bdabd6fceae2117c9b49a25a5a2453e767290f7a0880d467cc111b2b4b268bfa1489ff079dfaaf965 | C17: 12671 | D17: FE | E17: 46083 | F17: 46083.617 | G17: 900420442 | H17: INSTRUMENTOS PARTES S.A.S. | I17: =K17-J17 -> 581434 | J17: 110472.46 | K17: 691906.46 | L17: MANTENIMIENTO | M17: 46085 | N17: =IFERROR(IF(-_xlfn.DAYS(E17,M17)<0,0,-_xlfn.DAYS(E17,M17)), " - ") -> 2 | O17: FRANCY SALAS | T17: 46086 | U17: NO | W17: 0 A 5
A18: Factura electrónica | B18: ec9a72095ec16ccfc7be79fb72e17a23e1046ff5d8b832742b21f411645d93e78f79d9171d9582e278d0de690fa47fb8 | C18: 12670 | D18: FE | E18: 46083 | F18: 46083.609 | G18: 900420442 | H18: INSTRUMENTOS PARTES S.A.S. | I18: =K18-J18 -> 3537600 | J18: 672144 | K18: 4209744 | L18: MANTENIMIENTO | M18: 46085 | N18: =IFERROR(IF(-_xlfn.DAYS(E18,M18)<0,0,-_xlfn.DAYS(E18,M18)), " - ") -> 2 | O18: FRANCY SALAS | T18: 46094 | U18: NO | W18: 0 A 5
A19: Factura electrónica | B19: d67513e7638989d30665b71905e17ad219d13818862cd768c6b12bbcb12f3c11f1d61254fdea623072ddab9a18753507 | C19: 12669 | D19: FE | E19: 46083 | F19: 46083.609 | G19: 900420442 | H19: INSTRUMENTOS PARTES S.A.S. | I19: =K19-J19 -> 177100 | J19: 33649 | K19: 210749 | L19: MANTENIMIENTO | M19: 46085 | N19: =IFERROR(IF(-_xlfn.DAYS(E19,M19)<0,0,-_xlfn.DAYS(E19,M19)), " - ") -> 2 | O19: FRANCY SALAS | T19: 46086 | U19: NO | W19: 0 A 5
A20: Factura electrónica | B20: e19b861ae843069572105fcfb10eb09d7085c726a5101a781a88bbc02a05723b5173330311b96239bb236e6163acb7c3 | C20: 34140348 | D20: FE09 | E20: 46083 | F20: 46083.603 | G20: 809002625 | H20: INTERNACIONAL DE ELECTRICOS S.A.S | I20: =K20-J20 -> 1014900 | J20: 192831 | K20: 1207731 | L20: MANTENIMIENTO | M20: 46086 | N20: =IFERROR(IF(-_xlfn.DAYS(E20,M20)<0,0,-_xlfn.DAYS(E20,M20)), " - ") -> 3 | O20: FRANCY SALAS | T20: 46094 | U20: NO | W20: 0 A 5
A21: Factura electrónica | B21: c54a54a4848825ba3df25f9207314a4a1e856e5386c32de996e17f9aac9146ec8b8230108fe68f322a5ae0100901c2b8 | C21: 726599 | D21: FMED | E21: 46083 | F21: 46083.598 | G21: 890915475 | H21: EMPAQUETADURAS Y EMPAQUES S.A. | I21: =K21-J21 -> 192572 | J21: 36588.68 | K21: 229160.68 | L21: COMPRAS | M21: 46084 | N21: =IFERROR(IF(-_xlfn.DAYS(E21,M21)<0,0,-_xlfn.DAYS(E21,M21)), " - ") -> 1 | O21: FRANCY SALAS | T21: 46086 | U21: NO | W21: 0 A 5
A22: Factura electrónica | B22: d73b16e3a7df071193bc785d282c8a0c20be8d5540abacd0945b7c709fe9bcfd8b97f8ffa5156a9a03de1d26ecaac18f | C22: 346448 | D22: FFEE | E22: 46083 | F22: 46083.555 | G22: 800049074 | H22: PAPELERIA Y SERVICIOS SAS | I22: =K22-J22 -> 1100637 | J22: 187817 | K22: 1288454 | L22: COMPRAS | M22: 46087 | N22: =IFERROR(IF(-_xlfn.DAYS(E22,M22)<0,0,-_xlfn.DAYS(E22,M22)), " - ") -> 4 | O22: FRANCY SALAS | T22: 46094 | U22: NO | W22: 0 A 5
A23: Factura electrónica | B23: c804b968c2af3fbb7f73a93d1db0ec85e17eea1355e8d5fd7a9a30ad7a5fb9fcc85a44186072ea1e553931dff38459e5 | C23: 346483 | D23: FFEE | E23: 46083 | F23: 46083.556 | G23: 800049074 | H23: PAPELERIA Y SERVICIOS SAS | I23: =K23-J23 -> 81286 | J23: 4792 | K23: 86078 | L23: COMPRAS | M23: 46085 | N23: =IFERROR(IF(-_xlfn.DAYS(E23,M23)<0,0,-_xlfn.DAYS(E23,M23)), " - ") -> 2 | O23: FRANCY SALAS | T23: 46086 | U23: NO | W23: 0 A 5
A24: Factura electrónica | B24: 2faf2c03201a289199c6774d307de871f936b62645cd4ba118948971ed5bccd930269890f7a6e0cdf2eb93897492be3b | C24: 22134 | D24: FE | E24: 46083 | F24: 46083.525 | G24: 900083323 | H24: AGENCIA DE INVERSIONES PROSPERAR S.A.S. | I24: =K24-J24 -> 10707388 | J24: 1848510 | K24: 12555898 | L24: CONTABILIDAD | M24: 46084 | N24: =IFERROR(IF(-_xlfn.DAYS(E24,M24)<0,0,-_xlfn.DAYS(E24,M24)), " - ") -> 1 | O24: NATALIA BERNAZA | T24: 46085 | U24: NO | W24: 0 A 5
A25: Factura electrónica | B25: ff94655843b56f3fe5f5e558eba296ab12473487a6cb22e076d75e8ec12ad3fa266072f225f598df553ff68122bec015 | C25: 22135 | D25: FE | E25: 46083 | F25: 46083.525 | G25: 900083323 | H25: AGENCIA DE INVERSIONES PROSPERAR S.A.S. | I25: =K25-J25 -> 10707388 | J25: 1848510 | K25: 12555898 | L25: CONTABILIDAD | M25: 46084 | N25: =IFERROR(IF(-_xlfn.DAYS(E25,M25)<0,0,-_xlfn.DAYS(E25,M25)), " - ") -> 1 | O25: NATALIA BERNAZA | T25: 46085 | U25: NO | W25: 0 A 5
A26: Factura electrónica | B26: 4129f246ddab8f2034bda4b450328661e01dfe6c1d686f026230dd188c1b065cf7c34dace7ff7c8988e852bb0d872bbb | C26: 22069 | D26: FE | E26: 46083 | F26: 46083.508 | G26: 900083323 | H26: AGENCIA DE INVERSIONES PROSPERAR S.A.S. | I26: =K26-J26 -> 9007221 | J26: 1540482 | K26: 10547703 | L26: CONTABILIDAD | M26: 46084 | N26: =IFERROR(IF(-_xlfn.DAYS(E26,M26)<0,0,-_xlfn.DAYS(E26,M26)), " - ") -> 1 | O26: NATALIA BERNAZA | T26: 46085 | U26: NO | W26: 0 A 5
... A34: Factura electrónica | B34: e8f3d8f368cdbf39124e6070a13cc20fc1977b4c881bf530d0e9482231c1ac85bd221a46b8c4c2949544b684a9928d5d | C34: 22025 | D34: FE | E34: 46083 | F34: 46083.497 | G34: 900083323 | H34: AGENCIA DE INVERSIONES PROSPERAR S.A.S. | I34: =K34-J34 -> 8961500 | J34: 1702685 | K34: 10664185 | L34: CONTABILIDAD | M34: 46084 | N34: =IFERROR(IF(-_xlfn.DAYS(E34,M34)<0,0,-_xlfn.DAYS(E34,M34)), " - ") -> 1 | O34: NATALIA BERNAZA | T34: 46085 | U34: NO | W34: 0 A 5
A35: Factura electrónica | B35: 8adcc8242e738cd066b82e27efe20824cd88b9f5e79e2adf28df6eec32bb31b096bf961d2a2d989d98046d267f6d96b6 | C35: 3844 | D35: EC | E35: 46083 | F35: 46083.48 | G35: 900284447 | H35: COMERCIALIZADORA VIBO SAS | I35: =K35-J35 -> 519749 | J35: 98752.31 | K35: 618501.31 | L35: RECHAZO | M35: N/A | N35: =IFERROR(IF(-_xlfn.DAYS(E35,M35)<0,0,-_xlfn.DAYS(E35,M35)), " - ") -> - | O35: FRANCY SALAS
A36: Factura electrónica | B36: 9c18641be68d54bc9a565ea87bb1782f613fba3aa3375ed89f9117d20bf8e7a45db428f551ca2ef63efabd0af8370e72 | C36: 1491 | D36: FE | E36: 46083 | F36: 46083.493 | G36: 901950863 | H36: INVERSIONES TORNILLOS Y MANGUERAS S.A.S | I36: =K36-J36 -> 369500 | J36: 70205 | K36: 439705 | L36: MANTENIMIENTO | M36: 46085 | N36: =IFERROR(IF(-_xlfn.DAYS(E36,M36)<0,0,-_xlfn.DAYS(E36,M36)), " - ") -> 2 | O36: FRANCY SALAS | T36: 46094 | U36: NO | W36: 0 A 5
A37: Factura electrónica | B37: 1ae365ae67d46440926616c0731486c0b7f648949cf8603f1764d3980e10a3a36e05ea1a0a8b0987ffe3c865f5b9a1bd | C37: 1490 | D37: FE | E37: 46083 | F37: 46083.485 | G37: 901950863 | H37: INVERSIONES TORNILLOS Y MANGUERAS S.A.S | I37: =K37-J37 -> 79200 | J37: 15048 | K37: 94248 | L37: MANTENIMIENTO | M37: 46085 | N37: =IFERROR(IF(-_xlfn.DAYS(E37,M37)<0,0,-_xlfn.DAYS(E37,M37)), " - ") -> 2 | O37: FRANCY SALAS | T37: 46094 | U37: NO | W37: 0 A 5
A38: Factura electrónica | B38: fb4596aaf24da540d022c5e17fb87a86f4fefcf939cfb25559f9dfe602d05e5f233bfe66a427df921953f9f64fb49f4d | C38: 1333 | D38: SM | E38: 46083 | F38: 46083.476 | G38: 901561580 | H38: SUMINISTRO MATERIALES Y DOTACIONES SUMADO S.A.S | I38: =K38-J38 -> 1710000 | J38: 324900 | K38: 2034900 | L38: COMPRAS | M38: 46090 | N38: =IFERROR(IF(-_xlfn.DAYS(E38,M38)<0,0,-_xlfn.DAYS(E38,M38)), " - ") -> 7 | O38: FRANCY SALAS | T38: 46094 | U38: NO | W38: 6 A 10
A39: Factura electrónica | B39: 1421a0ce56943af79799f5e407d59fab51cd301463079cccba3147352d9831ac8cfe2f04f71d4ceb0d456d83975511f5 | C39: 8184 | E39: 46083 | F39: 46083.657 | G39: 901360705 | H39: DELTA TAGS SAS | I39: =K39-J39 -> 647500 | J39: 123025 | K39: 770525 | L39: COMPRAS | M39: 46087 | N39: =IFERROR(IF(-_xlfn.DAYS(E39,M39)<0,0,-_xlfn.DAYS(E39,M39)), " - ") -> 4 | O39: FRANCY SALAS | T39: 46094 | U39: NO | W39: 0 A 5
A40: Factura electrónica | B40: b24e55eb153dd80c05b7ef91c7ae431cf3d20891d1aa9f840e2953d465fe871a444b59475434bff57948b519d4dc025b | C40: 8183 | E40: 46083 | F40: 46083.65 | G40: 901360705 | H40: DELTA TAGS SAS | I40: =K40-J40 -> 649610 | J40: 123425.9 | K40: 773035.9 | L40: COMPRAS | M40: 46091 | N40: =IFERROR(IF(-_xlfn.DAYS(E40,M40)<0,0,-_xlfn.DAYS(E40,M40)), " - ") -> 8 | O40: FRANCY SALAS | T40: 46094 | U40: NO | W40: 6 A 10
A41: Factura electrónica | B41: bee55bc3d31ceef8631c9f8393f81f359939a0e08ae99ba78f68ad13be6e24d71e5d4e334562d05139ddc2df6b3afe5f | C41: 8182 | E41: 46083 | F41: 46083.47 | G41: 901360705 | H41: DELTA TAGS SAS | I41: =K41-J41 -> 14400 | J41: 2736 | K41: 17136 | L41: COMPRAS | M41: 46084 | N41: =IFERROR(IF(-_xlfn.DAYS(E41,M41)<0,0,-_xlfn.DAYS(E41,M41)), " - ") -> 1 | O41: FRANCY SALAS | T41: 46086 | U41: NO | W41: 0 A 5
A42: Factura electrónica | B42: bc431dfe205c5b2ddc8e89438cf9951517997c34ded2db4b0a39999934d7b5b9af868a5827a6f2f53cd9671573e06e29 | C42: 1488 | D42: FE | E42: 46083 | F42: 46083.468 | G42: 901950863 | H42: INVERSIONES TORNILLOS Y MANGUERAS S.A.S | I42: =K42-J42 -> 900000 | J42: 171000 | K42: 1071000 | L42: MANTENIMIENTO | M42: 46085 | N42: =IFERROR(IF(-_xlfn.DAYS(E42,M42)<0,0,-_xlfn.DAYS(E42,M42)), " - ") -> 2 | O42: FRANCY SALAS | T42: 46094 | U42: NO | W42: 0 A 5
A43: Factura electrónica | B43: 2cd7b8b55a61576178ae6728290c63a9d23acfac8b5795fcb0fc4c0b46bc255253358125fcf6f552734d9ba2df85892c | C43: 56416 | D43: FVE | E43: 46083 | F43: 46083.457 | G43: 900650486 | H43: DISTRIBUIDORA DE SOFTWARE Y MOVILIDAD S.A.S | I43: =K43-J43 -> 890000 | J43: 0 | K43: 890000 | L43: TI | M43: 46085 | N43: =IFERROR(IF(-_xlfn.DAYS(E43,M43)<0,0,-_xlfn.DAYS(E43,M43)), " - ") -> 2 | O43: FRANCY SALAS | T43: 46086 | U43: NO | W43: 0 A 5
A44: Factura electrónica | B44: 1c6c1cdb280e8210b50e7b3399a8a2e23c72250649a5e853a360415755899f07110f0da6b52f86085460f280b1abaeea | C44: 94937 | D44: ES | E44: 46083 | F44: 46083.439 | G44: 800128989 | H44: GUIMAR SEGURIDAD INDUSTRIAL S.A.S | I44: =K44-J44 -> 163345 | J44: 31035.55 | K44: 194380.55 | L44: COMPRAS | M44: 46084 | N44: =IFERROR(IF(-_xlfn.DAYS(E44,M44)<0,0,-_xlfn.DAYS(E44,M44)), " - ") -> 1 | O44: FRANCY SALAS | T44: 46086 | U44: NO | W44: 0 A 5
A45: Factura electrónica | B45: 085a013b624ca1f0ecb46cf6463e76f02d81dcc3ba39577e67b5f9d78d22a52e9f9e8b432a17c90137b0fdbbf57a9636 | C45: 101168 | D45: FM | E45: 46083 | F45: 46083.435 | G45: 890929497 | H45: MAPER S.A.S | I45: =K45-J45 -> 186110 | J45: 35361 | K45: 221471 | L45: MANTENIMIENTO | M45: 46087 | N45: =IFERROR(IF(-_xlfn.DAYS(E45,M45)<0,0,-_xlfn.DAYS(E45,M45)), " - ") -> 4 | O45: FRANCY SALAS | T45: 46094 | U45: NO | W45: 0 A 5
A46: Factura electrónica | B46: 4e0886e9ad6cd99ea7c5a9299ee0fc582db575973deb5f710772321541e3dbaf704ffe67764482926dc299b36abc8d9d | C46: 474 | D46: FE | E46: 46083 | F46: 46083.654 | G46: 900566277 | H46: Mi Cuento S.A.S | I46: =K46-J46 -> 9900000 | J46: 1881000 | K46: 11781000 | L46: COMPRAS | M46: 46097 | N46: =IFERROR(IF(-_xlfn.DAYS(E46,M46)<0,0,-_xlfn.DAYS(E46,M46)), " - ") -> 14 | O46: FRANCY SALAS | T46: 46098 | U46: NO | W46: MAS DE 10
A47: Factura electrónica | B47: 2be4699300c59182747afddc44c65080922a04558badbde8d3104a4aca9767b46ee73e5245adf43affcdd9b8f87508f4 | C47: 62066 | D47: 22T | E47: 46083 | F47: 46083.644 | G47: 860509514 | H47: AUTOGERMANA S A S | I47: =K47-J47 -> 84033.61 | J47: 15966.39 | K47: 100000 | L47: CAJA MENOR | N47: =IFERROR(IF(-_xlfn.DAYS(E47,M47)<0,0,-_xlfn.DAYS(E47,M47)), " - ") -> 0
A48: Factura electrónica | B48: c3d6b91a322e499f4842c04b4c5997bb8047dc0611cc0e004e1a6df1b28b22d9ea3c6bcf273def1a3afaf077a2747228 | C48: 274279 | D48: P1F8 | E48: 46083 | F48: 46083.539 | G48: 900276962 | H48: D1 S A S | I48: =K48-J48 -> 27586.34 | J48: 5213.67 | K48: 32800.01 | L48: CAJA MENOR | N48: =IFERROR(IF(-_xlfn.DAYS(E48,M48)<0,0,-_xlfn.DAYS(E48,M48)), " - ") -> 0
A49: Factura electrónica | B49: 9081e3a3673ba10f8e053b2bc1743b2f7051aa4687fa421f1e2e5da6d13df4d9ac3bba21a9aa292d7548198df15999c6 | C49: 5051830 | D49: I151 | E49: 46083 | F49: 46083.531 | G49: 891408584 | H49: FRISBY S.A. BIC | I49: =K49-J49 -> 28900 | J49: 0 | K49: 28900 | L49: CAJA MENOR | N49: =IFERROR(IF(-_xlfn.DAYS(E49,M49)<0,0,-_xlfn.DAYS(E49,M49)), " - ") -> 0
A50: Factura electrónica | B50: c622b6b9bc18f2e084e817c76361b7b6fd96d34c440b9bbedaa824faddeef586835dd584327e1bc7e157648506608613 | C50: 5051829 | D50: I151 | E50: 46083 | F50: 46083.531 | G50: 891408584 | H50: FRISBY S.A. BIC | I50: =K50-J50 -> 28500 | J50: 0 | K50: 28500 | L50: CAJA MENOR | N50: =IFERROR(IF(-_xlfn.DAYS(E50,M50)<0,0,-_xlfn.DAYS(E50,M50)), " - ") -> 0
A51: Factura electrónica | B51: 4e1fc1902ac63b6ae9b9ace399cbd192e4c45c565647f05a73e204084f3b887944f8bfe898b97cd51b19eab2185713df | C51: 5051828 | D51: I151 | E51: 46083 | F51: 46083.53 | G51: 891408584 | H51: FRISBY S.A. BIC | I51: =K51-J51 -> 28500 | J51: 0 | K51: 28500 | L51: CAJA MENOR | N51: =IFERROR(IF(-_xlfn.DAYS(E51,M51)<0,0,-_xlfn.DAYS(E51,M51)), " - ") -> 0
A52: Factura electrónica | B52: e584762a8947ead03fdf9b439c1695670703bb220bb27c5cabb3c2e7abdcb3ac49200463cd46b03119076f09486edb43 | C52: 101 | D52: FEDV | E52: 46083 | F52: 46083.519 | G52: 42790604 | H52: MARY LUZ JARAMILLO DIEZ | I52: =K52-J52 -> 16479495 | J52: 3131104 | K52: 19610599 | L52: CONTABILIDAD | M52: 46084 | N52: =IFERROR(IF(-_xlfn.DAYS(E52,M52)<0,0,-_xlfn.DAYS(E52,M52)), " - ") -> 1 | O52: NATALIA BERNAZA | T52: 46085 | U52: NO | W52: 0 A 5
A53: Factura electrónica | B53: f66c1cb434e25369578ef00e4e74a0321cbd9df7dec1cf8ccec1896dcb111441960cd610b510d62dc6e59f280533dea7 | C53: 106 | D53: FEKE | E53: 46083 | F53: 46083.48 | G53: 901693444 | H53: KEYSTONE INVERSIONES SAS | I53: =K53-J53 -> 33661928 | J53: 6395766.3 | K53: 40057694 | L53: CONTABILIDAD | M53: 46084 | N53: =IFERROR(IF(-_xlfn.DAYS(E53,M53)<0,0,-_xlfn.DAYS(E53,M53)), " - ") -> 1 | O53: NATALIA BERNAZA | T53: 46085 | U53: NO | W53: 0 A 5
A54: Factura electrónica | B54: 59b5ba806fcc127c2fce8cf9ee12cbe2015eb5fffd663c9a46f5ed907548a84e83a1952834c7eb153040b5c25f859a4c | C54: 320 | D54: FE | E54: 46083 | F54: 46083.472 | G54: 901703752 | H54: ACCION LEGAL 23 S.A.S. | I54: =K54-J54 -> 14946000 | J54: 2839740 | K54: 17785740 | L54: CONTABILIDAD | M54: 46084 | N54: =IFERROR(IF(-_xlfn.DAYS(E54,M54)<0,0,-_xlfn.DAYS(E54,M54)), " - ") -> 1 | O54: NATALIA BERNAZA | T54: 46085 | U54: NO | W54: 0 A 5
A55: Factura electrónica | B55: db73ba4adb509d628799cb6aae9d29f3356de6bc0c6b35f5e4c2dd6b1d2d57ef45e070219d42e4448c8ebf6671830750 | C55: 309 | D55: FE | E55: 46083 | F55: 46083.372 | G55: 901703752 | H55: ACCION LEGAL 23 S.A.S. | I55: =K55-J55 -> 14946 | J55: 2839.74 | K55: 17785.74 | L55: CONTABILIDAD | M55: 46084 | N55: =IFERROR(IF(-_xlfn.DAYS(E55,M55)<0,0,-_xlfn.DAYS(E55,M55)), " - ") -> 1 | O55: NATALIA BERNAZA | W55: 0 A 5
A56: Nota de crédito electrónica | B56: 9009f3038a4fd879b8977c4dffb15b07947ca91ba1bee9fc66d890ff027198d91201f8fd2b3aae7786fb919221d4a8b3 | C56: 47 | D56: NCV | E56: 46083 | F56: 46083.471 | G56: 901703752 | H56: ACCION LEGAL 23 S.A.S. | I56: =K56-J56 -> 14946 | J56: 2839.74 | K56: 17785.74 | L56: CONTABILIDAD | M56: 46084 | N56: =IFERROR(IF(-_xlfn.DAYS(E56,M56)<0,0,-_xlfn.DAYS(E56,M56)), " - ") -> 1 | O56: NATALIA BERNAZA | W56: 0 A 5
A57: Factura electrónica | B57: a2584a878293c01ead1819ddf5f968c9be36febe714a3bad4984bd1684314129155ca8dfd4b8278e08278709beb90767 | C57: 334 | D57: FEFL | E57: 46083 | F57: 46083.45 | G57: 900484386 | H57: FLOSILDA S.A.S | I57: =K57-J57 -> 27859250 | J57: 5293257.5 | K57: 33152508 | L57: CONTABILIDAD | M57: 46084 | N57: =IFERROR(IF(-_xlfn.DAYS(E57,M57)<0,0,-_xlfn.DAYS(E57,M57)), " - ") -> 1 | O57: NATALIA BERNAZA | T57: 46085 | W57: 0 A 5
A58: Factura electrónica | B58: 0ca4d24ae3216256426cc2dcf730aa36f7afe7debb19fad92896221d9026e87a018b824f3d1bdaba2525576ba9093864 | C58: 35794 | D58: FEV | E58: 46083 | F58: 46083.426 | G58: 900229913 | H58: FLOW CHEM SAS | I58: =K58-J58 -> 151563 | J58: 0 | K58: 151563 | L58: COMPRAS | M58: 46090 | N58: =IFERROR(IF(-_xlfn.DAYS(E58,M58)<0,0,-_xlfn.DAYS(E58,M58)), " - ") -> 7 | O58: FRANCY SALAS | T58: 46091 | U58: NO | W58: 6 A 10
A59: Factura electrónica | B59: bcf045d59a2cc592450fd7a333d5ebc6e3c69c36d5a75a04f8130969a7aa2c9a80af47464debb120462de97164e80f2e | C59: 11054 | D59: FEVT | E59: 46083 | F59: 46083.416 | G59: 900219834 | H59: F2X S.A.S. | I59: =K59-J59 -> 16806.72 | J59: 3193.28 | K59: 20000 | L59: COMPRAS | M59: 46084 | N59: =IFERROR(IF(-_xlfn.DAYS(E59,M59)<0,0,-_xlfn.DAYS(E59,M59)), " - ") -> 1 | O59: FRANCY SALAS | T59: 46086 | U59: NO | W59: 0 A 5
A60: Factura electrónica | B60: aab20b95b4264eb627d45c797d20bf1541437999fb6834617c3873e7dbc98a1da9fdddcc4d7a9a8696e2822846e48b28 | C60: 565766 | D60: AH | E60: 46083 | F60: 46083.362 | G60: 890800788 | H60: SUMATEC S.A.S BIC | I60: =K60-J60 -> 70056 | J60: 13311 | K60: 83367 | L60: COMPRAS | M60: 46084 | N60: =IFERROR(IF(-_xlfn.DAYS(E60,M60)<0,0,-_xlfn.DAYS(E60,M60)), " - ") -> 1 | O60: FRANCY SALAS | T60: 46086 | U60: NO | W60: 0 A 5
A61: Factura electrónica | B61: 8ce809776550bee0485e19e747d2a5f37777b20e065a1e5751f7b5853fc8d3580980a345977b269e4a9db1abc9d819fc | C61: 726469 | D61: FMED | E61: 46083 | F61: 46083.382 | G61: 890915475 | H61: EMPAQUETADURAS Y EMPAQUES S.A. | I61: =K61-J61 -> 464938 | J61: 88338.22 | K61: 553276.22 | L61: COMPRAS | M61: 46087 | N61: =IFERROR(IF(-_xlfn.DAYS(E61,M61)<0,0,-_xlfn.DAYS(E61,M61)), " - ") -> 4 | O61: FRANCY SALAS | T61: 46094 | U61: NO | W61: 0 A 5
A62: Factura electrónica | B62: cdea62b3a2c4e8ddb64d052fed1745a2f4323f6a2cc9f3a0de4e378ef92454697d248abf30176e2dd4e5bb299beac40a | C62: 3617 | D62: FE | E62: 46083 | F62: 46083.377 | G62: 811027589 | H62: Zonalogística S.A.S ZLG | I62: =K62-J62 -> 11200000 | J62: 2128000 | K62: 13328000 | L62: COMERCIAL | M62: 46097 | N62: =IFERROR(IF(-_xlfn.DAYS(E62,M62)<0,0,-_xlfn.DAYS(E62,M62)), " - ") -> 14 | O62: JULIAN MOSQUERA | T62: 46099 | U62: NO | W62: MAS DE 10
A63: Factura electrónica | B63: 5ae30b3fa444bf9890a1e884c96fe0d9983248097a63ab242f24bcb2730ef715464bc891570ce8cbbab6afb39fadd414 | C63: 565769 | D63: AH | E63: 46083 | F63: 46083.409 | G63: 890800788 | H63: SUMATEC S.A.S BIC | I63: =K63-J63 -> 330180 | J63: 62734 | K63: 392914 | L63: COMPRAS | M63: 46092 | N63: =IFERROR(IF(-_xlfn.DAYS(E63,M63)<0,0,-_xlfn.DAYS(E63,M63)), " - ") -> 9 | O63: PAOLA GARCIA | T63: 46094 | U63: NO | W63: 6 A 10
A64: Factura electrónica | B64: 8b22002bf98182b61757e4ad8a2b191f19422562dc0602f1e402523aa8624d32e64e755c5c7657c5fcc3b7006b69d740 | C64: 15160300 | D64: POL | E64: 46083 | F64: 46083.367 | G64: 860002180 | H64: SEGUROS COMERCIALES BOLIVAR SA | I64: =K64-J64 -> 2517500 | J64: 478325 | K64: 2995825 | L64: FINANCIERA | M64: 46099 | N64: =IFERROR(IF(-_xlfn.DAYS(E64,M64)<0,0,-_xlfn.DAYS(E64,M64)), " - ") -> 16 | O64: JAIME ARISMENDI | T64: 46100 | U64: NO | W64: MAS DE 10
A65: Factura electrónica | B65: 0d7b4adbefc5e7462083732aa59d186fb7490c5bb3d441dd30c071b1fccf607a068f574b51e4458853583c4cb73a5a3b | C65: 565763 | D65: AH | E65: 46083 | F65: 46083.342 | G65: 890800788 | H65: SUMATEC S.A.S BIC | I65: =K65-J65 -> 319950 | J65: 60791 | K65: 380741 | L65: COMPRAS | M65: 46085 | N65: =IFERROR(IF(-_xlfn.DAYS(E65,M65)<0,0,-_xlfn.DAYS(E65,M65)), " - ") -> 2 | O65: FRANCY SALAS | T65: 46094 | U65: NO | W65: 0 A 5
A66: Factura electrónica | B66: e4564e5dfa1aab528b22a8d0a22b1d5d9cb3be693dab87bcb5945859e4039979ff6c261a407420f6c4fdafe061f9c467 | C66: 726474 | D66: FMED | E66: 46083 | F66: 46083.385 | G66: 890915475 | H66: EMPAQUETADURAS Y EMPAQUES S.A. | I66: =K66-J66 -> 901756 | J66: 171333.64 | K66: 1073089.6 | L66: COMPRAS | M66: 46087 | N66: =IFERROR(IF(-_xlfn.DAYS(E66,M66)<0,0,-_xlfn.DAYS(E66,M66)), " - ") -> 4 | O66: FRANCY SALAS | T66: 46094 | U66: NO | W66: 0 A 5
A67: Factura electrónica | B67: bc549936096f08b71370366f26165809f08cd4aac40798ac5141904d8103aa26d7662f57d693a28886fd1457b815213f | C67: 346348 | D67: FFEE | E67: 46083 | F67: 46083.294 | G67: 800049074 | H67: PAPELERIA Y SERVICIOS SAS | I67: =K67-J67 -> 526610 | J67: 71462 | K67: 598072 | L67: COMPRAS | M67: 46085 | N67: =IFERROR(IF(-_xlfn.DAYS(E67,M67)<0,0,-_xlfn.DAYS(E67,M67)), " - ") -> 2 | O67: FRANCY SALAS | T67: 46094 | U67: NO | W67: 0 A 5
A68: Factura electrónica | B68: 533f9c8ce57fef18ddb517d11f217252c0daed0e43b6beea22293e3f4d57a95e281b4054f3bf8a728301d29d6dbc3203 | C68: 346361 | D68: FFEE | E68: 46083 | F68: 46083.294 | G68: 800049074 | H68: PAPELERIA Y SERVICIOS SAS | I68: =K68-J68 -> 28606 | J68: 5435 | K68: 34041 | L68: COMPRAS | M68: 46084 | N68: =IFERROR(IF(-_xlfn.DAYS(E68,M68)<0,0,-_xlfn.DAYS(E68,M68)), " - ") -> 1 | O68: FRANCY SALAS | T68: 46086 | U68: NO | W68: 0 A 5
A69: Factura electrónica | B69: 474cff7addf34e3423807a79295f2b17502480f7816589f3ab26b79cd5f94ab632681191c8eb97d36088df869e867aa8 | C69: 31722 | D69: IDEA | E69: 46083 | F69: 46083.314 | G69: 900322890 | H69: IDEAPACK S.A.S | I69: =K69-J69 -> 1835400 | J69: 348726 | K69: 2184126 | L69: COMPRAS | M69: 46085 | N69: =IFERROR(IF(-_xlfn.DAYS(E69,M69)<0,0,-_xlfn.DAYS(E69,M69)), " - ") -> 2 | O69: FRANCY SALAS | T69: 46094 | U69: NO | W69: 0 A 5
... A75: Factura electrónica | B75: e6946573e52d72b167d5026b955e891691f75d83eda400d8e1fa07f68fa6434d719c7026929c1745c5ca11dc88af9300 | C75: 726384 | D75: FMED | E75: 46083 | F75: 46083.259 | G75: 890915475 | H75: EMPAQUETADURAS Y EMPAQUES S.A. | I75: =K75-J75 -> 1475040 | J75: 280257.6 | K75: 1755297.6 | L75: COMPRAS | M75: 46087 | N75: =IFERROR(IF(-_xlfn.DAYS(E75,M75)<0,0,-_xlfn.DAYS(E75,M75)), " - ") -> 4 | O75: FRANCY SALAS | T75: 46094 | U75: NO | W75: 0 A 5
A76: Factura electrónica | B76: c01e7522dd31cad7d1ea5515316731dba7c76882385ef573f895be81cf1d818c2d6eb5b9a638c611112be6c39b27c09e | C76: 346359 | D76: FFEE | E76: 46083 | F76: 46083.294 | G76: 800049074 | H76: PAPELERIA Y SERVICIOS SAS | I76: =K76-J76 -> 1023684 | J76: 184424 | K76: 1208108 | L76: COMPRAS | M76: 46090 | N76: =IFERROR(IF(-_xlfn.DAYS(E76,M76)<0,0,-_xlfn.DAYS(E76,M76)), " - ") -> 7 | O76: FRANCY SALAS | W76: 6 A 10
A77: Factura electrónica | B77: 5f78a00db751a3ffca0d7b802b2b590039f3f12b1b48133c35973a7a5c1879f5a6e82280f7aeced83e1dd9252cd103f8 | C77: 346345 | D77: FFEE | E77: 46083 | F77: 46083.294 | G77: 800049074 | H77: PAPELERIA Y SERVICIOS SAS | I77: =K77-J77 -> 101303 | J77: 7710 | K77: 109013 | L77: COMPRAS | M77: 46085 | N77: =IFERROR(IF(-_xlfn.DAYS(E77,M77)<0,0,-_xlfn.DAYS(E77,M77)), " - ") -> 2 | O77: FRANCY SALAS | T77: 46094 | U77: NO | W77: 0 A 5
A78: Factura electrónica | B78: ad75816eda40ce9275a8335b4a3b22269d9760c180c24edf237afde8701bad5e89217274990ab650e9ee42d875a93f40 | C78: 346349 | D78: FFEE | E78: 46083 | F78: 46083.294 | G78: 800049074 | H78: PAPELERIA Y SERVICIOS SAS | I78: =K78-J78 -> 3462480 | J78: 657871 | K78: 4120351 | L78: COMPRAS | M78: 46087 | N78: =IFERROR(IF(-_xlfn.DAYS(E78,M78)<0,0,-_xlfn.DAYS(E78,M78)), " - ") -> 4 | O78: FRANCY SALAS | T78: 46094 | U78: NO | W78: 0 A 5
A79: Factura electrónica | B79: c9686903f7c7e77e1de3ef487169af1dedc2f6669627b01657a2d55eb86510d9e47eb068eb419d8f4215d73530ceecc1 | C79: 723487 | D79: FBOG | E79: 46083 | F79: 46083.285 | G79: 890915475 | H79: EMPAQUETADURAS Y EMPAQUES S.A. | I79: =K79-J79 -> 715380 | J79: 135922.2 | K79: 851302.2 | L79: COMPRAS | M79: 46085 | N79: =IFERROR(IF(-_xlfn.DAYS(E79,M79)<0,0,-_xlfn.DAYS(E79,M79)), " - ") -> 2 | O79: FRANCY SALAS | T79: 46094 | U79: NO | W79: 0 A 5
A80: Factura electrónica | B80: 12a4f4fe8af86e4b437dcb683d1b834d92d10a1332f53493e512dacad383f30d6f5deb05ab36df2840f03ffb27e1f9fa | C80: 346360 | D80: FFEE | E80: 46083 | F80: 46083.294 | G80: 800049074 | H80: PAPELERIA Y SERVICIOS SAS | I80: =K80-J80 -> 33359 | J80: 4432 | K80: 37791 | L80: COMPRAS | M80: 46084 | N80: =IFERROR(IF(-_xlfn.DAYS(E80,M80)<0,0,-_xlfn.DAYS(E80,M80)), " - ") -> 1 | O80: FRANCY SALAS | T80: 46086 | U80: NO | W80: 0 A 5
A81: Factura electrónica | B81: d4e2e4bc540e0b2851c00d29d80a5f33113cd32a5dafc826123a86268e88701223a07a21afa3e2935888f794d341a0b0 | C81: 346358 | D81: FFEE | E81: 46083 | F81: 46083.294 | G81: 800049074 | H81: PAPELERIA Y SERVICIOS SAS | I81: =K81-J81 -> 662474 | J81: 55283 | K81: 717757 | L81: COMPRAS | M81: 46084 | N81: =IFERROR(IF(-_xlfn.DAYS(E81,M81)<0,0,-_xlfn.DAYS(E81,M81)), " - ") -> 1 | O81: FRANCY SALAS | T81: 46086 | U81: NO | W81: 0 A 5
A82: Factura electrónica | B82: a49d80d35655f283378eaa383690d09fe907337d078902511ab7df32356b46397f7d37fcc848a71e34154290245118b2 | C82: 726426 | D82: FMED | E82: 46083 | F82: 46083.302 | G82: 890915475 | H82: EMPAQUETADURAS Y EMPAQUES S.A. | I82: =K82-J82 -> 182671 | J82: 34707.49 | K82: 217378.49 | L82: COMPRAS | M82: 46084 | N82: =IFERROR(IF(-_xlfn.DAYS(E82,M82)<0,0,-_xlfn.DAYS(E82,M82)), " - ") -> 1 | O82: FRANCY SALAS | T82: 46086 | U82: NO | W82: 0 A 5
A83: Factura electrónica | B83: 22d7e92af348628c11e75353dd3d20d23b392c3850361a9ef81448286234f8e2955769d00b8a010ec9513cc65452cbfe | C83: 346346 | D83: FFEE | E83: 46083 | F83: 46083.294 | G83: 800049074 | H83: PAPELERIA Y SERVICIOS SAS | I83: =K83-J83 -> 270988 | J83: 25660 | K83: 296648 | L83: COMPRAS | M83: 46085 | N83: =IFERROR(IF(-_xlfn.DAYS(E83,M83)<0,0,-_xlfn.DAYS(E83,M83)), " - ") -> 2 | O83: FRANCY SALAS | T83: 46094 | U83: NO | W83: 0 A 5
A84: Factura electrónica | B84: 306775544060cf03d6cf2419154b5be7dd95f46e8b1d733f03e164ebc34e9410ded806bbbcd625264b394fd11927986a | C84: 346347 | D84: FFEE | E84: 46083 | F84: 46083.294 | G84: 800049074 | H84: PAPELERIA Y SERVICIOS SAS | I84: =K84-J84 -> 514115 | J84: 75060 | K84: 589175 | L84: CRUZA | M84: N/A | N84: =IFERROR(IF(-_xlfn.DAYS(E84,M84)<0,0,-_xlfn.DAYS(E84,M84)), " - ") -> - | O84: FRANCY SALAS
A85: Factura electrónica | B85: 6cce6d9b81b42bbb1872257964b06b43766b41afd25cb688e94ebd8a7aebdd3b00ceba7287409cc9d344180eff9b3c46 | C85: 15782 | D85: EA | E85: 46083 | F85: 46083.403 | G85: 39440924 | H85: PATRICIA ELENA ARBELAEZ SEPULVEDA | I85: =K85-J85 -> 1680.7 | J85: 319.33 | K85: 2000.03 | L85: CAJA MENOR | N85: =IFERROR(IF(-_xlfn.DAYS(E85,M85)<0,0,-_xlfn.DAYS(E85,M85)), " - ") -> 0
A86: Factura electrónica | B86: 56a9e79bc617e41a24752b2c34f2a557e2f74a561a7cf9b25f39aba9812bcce7731a124952ff73a31c0e82440adcf187 | C86: 198514 | D86: FE | E86: 46083 | F86: 46083.386 | G86: 800180675 | H86: INMOBILIARIA RENTAR SAS | I86: =K86-J86 -> 1965813 | J86: 0 | K86: 1965813 | L86: CONTABILIDAD | M86: 46084 | N86: =IFERROR(IF(-_xlfn.DAYS(E86,M86)<0,0,-_xlfn.DAYS(E86,M86)), " - ") -> 1 | O86: NATALIA BERNAZA | T86: 46085 | U86: NO | W86: 0 A 5
A87: Factura electrónica | B87: bc0935d51eb6f806b4485d514e66df8863a20441f9977df18b75f7d666a2523a7da93c867fd1bfc459690464476dc9d6 | C87: 169677 | D87: 392 | E87: 46083 | F87: 46083.378 | G87: 860000018 | H87: AGENCIA DE VIAJES Y TURISMO AVIATUR S.A.S | I87: =K87-J87 -> 580000 | J87: 110200 | K87: 690200 | L87: COMPRAS | M87: 46091 | N87: =IFERROR(IF(-_xlfn.DAYS(E87,M87)<0,0,-_xlfn.DAYS(E87,M87)), " - ") -> 8 | O87: FRANCY SALAS | T87: 46098 | U87: NO | W87: 6 A 10
A88: Factura electrónica | B88: 34316c96682f80a313e2c9963ad8db3a944a1977c5fd9f64983fce7a386ebbabf6933699ffc944396e1c54d3bfb5ed19 | C88: 191512 | D88: 003F | E88: 46083 | F88: 46083.346 | G88: 860533413 | H88: IRCC SAS | I88: =K88-J88 -> 24900 | J88: 0 | K88: 24900 | L88: CAJA MENOR | N88: =IFERROR(IF(-_xlfn.DAYS(E88,M88)<0,0,-_xlfn.DAYS(E88,M88)), " - ") -> 0
A89: Factura electrónica | B89: 747445f5546fb3c93d0660b5f3e74d8dda632cfd211e710c2d75db69fe2c74a2d11a6e1d8a3f8592e02b1f5f0502ac77 | C89: 191511 | D89: 003F | E89: 46083 | F89: 46083.345 | G89: 860533413 | H89: IRCC SAS | I89: =K89-J89 -> 30900 | J89: 0 | K89: 30900 | L89: CAJA MENOR | N89: =IFERROR(IF(-_xlfn.DAYS(E89,M89)<0,0,-_xlfn.DAYS(E89,M89)), " - ") -> 0
A90: Factura electrónica | B90: d8620f043263417293ab80a053925e8d166baa7665a5ec0f5aac16e0e278f1d4e141b26ec8b75e4d6acf49a7380ca1b8 | C90: 191510 | D90: 003F | E90: 46083 | F90: 46083.344 | G90: 860533413 | H90: IRCC SAS | I90: =K90-J90 -> 25900 | J90: 0 | K90: 25900 | L90: CAJA MENOR | N90: =IFERROR(IF(-_xlfn.DAYS(E90,M90)<0,0,-_xlfn.DAYS(E90,M90)), " - ") -> 0
A91: Factura electrónica | B91: 2a0136c9bdcd69120a9f5f45bc3cf89158324501098c0a515754ea44e53ced4f854f07abf7c497012a38da159a12b884 | C91: 291924 | D91: CQ | E91: 46083 | F91: 46083.309 | G91: 890917295 | H91: COLORQUIMICA S.A.S. | I91: =K91-J91 -> 130000 | J91: 24700 | K91: 154700 | L91: COMPRAS | M91: 46084 | N91: =IFERROR(IF(-_xlfn.DAYS(E91,M91)<0,0,-_xlfn.DAYS(E91,M91)), " - ") -> 1 | O91: FRANCY SALAS | T91: 46086 | U91: NO | W91: 0 A 5
A92: Factura electrónica | B92: 808aea4e2596bea2a61daa302e35951076d03cce9ea63f4b2a3e613c9df8ec4634e55f955955f151d0cab0631eaecb66 | C92: 80591 | D92: FEOL | E92: 46083 | F92: 46083.28 | G92: 900359070 | H92: 1900 CAFÉ S.A.S | I92: =K92-J92 -> 14400 | J92: 0 | K92: 14400 | L92: CAJA MENOR | N92: =IFERROR(IF(-_xlfn.DAYS(E92,M92)<0,0,-_xlfn.DAYS(E92,M92)), " - ") -> 0
A93: Factura electrónica | B93: 588b34005030de45259df4e986e8327395c9e50007236211ea05c413faa1696118833b360facce3b3b08681222a4f904 | C93: 145 | D93: JA | E93: 46084 | F93: 46084.841 | G93: 15442838 | H93: GOMEZ JHON ARLEY | I93: =K93-J93 -> 780000 | J93: 148200 | K93: 928200 | L93: OPERACIONES | M93: 46086 | N93: =IFERROR(IF(-_xlfn.DAYS(E93,M93)<0,0,-_xlfn.DAYS(E93,M93)), " - ") -> 2 | O93: FRANCY SALAS | T93: 46087 | W93: 0 A 5
A94: Factura electrónica | B94: 51812d6e3e0c68328b8ac1ae77b932b5980a3840d9ee3f89a01dcb9079a09683e2d2ce2773fc7daba118841acc6e210f | C94: 1307 | D94: MY | E94: 46084 | F94: 46084.784 | G94: 900933624 | H94: MECANIZADOS Y SERVICIOS MAYROP SAS | I94: =K94-J94 -> 3200000 | J94: 608000 | K94: 3808000 | L94: MANTENIMIENTO | M94: 46091 | N94: =IFERROR(IF(-_xlfn.DAYS(E94,M94)<0,0,-_xlfn.DAYS(E94,M94)), " - ") -> 7 | O94: FRANCY SALAS | T94: 46098 | U94: NO | W94: 6 A 10
A95: Factura electrónica | B95: d41f18e4a4561f223d634441d05da00858f6cb142b95a5a7cf614d6c6a8ec435ecdb36c70126c813b425061f7ca09b15 | C95: 1306 | D95: MY | E95: 46084 | F95: 46084.78 | G95: 900933624 | H95: MECANIZADOS Y SERVICIOS MAYROP SAS | I95: =K95-J95 -> 200000 | J95: 38000 | K95: 238000 | L95: MANTENIMIENTO | M95: 46091 | N95: =IFERROR(IF(-_xlfn.DAYS(E95,M95)<0,0,-_xlfn.DAYS(E95,M95)), " - ") -> 7 | O95: FRANCY SALAS | T95: 46094 | U95: NO | W95: 6 A 10
A96: Factura electrónica | B96: 1aa010c3b4c3fa3044c3c26aa7cd8bb7c61d904528c372de83455c1fcb77cd47b3727f59b72206087981816f7fa6c877 | C96: 1305 | D96: MY | E96: 46084 | F96: 46084.777 | G96: 900933624 | H96: MECANIZADOS Y SERVICIOS MAYROP SAS | I96: =K96-J96 -> 6800000 | J96: 1292000 | K96: 8092000 | L96: MANTENIMIENTO | M96: 46091 | N96: =IFERROR(IF(-_xlfn.DAYS(E96,M96)<0,0,-_xlfn.DAYS(E96,M96)), " - ") -> 7 | O96: FRANCY SALAS | T96: 46094 | U96: NO | W96: 6 A 10
A97: Factura electrónica | B97: 2246dd186516e2050780ec7917624a73bd488490c4aebc43db6e3680c0b05854198464147e2de4adbe8f5cd90b527718 | C97: 9562 | D97: FE | E97: 46084 | F97: 46084.76 | G97: 900103086 | H97: COLOMBIA CRANE | I97: =K97-J97 -> 6000000 | J97: 1140000 | K97: 7140000 | L97: SSTA | M97: 46087 | N97: =IFERROR(IF(-_xlfn.DAYS(E97,M97)<0,0,-_xlfn.DAYS(E97,M97)), " - ") -> 3 | O97: FRANCY SALAS | T97: 46094 | U97: NO | W97: 0 A 5
A98: Factura electrónica | B98: 3228277f25bcfb72d0f35144562c03cc43fef4d2ee73e7af489139d8cb01f49862e00c249c5468c60530d38fead168de | C98: 114211 | D98: VI | E98: 46084 | F98: 46084.719 | G98: 900494362 | H98: TECNOMEDICA MD S.A.S | I98: =K98-J98 -> 6800 | J98: 1292 | K98: 8092 | L98: COMPRAS | M98: 46086 | N98: =IFERROR(IF(-_xlfn.DAYS(E98,M98)<0,0,-_xlfn.DAYS(E98,M98)), " - ") -> 2 | O98: FRANCY SALAS | T98: 46094 | U98: NO | W98: 0 A 5
A99: Factura electrónica | B99: 6809d14e64e52ec90c33308e666dbd5c55a7eecfd212cca006abba2060731823cc0b6db5185191cb86db6846d724eefa | C99: 754 | D99: FE | E99: 46084 | F99: 46084.707 | G99: 71660004 | H99: RAMIREZ CADAVID JUAN PABLO | I99: =K99-J99 -> 32000 | J99: 0 | K99: 32000 | L99: COMPRAS | M99: 46086 | N99: =IFERROR(IF(-_xlfn.DAYS(E99,M99)<0,0,-_xlfn.DAYS(E99,M99)), " - ") -> 2 | O99: FRANCY SALAS | T99: 46094 | U99: NO | W99: 0 A 5
A100: Factura electrónica | B100: da7fd52cdbe1976ae17e370e62fe0272c60fd62adbe3eed973bf8d2d0a5a82dd5524bf48129ad5907fddc13d46dfca0f | C100: 752 | D100: FE | E100: 46084 | F100: 46084.702 | G100: 71660004 | H100: RAMIREZ CADAVID JUAN PABLO | I100: =K100-J100 -> 18000 | J100: 0 | K100: 18000 | L100: COMPRAS | M100: 46086 | N100: =IFERROR(IF(-_xlfn.DAYS(E100,M100)<0,0,-_xlfn.DAYS(E100,M100)), " - ") -> 2 | O100: FRANCY SALAS | T100: 46087 | W100: 0 A 5
A101: Factura electrónica | B101: 739f6399232eba22bb667b1e228fc3aa5afc56497cfa5b13aba186846864df70a7e2ca852a93c51510f1520ee8c1f5fd | C101: 753 | D101: FE | E101: 46084 | F101: 46084.705 | G101: 71660004 | H101: RAMIREZ CADAVID JUAN PABLO | I101: =K101-J101 -> 48000 | J101: 0 | K101: 48000 | L101: COMPRAS | M101: 46086 | N101: =IFERROR(IF(-_xlfn.DAYS(E101,M101)<0,0,-_xlfn.DAYS(E101,M101)), " - ") -> 2 | O101: FRANCY SALAS | T101: 46094 | U101: NO | W101: 0 A 5
A102: Factura electrónica | B102: e05d0060fdb8e147e9fd507f9786777b92d879f35e92151ea7684290915f7f763574db2f7feb4da2851c2f64bca0167c | C102: 726841 | D102: FMED | E102: 46084 | F102: 46084.659 | G102: 890915475 | H102: EMPAQUETADURAS Y EMPAQUES S.A. | I102: =K102-J102 -> 99193 | J102: 18846.67 | K102: 118039.67 | L102: COMPRAS | M102: 46086 | N102: =IFERROR(IF(-_xlfn.DAYS(E102,M102)<0,0,-_xlfn.DAYS(E102,M102)), " - ") -> 2 | O102: FRANCY SALAS | T102: 46087 | W102: 0 A 5
A103: Factura electrónica | B103: 4e10cdc03030f75ad9cfb04dd710af4da6583c09355e61a467af417a9a736af04808a41bf63a1079e36ec3c1a3bfce13 | C103: 4484 | D103: FEL | E103: 46084 | F103: 46084.449 | G103: 1037587911 | H103: SOTO NOREÑA SEBASTIAN | I103: =K103-J103 -> 1029916 | J103: 195684.03 | K103: 1225600 | L103: COMPRAS | M103: 46086 | N103: =IFERROR(IF(-_xlfn.DAYS(E103,M103)<0,0,-_xlfn.DAYS(E103,M103)), " - ") -> 2 | O103: FRANCY SALAS | T103: 46094 | U103: NO | W103: 0 A 5
A104: Factura electrónica | B104: 6cf8a0b42fc943eb49942673ab8e24053d816801dd4d05fb6122297a427ee59bedcc504efea7c7e2995e306038a998a8 | C104: 4923 | D104: PE3 | E104: 46084 | F104: 46084.938 | G104: 901560228 | H104: NIKO PARRILLA S.A.S | I104: =K104-J104 -> 42000 | J104: 0 | K104: 42000 | L104: CAJA MENOR | N104: =IFERROR(IF(-_xlfn.DAYS(E104,M104)<0,0,-_xlfn.DAYS(E104,M104)), " - ") -> 0
A105: Factura electrónica | B105: a2888e2b2134126be08af8b2040b0219b31b34032f3e5b51d0485651c964a9a409e6f99de32b7f9245c66408c5519b6f | C105: 6466 | E105: 46084 | F105: 46084.885 | G105: 32150739 | H105: NATALIA ANDREA ACOSTA COLORADO | I105: =K105-J105 -> 693000 | J105: 0 | K105: 693000 | L105: GESTION HUMANA | M105: 46087 | N105: =IFERROR(IF(-_xlfn.DAYS(E105,M105)<0,0,-_xlfn.DAYS(E105,M105)), " - ") -> 3 | O105: FRANCY SALAS | T105: 46091 | U105: NO | W105: 0 A 5
A106: Factura electrónica | B106: 0d473049822ef59174a878a7f1f299d4a5967d4b32de70e1ee7bd3daaf5e53f8861ea163ac9412d70e27c10d9236a531 | C106: 10495 | D106: E | E106: 46084 | F106: 46084.867 | G106: 890927621 | H106: GONCALVES CORREA SAS | I106: =K106-J106 -> 1349680 | J106: 0 | K106: 1349680 | L106: CAJA MENOR | N106: =IFERROR(IF(-_xlfn.DAYS(E106,M106)<0,0,-_xlfn.DAYS(E106,M106)), " - ") -> 0 | T106: 46107
A107: Factura electrónica | B107: f9df2930ab6f2bd71742ab3c44bc1e5accaaf42f8f28c29f984bfc33a2cae3688bdf78ce907b9f898e721c0b6a42001b | C107: 5051959 | D107: I151 | E107: 46084 | F107: 46084.755 | G107: 891408584 | H107: FRISBY S.A. BIC | I107: =K107-J107 -> 20800 | J107: 0 | K107: 20800 | L107: CAJA MENOR | N107: =IFERROR(IF(-_xlfn.DAYS(E107,M107)<0,0,-_xlfn.DAYS(E107,M107)), " - ") -> 0
A108: Factura electrónica | B108: cb1bf07b806dacc46aac71098265a5777f9ef63da845309136f36552f5b7853b9e5aad57eb201c3837c6aac713bfcf8b | C108: 5051958 | D108: I151 | E108: 46084 | F108: 46084.754 | G108: 891408584 | H108: FRISBY S.A. BIC | I108: =K108-J108 -> 28500 | J108: 0 | K108: 28500 | L108: CAJA MENOR | N108: =IFERROR(IF(-_xlfn.DAYS(E108,M108)<0,0,-_xlfn.DAYS(E108,M108)), " - ") -> 0
A109: Factura electrónica | B109: 615fdf967ef705ea15675cf3cc710d6d645a64fea9c809d1529be9ed861619c645ec71be5801ed70bcd2f350fe18f689 | C109: 65002 | D109: 285B | E109: 46084 | F109: 46084.744 | G109: 900480569 | H109: JERONIMO MARTINS COLOMBIA S.A.S. | I109: =K109-J109 -> 10684.79 | J109: 1515.21 | K109: 12200 | L109: CAJA MENOR | N109: =IFERROR(IF(-_xlfn.DAYS(E109,M109)<0,0,-_xlfn.DAYS(E109,M109)), " - ") -> 0
A110: Documento equivalente - Cobro de peajes | B110: e89bb07383ec1e083b1d1746c5606bec13707f6489c49e49693defaca9175a5f299f3de2f6450bd8541d74f5474011c4 | C110: 89413867 | D110: DEFL | E110: 46084 | F110: 46084.735 | G110: 900219834 | H110: F2X S.A.S. | I110: =K110-J110 -> 18500 | J110: 0 | K110: 18500 | L110: COMPRAS | M110: 46086 | N110: =IFERROR(IF(-_xlfn.DAYS(E110,M110)<0,0,-_xlfn.DAYS(E110,M110)), " - ") -> 2 | O110: FRANCY SALAS | T110: 46098 | U110: NO | W110: 0 A 5
A111: Documento equivalente - Cobro de peajes | B111: ab831ddc4aa1ec5e78e9eddf2ee63c30b4b77644257a16870cf8bfc1bc89d8cc26f4cf898f4d672e3751d84a67339b6b | C111: 89411392 | D111: DEFL | E111: 46084 | F111: 46084.731 | G111: 900219834 | H111: F2X S.A.S. | I111: =K111-J111 -> 20200 | J111: 0 | K111: 20200 | L111: COMPRAS | M111: 46086 | N111: =IFERROR(IF(-_xlfn.DAYS(E111,M111)<0,0,-_xlfn.DAYS(E111,M111)), " - ") -> 2 | O111: FRANCY SALAS | T111: 46098 | U111: NO | W111: 0 A 5
A112: Factura electrónica | B112: 278c4ac71ad27841c6286eb1d2d67258d4e9ac393582377a83abbdc1399121e4419c685bb7121c9c00383155d0bd4cc9 | C112: 51602 | D112: 321F | E112: 46084 | F112: 46084.726 | G112: 860533413 | H112: IRCC SAS | I112: =K112-J112 -> 41900 | J112: 0 | K112: 41900 | L112: CAJA MENOR | N112: =IFERROR(IF(-_xlfn.DAYS(E112,M112)<0,0,-_xlfn.DAYS(E112,M112)), " - ") -> 0
...

Sheet Indicadores.
A1: FECHA DE ENTREGA | B1: (Varios elementos) | J1: FECHA DE ENTREGA | K1: (en blanco)
A2: MES | B2: MARZO | J2: MES | K2: MARZO
A4: Cuenta de Folio | B4: Etiquetas de columna | J4: Etiquetas de fila | K4: Cuenta de Folio
A5: Etiquetas de fila | B5: 0 A 5 | C5: 6 a 10 | D5: MAS DE 10 | E5: Total general | J5: COMPRAS | K5: 1
A6: BIENESTAR | B6: 3 | E6: 3 | J6: GESTION HUMANA | K6: 3
A7: CALIDAD | B7: 12 | E7: 12 | J7: MANTENIMIENTO | K7: 4
A8: COMERCIAL | C8: 1 | D8: 1 | E8: 2 | J8: NOMINA | K8: 4
A9: COMPRAS | B9: 266 | C9: 29 | D9: 7 | E9: 302 | J9: OPERACIONES | K9: 13
A10: CONTABILIDAD | B10: 33 | E10: 33 | J10: Total general | K10: 25
A11: FINANCIERA | B11: 1 | C11: 1 | D11: 1 | E11: 3
A12: GERENCIA | B12: 1 | C12: 1 | D12: 1 | E12: 3
A13: GESTION HUMANA | B13: 19 | C13: 5 | D13: 1 | E13: 25
A14: MANTENIMIENTO | B14: 101 | C14: 38 | D14: 5 | E14: 144
A15: NOMINA | B15: 11 | C15: 6 | D15: 3 | E15: 20
A16: OPERACIONES | B16: 24 | C16: 5 | D16: 3 | E16: 32
A17: SSTA | B17: 8 | C17: 3 | E17: 11
A18: TI | B18: 25 | C18: 6 | D18: 4 | E18: 35
A19: Total general | B19: 504 | C19: 95 | D19: 26 | E19: 625
B21: =(504*100%)/625 -> 0.8064 | C21: =(121*100%)/625 -> 0.1936
D24: A tiempo | E24: Por fuera del tiempo
A26: Facturas entregadas 30/03/2026 | B26: 625 | D26: 504 | E26: 121
A27: Facturas de Caja Menor | B27: 137
A28: Facturas rechazadas | B28: 56
A29: Pendientes por entregar | B29: 25 | D29: 22 | E29: =B29-D29 -> 3

Sheet Hoja1
A1: FECHA DE ENTREGA | B1: (Varios elementos) | I1: MES | J1: ABRIL
A2: MES | B2: ABRIL | I2: FECHA DE ENTREGA | J2: (en blanco)
A4: Cuenta de Folio | B4: Etiquetas de columna | I4: Etiquetas de fila | J4: Cuenta de Folio
A5: Etiquetas de fila | B5: 0 A 5 | C5: 6 a 10 | D5: Más de 10 | E5: Total general | I5: CALIDAD | J5: 2
A6: BIENESTAR | B6: 1 | E6: 1 | I6: COMPRAS | J6: 45
A7: COMPRAS | B7: 115 | C7: 12 | D7: 18 | E7: 145 | I7: FINANCIERA | J7: 1
A8: CONTABILIDAD | B8: 24 | D8: 2 | E8: 26 | I8: GESTION HUMANA | J8: 3
A9: FINANCIERA | B9: 2 | C9: 1 | E9: 3 | I9: MANTENIMIENTO | J9: 23
A10: GERENCIA | B10: 1 | E10: 1 | I10: NOMINA | J10: 2
A11: GESTION HUMANA | B11: 6 | C11: 2 | E11: 8 | I11: OPERACIONES | J11: 4
A12: MANTENIMIENTO | B12: 16 | C12: 6 | D12: 11 | E12: 33 | I12: TESORERIA | J12: 1
A13: NOMINA | B13: 6 | C13: 1 | E13: 7 | I13: TI | J13: 1
A14: OPERACIONES | B14: 2 | D14: 1 | E14: 3 | I14: Total general | J14: 82
A15: TI | B15: 10 | C15: 1 | E15: 11
A16: Total general | B16: 183 | C16: 23 | D16: 32 | E16: 238
B18: =(183*100%)/238 -> 0.76890756 | C18: =(55*100%)/238 -> 0.23109244
D20: A tiempo | E20: Por fuera del tiempo
A22: Facturas entregadas 30/03/2026 | B22: 238 | D22: 183 | E22: 55
A23: Facturas de Caja Menor | B23: 40
A24: Facturas rechazadas | B24: 4
A25: Pendientes por entregar | B25: 82 | D25: 22 | E25: =B25-D25 -> 60

Sheet CONTROL GENERAL
A1: Tipo documento | B1: CUFE/CUDE | C1: Folio | D1: Prefijo | E1: Fecha Emisión | F1: Fecha Recepción | G1: MES | H1: NIT | I1: Nombre Emisor | J1: Subtotal | K1: IVA | L1: Total | M1: Responsable | N1: FECHA DE ENTREGA | O1: DÍAS DE ENTREGA A CONTABILIDAD | P1: QUIEN ENTREGA | Q1: NOMBRE A QUIEN SE DEVUELVE | R1: FECHA DEVOLUCION | S1: REINTEGRO | T1: RANGO DE ENTREGA A TESORERIA DIAS | U1: FECHA ENTREGA TESORERIA | V1: REQUIERE FIRMA DE GERENCIA | W1: FIRMADAS | X1: RANGO DÍAS DE ENTREGA
A2: Factura electrónica | B2: 0ef6b07b4cf2dd55e06ea624c82b02171fe92ef73061ac8a62c89489ed0c24e6a83be88e948a6bd96fb67ea13f0e8201 | C2: 104 | D2: JA | E2: 46023 | F2: 46023.857 | G2: =UPPER(TEXT(E2, "MMMM")) -> ENERO | H2: 15442838 | I2: GOMEZ JHON ARLEY | J2: =L2/K2 -> 6.2631579 | K2: 288496 | L2: 1806896 | M2: OPERACIONES | N2: 46027 | O2: =IFERROR(IF(-_xlfn.DAYS(E2,N2)<0,0,-_xlfn.DAYS(E2,N2)), " - ") -> 4 | P2: ANGELA FRANCO | U2: 46028 | X2: 0 a 5
A3: Factura electrónica | B3: d34baf94ce1e0e60d9018e680f6b1794d38ed6df72f72bd46baba67cf7e955d9690eda0ab6bb26fecb6bdb525e6ac2f3 | C3: 1207940 | D3: 2091 | E3: 46023 | F3: 46023.577 | G3: =UPPER(TEXT(E3, "MMMM")) -> ENERO | H3: 890903790 | I3: SEGUROS DE VIDA SURAMERICANA S.A | J3: =L3-K3 -> 1643587 | K3: 82179.35 | L3: 1725766.4 | M3: GESTION HUMANA | N3: 46037 | O3: =IFERROR(IF(-_xlfn.DAYS(E3,N3)<0,0,-_xlfn.DAYS(E3,N3)), " - ") -> 14 | P3: YENIFER PARRA | U3: 46042 | V3: NO | X3: Más de 10
A4: Factura electrónica | B4: a665605c3e744f7b8e905df90241686b912b3dbc512392e44c0d17f0ac35f1e0828e415703c87f4e4bced120e3e6c08a | C4: 34015 | D4: AEZY | E4: 46023 | F4: 46023.267 | G4: =UPPER(TEXT(E4, "MMMM")) -> ENERO | H4: 900610585 | I4: Easytaxi Colombia SAS | J4: =L4-K4 -> 1560304 | K4: 40891 | L4: 1601195 | M4: COMPRAS | N4: 46037 | O4: =IFERROR(IF(-_xlfn.DAYS(E4,N4)<0,0,-_xlfn.DAYS(E4,N4)), " - ") -> 14 | P4: YENIFER PARRA | U4: 46029 | V4: NO | X4: Más de 10
A5: Factura electrónica | B5: 2a830f0355d0bbaef7f2cbdda6631a7189a1fc3c0e3264f117de9ac19dd6d8235fbbd40c73aff9d5598bcb089cadd657 | C5: 250 | D5: FE | E5: 46023 | F5: 46023.982 | G5: =UPPER(TEXT(E5, "MMMM")) -> ENERO | H5: 901703752 | I5: ACCION LEGAL 23 S.A.S. | J5: =L5-K5 -> 14946000 | K5: 2839740 | L5: 17785740 | M5: CONTABILIDAD | N5: 46037 | O5: =IFERROR(IF(-_xlfn.DAYS(E5,N5)<0,0,-_xlfn.DAYS(E5,N5)), " - ") -> 14 | P5: ANGELA FRANCO | U5: 46028 | V5: SI | X5: Más de 10
A6: Factura electrónica | B6: 194c7373fb40685d6ed80b32a52bc4c1365388bb20d830b989d25dc1053d9cedd7495e96a95b00712bbcc90f046a3dc8 | C6: 3472 | D6: RIND | E6: 46023 | F6: 46023.156 | G6: =UPPER(TEXT(E6, "MMMM")) -> ENERO | H6: 901609691 | I6: RINDEGASTOS COLOMBIA S.A.S. | J6: =L6-K6 -> 696000 | K6: 132240 | L6: 828240 | M6: CONTABILIDAD | N6: 46037 | O6: =IFERROR(IF(-_xlfn.DAYS(E6,N6)<0,0,-_xlfn.DAYS(E6,N6)), " - ") -> 14 | P6: ANGELA FRANCO | U6: 46028 | V6: SI | X6: Más de 10
A7: Factura electrónica | B7: 5b1c9d8483bfcbdd90730678fc9c23fcb9ea92ab667ae8a1a4f52cb5e4f3726481aa2a35f4bb7336d2a242d8121fb1fd | C7: 69855990 | D7: SFEE | E7: 46023 | F7: 46023.087 | G7: =UPPER(TEXT(E7, "MMMM")) -> ENERO | H7: 900843898 | I7: RAPPI S.A.S | J7: =L7-K7 -> 9453.77 | K7: 1796.23 | L7: 11250 | M7: CAJA MENOR | O7: =IFERROR(IF(-_xlfn.DAYS(E7,N7)<0,0,-_xlfn.DAYS(E7,N7)), " - ") -> 0 | P7: YENIFER PARRA | U7: 46119 | V7: NO | X7: Más de 10
A8: Factura electrónica | B8: 3c790c92d6bb7149d735f17aa0e4821cc0cfc1fb0e710a652c97b942de67a594f49e41fe37e338954f466d49a678e06d | C8: 292475957 | D8: 3 | E8: 46023 | F8: 46028.666 | G8: =UPPER(TEXT(E8, "MMMM")) -> ENERO | H8: 800153993 | I8: COMUNICACION CELULAR S A COMCEL S A | J8: =L8-K8 -> 1967321 | K8: 44197.99 | L8: 2011519 | M8: TI | N8: 46037 | O8: =IFERROR(IF(-_xlfn.DAYS(E8,N8)<0,0,-_xlfn.DAYS(E8,N8)), " - ") -> 14 | P8: JAIME GARCIA | U8: 46036 | V8: NO | X8: Más de 10
A9: Factura electrónica | B9: 26ccd53871efebb6ab46920892287d669ddff596b0ba1f42cdafdf6267fce02b02a51d45901a84efa0fcd9bab645c1a7 | C9: 19410 | D9: FE | E9: 46024 | F9: 46024.725 | G9: =UPPER(TEXT(E9, "MMMM")) -> ENERO | H9: 890903388 | I9: CLUB UNION SA | J9: =L9-K9 -> 1699072 | K9: 322823.68 | L9: 2021895.7 | M9: CONTABILIDAD | N9: 46037 | O9: =IFERROR(IF(-_xlfn.DAYS(E9,N9)<0,0,-_xlfn.DAYS(E9,N9)), " - ") -> 13 | P9: ANGELA FRANCO | U9: 46028 | V9: SI | X9: Más de 10
A10: Factura electrónica | B10: 65e2ebf9c29ad3ac559bd09c90e241a43ddba3ede59ff48ffe9ff7e8dff82e48b017c815bbfb2958060b642561c8f824 | C10: 11821 | D10: FACT | E10: 46024 | F10: 46024.685 | G10: =UPPER(TEXT(E10, "MMMM")) -> ENERO | H10: 800192047 | I10: SERVIRUTAS SAS | J10: =L10-K10 -> 850000 | K10: 0 | L10: 850000 | M10: COMPRAS | N10: 46037 | O10: =IFERROR(IF(-_xlfn.DAYS(E10,N10)<0,0,-_xlfn.DAYS(E10,N10)), " - ") -> 13 | P10: YENIFER PARRA | U10: 46030 | V10: NO | X10: Más de 10
A11: Factura electrónica | B11: 99c2afca11be5ca6e0eda0d2fdf5efd571b5d1b90faf43b172c1b32331b4ba74456f24379916946cbc705ab51bf39522 | C11: 4836 | D11: FEIT | E11: 46024 | F11: 46024.796 | G11: =UPPER(TEXT(E11, "MMMM")) -> ENERO | H11: 901042685 | I11: ITTERACTIVO S.A.S. | J11: =L11-K11 -> 1893835 | K11: 0 | L11: 1893835 | M11: TI | N11: 46037 | O11: =IFERROR(IF(-_xlfn.DAYS(E11,N11)<0,0,-_xlfn.DAYS(E11,N11)), " - ") -> 13 | P11: JAIME GARCIA | U11: 46037 | V11: NO | X11: Más de 10
A12: Factura electrónica | B12: cc8f767c5542712e3920894882718c829dca516f46ca34c8f3f8b8347d773d049046da45089f411d597b6102bb07cc00 | C12: 11820 | D12: FACT | E12: 46024 | F12: 46024.683 | G12: =UPPER(TEXT(E12, "MMMM")) -> ENERO | H12: 800192047 | I12: SERVIRUTAS SAS | J12: =L12-K12 -> 1300000 | K12: 0 | L12: 1300000 | M12: COMPRAS | N12: 46037 | O12: =IFERROR(IF(-_xlfn.DAYS(E12,N12)<0,0,-_xlfn.DAYS(E12,N12)), " - ") -> 13 | P12: YENIFER PARRA | U12: 46030 | V12: NO | X12: Más de 10
A13: Factura electrónica | B13: 8266e0f387a062abe5c68b43abd507585a82b41d06f1f5daa1547a4f344b82550781d52d8867fb42e378b9cfe06e73fb | C13: 4830 | D13: FEIT | E13: 46024 | F13: 46024.696 | G13: =UPPER(TEXT(E13, "MMMM")) -> ENERO | H13: 901042685 | I13: ITTERACTIVO S.A.S. | J13: =L13-K13 -> 1299000 | K13: 0 | L13: 1299000 | M13: TI | N13: 46037 | O13: =IFERROR(IF(-_xlfn.DAYS(E13,N13)<0,0,-_xlfn.DAYS(E13,N13)), " - ") -> 13 | P13: JAIME GARCIA | U13: 46037 | V13: NO | X13: Más de 10
A14: Factura electrónica | B14: 73d3e26e12ee3c9e735f2169a519673d4eeea57d30496875a60bc6a86bf5b0c47b6d428880534f95f570733c3d2a5140 | C14: 450321 | D14: IFXC | E14: 46024 | F14: 46024.705 | G14: =UPPER(TEXT(E14, "MMMM")) -> ENERO | H14: 830058677 | I14: IFX NETWORKS COLOMBIA S.A.S. | J14: =L14-K14 -> 13180561 | K14: 2504306.6 | L14: 15684868 | M14: TI | N14: 46037 | O14: =IFERROR(IF(-_xlfn.DAYS(E14,N14)<0,0,-_xlfn.DAYS(E14,N14)), " - ") -> 13 | P14: JAIME GARCIA | U14: 46036 | V14: NO | X14: Más de 10
A15: Factura electrónica | B15: d2c7ed4c0244b1c9507962985e5c7705cf37530dab2855d222d530cd953b7c0019e074ab3d7880a573a2b2f44b47b5f4 | C15: 1907 | E15: 46024 | F15: 46024.62 | G15: =UPPER(TEXT(E15, "MMMM")) -> ENERO | H15: 71737920 | I15: Fabian Alonso Cañas | J15: =L15-K15 -> 350000 | K15: 0 | L15: 350000 | M15: COMPRAS | N15: 46037 | O15: =IFERROR(IF(-_xlfn.DAYS(E15,N15)<0,0,-_xlfn.DAYS(E15,N15)), " - ") -> 13 | P15: YENIFER PARRA | U15: 46036 | V15: NO | X15: Más de 10
A16: Factura electrónica | B16: be2ddcbb3e85bd686814a42e1caeb380caa1fc0d18bf3b311ba21f52740b36ec2838ba8eaac7a67114db2013e569bac5 | C16: 21343 | D16: FE | E16: 46024 | F16: 46024.437 | G16: =UPPER(TEXT(E16, "MMMM")) -> ENERO | H16: 900083323 | I16: AGENCIA DE INVERSIONES PROSPERAR S.A.S. | J16: =L16-K16 -> 9797253 | K16: 1710000 | L16: 11507253 | M16: CONTABILIDAD | N16: 46037 | O16: =IFERROR(IF(-_xlfn.DAYS(E16,N16)<0,0,-_xlfn.DAYS(E16,N16)), " - ") -> 13 | P16: ANGELA FRANCO | U16: 46028 | V16: SI | X16: Más de 10
A17: Factura electrónica | B17: d3c9d62eba6465d53f7f6b9b960e4c86f0b8b431f1b7b6de7087c96c6876702390f4e5240a9b6902164cdcc1acc92397 | C17: 21342 | D17: FE | E17: 46024 | F17: 46024.437 | G17: =UPPER(TEXT(E17, "MMMM")) -> ENERO | H17: 900083323 | I17: AGENCIA DE INVERSIONES PROSPERAR S.A.S. | J17: =L17-K17 -> 9797253 | K17: 1710000 | L17: 11507253 | M17: CONTABILIDAD | N17: 46037 | O17: =IFERROR(IF(-_xlfn.DAYS(E17,N17)<0,0,-_xlfn.DAYS(E17,N17)), " - ") -> 13 | P17: ANGELA FRANCO | U17: 46028 | V17: SI | X17: Más de 10
A18: Factura electrónica | B18: 5af0767de6a4ec2511050c1950fd27faa4d96ed723d9842a4927fed079130f069aa7c4c3ecc8876e3173358d8f3eed43 | C18: 21278 | D18: FE | E18: 46024 | F18: 46024.418 | G18: =UPPER(TEXT(E18, "MMMM")) -> ENERO | H18: 900083323 | I18: AGENCIA DE INVERSIONES PROSPERAR S.A.S. | J18: =L18-K18 -> 8840704 | K18: 1540482 | L18: 10381186 | M18: CONTABILIDAD | N18: 46037 | O18: =IFERROR(IF(-_xlfn.DAYS(E18,N18)<0,0,-_xlfn.DAYS(E18,N18)), " - ") -> 13 | P18: ANGELA FRANCO | U18: 46028 | V18: SI | X18: Más de 10
A19: Factura electrónica | B19: 29ec3c680dc84177abebfa49508d83eee06c69a11629305bc70d97b2742bc4198b5b11b99ca52f6960b7033a4fdc446f | C19: 21279 | D19: FE | E19: 46024 | F19: 46024.419 | G19: =UPPER(TEXT(E19, "MMMM")) -> ENERO | H19: 900083323 | I19: AGENCIA DE INVERSIONES PROSPERAR S.A.S. | J19: =L19-K19 -> 8840704 | K19: 1540482 | L19: 10381186 | M19: CONTABILIDAD | N19: 46037 | O19: =IFERROR(IF(-_xlfn.DAYS(E19,N19)<0,0,-_xlfn.DAYS(E19,N19)), " - ") -> 13 | P19: ANGELA FRANCO | U19: 46028 | V19: SI | X19: Más de 10
A20: Factura electrónica | B20: 5666374ceea356bbe35a0c521004caba9d5e1d8b1b3033edbab6a2c9a941b232ea2863742bf36c82e27b46f5b94bb239 | C20: 21233 | D20: FE | E20: 46024 | F20: 46024.41 | G20: =UPPER(TEXT(E20, "MMMM")) -> ENERO | H20: 900083323 | I20: AGENCIA DE INVERSIONES PROSPERAR S.A.S. | J20: =L20-K20 -> 8290100 | K20: 1575119 | L20: 9865219 | M20: CONTABILIDAD | N20: 46037 | O20: =IFERROR(IF(-_xlfn.DAYS(E20,N20)<0,0,-_xlfn.DAYS(E20,N20)), " - ") -> 13 | P20: ANGELA FRANCO | U20: 46028 | V20: SI | X20: Más de 10
A21: Factura electrónica | B21: 4ef379d11b05be76b2f81f78b985b05eeceed4431ada66342b30c59eb9af8e8ce65a49f52ddf8e5476ac8b1b07217f91 | C21: 21232 | D21: FE | E21: 46024 | F21: 46024.409 | G21: =UPPER(TEXT(E21, "MMMM")) -> ENERO | H21: 900083323 | I21: AGENCIA DE INVERSIONES PROSPERAR S.A.S. | J21: =L21-K21 -> 8290100 | K21: 1575119 | L21: 9865219 | M21: CONTABILIDAD | N21: 46037 | O21: =IFERROR(IF(-_xlfn.DAYS(E21,N21)<0,0,-_xlfn.DAYS(E21,N21)), " - ") -> 13 | P21: ANGELA FRANCO | U21: 46028 | V21: SI | X21: Más de 10
A22: Factura electrónica | B22: c2df7a609c5c91b310df46183f4631db7f9cd230721a4d8d29efbfee33fae36d4f1b03d76f27f1df8bf95e421e00cdb5 | C22: 99 | D22: FEDV | E22: 46024 | F22: 46024.934 | G22: =UPPER(TEXT(E22, "MMMM")) -> ENERO | H22: 42790604 | I22: MARY LUZ JARAMILLO DIEZ | J22: =L22-K22 -> 16479495 | K22: 3131104 | L22: 19610599 | M22: CONTABILIDAD | N22: 46027 | O22: =IFERROR(IF(-_xlfn.DAYS(E22,N22)<0,0,-_xlfn.DAYS(E22,N22)), " - ") -> 3 | P22: ANGELA FRANCO | U22: 46028 | V22: SI | X22: 0 a 5
A23: Documento equivalente - Cobro de peajes | B23: bed908a634e8806eab71f3cca67137093b53606d4cb95ed0c6cb52b8c125ad0ac1a68c2b693670c6c6939a7618341301 | C23: 77524141 | D23: DEFL | E23: 46024 | F23: 46024.789 | G23: =UPPER(TEXT(E23, "MMMM")) -> ENERO | H23: 900219834 | I23: F2X S.A.S. | J23: =L23-K23 -> 19100 | K23: 0 | L23: 19100 | M23: COMPRAS | N23: 46027 | O23: =IFERROR(IF(-_xlfn.DAYS(E23,N23)<0,0,-_xlfn.DAYS(E23,N23)), " - ") -> 3 | P23: YENIFER PARRA | U23: 46038 | V23: NO | X23: 0 a 5
A24: Factura electrónica | B24: 1c091bc2edde713e819895dd4be42747f832c91875b5c59c6c89c2c5b0e32177ba46beeb62019cd1c58e37fee7526b0b | C24: 9019629392 | D24: AR | E24: 46024 | F24: 46024.769 | G24: =UPPER(TEXT(E24, "MMMM")) -> ENERO | H24: 830095213 | I24: ORGANIZACIÓN TERPEL S.A. | J24: =L24-K24 -> 392028.98 | K24: 0 | L24: 392028.98 | M24: COMPRAS | N24: 46027 | O24: =IFERROR(IF(-_xlfn.DAYS(E24,N24)<0,0,-_xlfn.DAYS(E24,N24)), " - ") -> 3 | P24: YENIFER PARRA | U24: 46029 | V24: NO | X24: 0 a 5
A25: Factura electrónica | B25: bbe4af0f4bcc469faac7010f4fb6f153f4cf60c0caa5a6e1db51a8d6257da30d908e2e0474772e788a1640ade21d60d5 | C25: 1908 | E25: 46024 | F25: 46024.622 | G25: =UPPER(TEXT(E25, "MMMM")) -> ENERO | H25: 71737920 | I25: Fabian Alonso Cañas | J25: =L25-K25 -> 90000 | K25: 0 | L25: 90000 | M25: COMPRAS | N25: 46027 | O25: =IFERROR(IF(-_xlfn.DAYS(E25,N25)<0,0,-_xlfn.DAYS(E25,N25)), " - ") -> 3 | P25: YENIFER PARRA | U25: 46027 | V25: NO | X25: 0 a 5
A26: Factura electrónica | B26: 2b721669a3fd31d7146969f20bd0df755788abdd20721ecbbb738c46358cd0eb350a4459485929385d8600169a72bdd8 | C26: 191240 | D26: FE | E26: 46024 | F26: 46024.62 | G26: =UPPER(TEXT(E26, "MMMM")) -> ENERO | H26: 800180675 | I26: INMOBILIARIA RENTAR SAS | J26: =L26-K26 -> 1965813 | K26: 0 | L26: 1965813 | M26: CONTABILIDAD | N26: 46027 | O26: =IFERROR(IF(-_xlfn.DAYS(E26,N26)<0,0,-_xlfn.DAYS(E26,N26)), " - ") -> 3 | P26: ANGELA FRANCO | U26: 46028 | V26: SI | X26: 0 a 5
A27: Factura electrónica | B27: ca16291f27e8cd1b59460d1037edd6a673e6ffc29263da8e893e580f1ac2f796d3664444921a8de01b3b5d978cc9eda7 | C27: 21228 | D27: FE | E27: 46024 | F27: 46024.409 | G27: =UPPER(TEXT(E27, "MMMM")) -> ENERO | H27: 900083323 | I27: AGENCIA DE INVERSIONES PROSPERAR S.A.S. | J27: =L27-K27 -> 17766259 | K27: 2943005 | L27: 20709264 | M27: CONTABILIDAD | N27: 46027 | O27: =IFERROR(IF(-_xlfn.DAYS(E27,N27)<0,0,-_xlfn.DAYS(E27,N27)), " - ") -> 3 | P27: ANGELA FRANCO | U27: 46028 | V27: SI | X27: 0 a 5
A28: Factura electrónica | B28: d869f8d42f496ba2fa6d109528f67332e8d3412c3f9244c934497e7be12b0aa215dd936776dc72fc713ce47ae5c38f8b | C28: 164256 | D28: 392 | E28: 46024 | F28: 46024.408 | G28: =UPPER(TEXT(E28, "MMMM")) -> ENERO | H28: 860000018 | I28: AGENCIA DE VIAJES Y TURISMO AVIATUR S.A.S | J28: =L28-K28 -> 260000 | K28: 49400 | L28: 309400 | M28: COMPRAS | N28: 46027 | O28: =IFERROR(IF(-_xlfn.DAYS(E28,N28)<0,0,-_xlfn.DAYS(E28,N28)), " - ") -> 3 | P28: YENIFER PARRA | U28: 46035 | V28: NO | X28: 0 a 5
A29: Factura electrónica | B29: 04e7e06e27662008c7478c679f9464c97e41db457b8308e96a384ec405ad3bb6f2fa5c9b234aa7c464fe8fd5ce399919 | C29: 164259 | D29: 392 | E29: 46024 | F29: 46024.406 | G29: =UPPER(TEXT(E29, "MMMM")) -> ENERO | H29: 860000018 | I29: AGENCIA DE VIAJES Y TURISMO AVIATUR S.A.S | J29: =L29-K29 -> 260000 | K29: 49400 | L29: 309400 | M29: COMPRAS | N29: 46027 | O29: =IFERROR(IF(-_xlfn.DAYS(E29,N29)<0,0,-_xlfn.DAYS(E29,N29)), " - ") -> 3 | P29: YENIFER PARRA | U29: 46035 | V29: NO | X29: 0 a 5
A30: Factura electrónica | B30: 7996925666c650a9a1353f910d88b1ea20c53bdb8386d0122158a2c64a1acb500a1c2370d9172cf6e53f5b7c17686341 | C30: 15 | D30: FE | E30: 46024 | F30: 46024.395 | G30: =UPPER(TEXT(E30, "MMMM")) -> ENERO | H30: 901995498 | I30: LA CLAVE RESTAURANTE Y CAFE SAS | J30: =L30-K30 -> 2041200 | K30: 0 | L30: 2041200 | M30: CRUZA | N30: 46028 | O30: =IFERROR(IF(-_xlfn.DAYS(E30,N30)<0,0,-_xlfn.DAYS(E30,N30)), " - ") -> 4
A31: Factura electrónica | B31: eb0b6c479c3695e2123e0824d14f56c7b346e92528855d0c786fa301133a32c9b6d59278046f47aa42c926e9b63299f9 | C31: 4848 | D31: FEL | E31: 46024 | F31: 46024.382 | G31: =UPPER(TEXT(E31, "MMMM")) -> ENERO | H31: 10103705 | I31: RAMIREZ LOPEZ LUIS FERNANDO | J31: =L31-K31 -> 798319.28 | K31: 151680.66 | L31: 949999.94 | M31: SSTA | N31: 46028 | O31: =IFERROR(IF(-_xlfn.DAYS(E31,N31)<0,0,-_xlfn.DAYS(E31,N31)), " - ") -> 4 | P31: YENIFER PARRA | U31: 46044 | V31: NO | X31: 0 a 5
A32: Factura electrónica | B32: 376f585881b95e871c5a69484318c2ee75714de1d512f166e4294afdee45a60954346f1933b4f64a36773326fe4cf828 | C32: 68524 | D32: FETG | E32: 46025 | F32: 46025.48 | G32: =UPPER(TEXT(E32, "MMMM")) -> ENERO | H32: 811001497 | I32: Logistica y Transportes TGB S.A.S | J32: =L32-K32 -> 7508232 | K32: 0 | L32: 7508232 | M32: OPERACIONES | N32: 46027 | O32: =IFERROR(IF(-_xlfn.DAYS(E32,N32)<0,0,-_xlfn.DAYS(E32,N32)), " - ") -> 2 | P32: ANGELA FRANCO | U32: 46028 | V32: NO | X32: 0 a 5
A33: Factura electrónica | B33: ede562a0a9b250d02279cd2926982cbc506e32ad552b217128a645d462d91936ecbb25ea69794e1781ac298783672e9a | C33: 376 | D33: PRS | E33: 46025 | F33: 46025.839 | G33: =UPPER(TEXT(E33, "MMMM")) -> ENERO | H33: 901847080 | I33: PROVSERVICE S.A.S | J33: =L33-K33 -> 26955907 | K33: 5121622.2 | L33: 32077529 | M33: ACERIAS | N33: 46028 | O33: =IFERROR(IF(-_xlfn.DAYS(E33,N33)<0,0,-_xlfn.DAYS(E33,N33)), " - ") -> 3 | P33: YENIFER PARRA | U33: 46044 | V33: NO | X33: 0 a 5
A34: Factura electrónica | B34: ebfe665607bed4ae7b677f824f8cc5e09fca30a59057d7be20a44147b5f665a66ef5084ba3c4075c7a79ef576705db80 | C34: 375 | D34: PRS | E34: 46025 | F34: 46025.825 | G34: =UPPER(TEXT(E34, "MMMM")) -> ENERO | H34: 901847080 | I34: PROVSERVICE S.A.S | J34: =L34-K34 -> 31523796 | K34: 5989521.2 | L34: 37513317 | M34: ACERIAS | N34: 46036 | O34: =IFERROR(IF(-_xlfn.DAYS(E34,N34)<0,0,-_xlfn.DAYS(E34,N34)), " - ") -> 11 | P34: YENIFER PARRA | U34: 46063 | V34: NO | X34: Más de 10
A35: Factura electrónica | B35: f94e9634014b2fae9e1f2a2f089b37bbc2e0658d647647291acea0b426dde23d8f32a4a06ae3b9339cad23c108388556 | C35: 91096 | D35: PEP2 | E35: 46025 | F35: 46025.661 | G35: =UPPER(TEXT(E35, "MMMM")) -> ENERO | H35: 900443098 | I35: SAUL ZULUAGA SAS | J35: =L35-K35 -> 150210.08 | K35: 28539.92 | L35: 178750 | M35: CAJA MENOR | O35: =IFERROR(IF(-_xlfn.DAYS(E35,N35)<0,0,-_xlfn.DAYS(E35,N35)), " - ") -> 0
A36: Factura electrónica | B36: 66ef824d146aec43ca131b38f2b941f1a0f4bf64d1fa4444ec0ff68135febfa3af664a385e55910ee63d7d5e7e10a9ea | C36: 872831 | D36: FEFL | E36: 46025 | F36: 46025.574 | G36: =UPPER(TEXT(E36, "MMMM")) -> ENERO | H36: 900219834 | I36: F2X S.A.S. | J36: =L36-K36 -> 3361.35 | K36: 638.65 | L36: 4000 | M36: COMPRAS | N36: 46042 | O36: =IFERROR(IF(-_xlfn.DAYS(E36,N36)<0,0,-_xlfn.DAYS(E36,N36)), " - ") -> 17 | P36: YENIFER PARRA | U36: 46045 | V36: NO | X36: Más de 10
A37: Factura electrónica | B37: 9fe5cd107c2e0f10b0b6b57e877f4f83e3c5d77c7d3e2eadab89f93744903d1b09778736ce70c4dd17fcd6a21c6a3104 | C37: 167169597 | D37: BCPT | E37: 46025 | F37: 46025.285 | G37: =UPPER(TEXT(E37, "MMMM")) -> ENERO | H37: 830114921 | I37: COLOMBIA MOVIL S.A. ESP | J37: =L37-K37 -> 45428.44 | K37: 8471.56 | L37: 53900 | M37: TI | N37: 46028 | O37: =IFERROR(IF(-_xlfn.DAYS(E37,N37)<0,0,-_xlfn.DAYS(E37,N37)), " - ") -> 3 | P37: JAIME GARCIA | U37: 46036 | V37: NO | X37: 0 a 5
A38: Factura electrónica | B38: 9f9d5aeb205196e37c234bfe19697bcde78fd0b1645602a0363793846f886e550805f9ecad0d6f68e7ab6ef60ad7b3eb | C38: 376 | D38: MD | E38: 46026 | F38: 46026.765 | G38: =UPPER(TEXT(E38, "MMMM")) -> ENERO | H38: 900484392 | I38: Sigfrido SAS | J38: =L38-K38 -> 27859250 | K38: 5293257.5 | L38: 33152508 | M38: CONTABILIDAD | N38: 46027 | O38: =IFERROR(IF(-_xlfn.DAYS(E38,N38)<0,0,-_xlfn.DAYS(E38,N38)), " - ") -> 1 | P38: ANGELA FRANCO | U38: 46028 | V38: SI | X38: 0 a 5
A39: Factura electrónica | B39: 1fa3dd2916332ddd1cc950207759dce016b23fb2b20869c0b6c4407c15d924325cb9862c696f6dc363677b3ccaedff2c | C39: 9006615 | D39: SPRM | E39: 46026 | F39: 46026.394 | G39: =UPPER(TEXT(E39, "MMMM")) -> ENERO | H39: 900843898 | I39: RAPPI S.A.S | J39: =L39-K39 -> 25126.05 | K39: 4773.95 | L39: 29900 | M39: CAJA MENOR | O39: =IFERROR(IF(-_xlfn.DAYS(E39,N39)<0,0,-_xlfn.DAYS(E39,N39)), " - ") -> 0 | U39: 46119 | V39: NO
A40: Factura electrónica | B40: a339170c2cd5e55a457e8057fc81bfd87cc7c6d974aa2cf2587acbc053abe14369fe8e0e0eb7d22e2287f19949f7fb58 | C40: 5482 | E40: 46027 | F40: 46027.948 | G40: =UPPER(TEXT(E40, "MMMM")) -> ENERO | H40: 32150739 | I40: NATALIA ANDREA ACOSTA COLORADO | J40: =L40-K40 -> 424000 | K40: 0 | L40: 424000 | M40: GESTION HUMANA | N40: 46030 | O40: =IFERROR(IF(-_xlfn.DAYS(E40,N40)<0,0,-_xlfn.DAYS(E40,N40)), " - ") -> 3 | P40: YENIFER PARRA | U40: 46036 | V40: NO | X40: 0 a 5
A41: Factura electrónica | B41: b679de5f22900f42f2220cb7686dbad9c628abbd40a62f86c567425732e71189b1ccbda0275389204fb3abaf25864f7d | C41: 2780738 | D41: CA07 | E41: 46027 | F41: 46027.828 | G41: =UPPER(TEXT(E41, "MMMM")) -> ENERO | H41: 890903939 | I41: POSTOBON S.A. | J41: =L41-K41 -> 186900 | K41: 0 | L41: 186900 | M41: COMPRAS | N41: 46029 | O41: =IFERROR(IF(-_xlfn.DAYS(E41,N41)<0,0,-_xlfn.DAYS(E41,N41)), " - ") -> 2 | P41: YENIFER PARRA | U41: 46035 | V41: NO | X41: 0 a 5
A42: Factura electrónica | B42: f4a9a163f4c8db2ed5eb48efeafbcd63873be61899578fabd932cac12cd37ff6c96bf58a158c585c93aeecb012311410 | C42: 2780766 | D42: CA07 | E42: 46027 | F42: 46027.828 | G42: =UPPER(TEXT(E42, "MMMM")) -> ENERO | H42: 890903939 | I42: POSTOBON S.A. | J42: =L42-K42 -> 15798.3 | K42: 3001.68 | L42: 18799.98 | M42: RECHAZADA | N42: 46031 | O42: =IFERROR(IF(-_xlfn.DAYS(E42,N42)<0,0,-_xlfn.DAYS(E42,N42)), " - ") -> 4
A43: Factura electrónica | B43: c40fd25082662b9134b47845b5ce48ec3cba4a83c374fa1a95cc8c6139a413e4d4c93c53e6414b8b06486ca256625a44 | C43: 4863 | D43: FEIT | E43: 46027 | F43: 46027.803 | G43: =UPPER(TEXT(E43, "MMMM")) -> ENERO | H43: 901042685 | I43: ITTERACTIVO S.A.S. | J43: =L43-K43 -> 74394 | K43: 0 | L43: 74394 | M43: TI | N43: 46036 | O43: =IFERROR(IF(-_xlfn.DAYS(E43,N43)<0,0,-_xlfn.DAYS(E43,N43)), " - ") -> 9 | P43: JAIME GARCIA | U43: 46037 | V43: NO | X43: 6 a 10
A44: Factura electrónica | B44: 51aa0b95acbe7552fd3b52448603357193286c8bac8877f50740675ff0e20f84267ba44c01d8d79cb7e1d79a18744593 | C44: 20013351 | D44: 41 | E44: 46027 | F44: 46027.756 | G44: =UPPER(TEXT(E44, "MMMM")) -> ENERO | H44: 860009195 | I44: CESCE COLOMBIA S.A. COMPAÑIA DE SEGUROS | J44: =L44-K44 -> 750000 | K44: 142500 | L44: 892500 | M44: FINANCIERA | N44: 46050 | O44: =IFERROR(IF(-_xlfn.DAYS(E44,N44)<0,0,-_xlfn.DAYS(E44,N44)), " - ") -> 23 | P44: DIANA ARIAS | U44: 46056 | V44: NO | X44: Más de 10
A45: Factura electrónica | B45: 7bd71f2b3461b541fda15e9160da89b7aa8c180c8f8ae40b29cb6c1381b9f7109466833068ba4ebb0029da19a82f1361 | C45: 55255 | D45: FVE | E45: 46027 | F45: 46027.727 | G45: =UPPER(TEXT(E45, "MMMM")) -> ENERO | H45: 900650486 | I45: DISTRIBUIDORA DE SOFTWARE Y MOVILIDAD S.A.S | J45: =L45-K45 -> 50419.33 | K45: 9579.67 | L45: 59999 | M45: TI | N45: 46028 | O45: =IFERROR(IF(-_xlfn.DAYS(E45,N45)<0,0,-_xlfn.DAYS(E45,N45)), " - ") -> 1 | P45: JAIME GARCIA | U45: 46036 | V45: NO | X45: 0 a 5
A46: Factura electrónica | B46: 45dfeadec961c60f9516447a369ffc72162262625854a243a946bb449e11bbbdae3e2dcd06bbb10a4d2373b2324bb172 | C46: 32224 | D46: FEN | E46: 46027 | F46: 46027.71 | G46: =UPPER(TEXT(E46, "MMMM")) -> ENERO | H46: 9522660 | I46: OCTAVIANO TORRES GUEVARA | J46: =L46-K46 -> 420168.1 | K46: 79831.94 | L46: 500000.04 | M46: ACERIAS | N46: 46030 | O46: =IFERROR(IF(-_xlfn.DAYS(E46,N46)<0,0,-_xlfn.DAYS(E46,N46)), " - ") -> 3 | P46: YENIFER PARRA | U46: 46044 | V46: NO | X46: 0 a 5
A47: Factura electrónica | B47: ad0741763197e975ff5b96e1649009a5668749d114d40e024a76e8f368ad617396f24c686300ae28f4d788775a375210 | C47: 119501 | D47: FE | E47: 46027 | F47: 46027.686 | G47: =UPPER(TEXT(E47, "MMMM")) -> ENERO | H47: 830000818 | I47: Crowe CO S.A.S | J47: =L47-K47 -> 9520000 | K47: 1808800 | L47: 11328800 | M47: CONTABILIDAD | N47: 46028 | O47: =IFERROR(IF(-_xlfn.DAYS(E47,N47)<0,0,-_xlfn.DAYS(E47,N47)), " - ") -> 1 | P47: NATALIA BERNAZA | U47: 46028 | V47: SI | X47: 0 a 5
A48: Factura electrónica | B48: 4fde243d0b6ca68d592bf3b6ae040bc2ebd293a3921e39b14faf5ef950201593e9a3fc063880cbaf67aa213eeeb2f15b | C48: 1251 | D48: SM | E48: 46027 | F48: 46027.662 | G48: =UPPER(TEXT(E48, "MMMM")) -> ENERO | H48: 901561580 | I48: SUMINISTRO MATERIALES Y DOTACIONES SUMADO S.A.S | J48: =L48-K48 -> 4627494 | K48: 879223.86 | L48: 5506717.9 | M48: MANTENIMIENTO | N48: 46029 | O48: =IFERROR(IF(-_xlfn.DAYS(E48,N48)<0,0,-_xlfn.DAYS(E48,N48)), " - ") -> 2 | P48: YENIFER PARRA | U48: 46044 | V48: NO | X48: 0 a 5
A49: Factura electrónica | B49: 212e54036eedc203248100ff35fcb779f81b91cfe1514566c3d2d3cdf19d51dd15d6dab1f7178bf7e027e3bdb37ee566 | C49: 253334 | D49: BGFE | E49: 46027 | F49: 46027.641 | G49: =UPPER(TEXT(E49, "MMMM")) -> ENERO | H49: 890907841 | I49: ALMACEN RODAMIENTOS S.A | J49: =L49-K49 -> 424845 | K49: 80721 | L49: 505566 | M49: ACERIAS | N49: 46029 | O49: =IFERROR(IF(-_xlfn.DAYS(E49,N49)<0,0,-_xlfn.DAYS(E49,N49)), " - ") -> 2 | P49: YENIFER PARRA | U49: 46044 | V49: NO | X49: 0 a 5
A50: Factura electrónica | B50: 317853a5047b2518d9297f3f91cda3f79f3a92e3bde43e557a125158b39c7dcbf9a00648430e13d0e4f75d360f054094 | C50: 1008835 | D50: PABF | E50: 46027 | F50: 46027.627 | G50: =UPPER(TEXT(E50, "MMMM")) -> ENERO | H50: 860016640 | I50: TCC S.A.S. | J50: =L50-K50 -> 3023165 | K50: 0 | L50: 3023165 | M50: COMPRAS | N50: 46028 | O50: =IFERROR(IF(-_xlfn.DAYS(E50,N50)<0,0,-_xlfn.DAYS(E50,N50)), " - ") -> 1 | P50: YENIFER PARRA | U50: 46037 | V50: NO | X50: 0 a 5
A51: Factura electrónica | B51: 298f1e7aa74df1092f76d5be570843dc36f511352cc9279fe8bbe5d2f446d538f30901c9402d095d174d01880aac32ea | C51: 103220 | D51: FAE | E51: 46027 | F51: 46027.624 | G51: =UPPER(TEXT(E51, "MMMM")) -> ENERO | H51: 830120839 | I51: MULTISUMINISTROS INDUSTRIALES S A S | J51: =L51-K51 -> 3054080 | K51: 580275 | L51: 3634355 | M51: MANTENIMIENTO | N51: 46028 | O51: =IFERROR(IF(-_xlfn.DAYS(E51,N51)<0,0,-_xlfn.DAYS(E51,N51)), " - ") -> 1 | P51: YENIFER PARRA | U51: 46044 | V51: NO | X51: 0 a 5
A52: Factura electrónica | B52: 290147ebbbe3d25b6b3386a1398087d1f605fe30bb40c4244dc1ab9981eb84a3ad08b3c7ace78b09ffa7c98c27ff73e2 | C52: 103219 | D52: FAE | E52: 46027 | F52: 46027.62 | G52: =UPPER(TEXT(E52, "MMMM")) -> ENERO | H52: 830120839 | I52: MULTISUMINISTROS INDUSTRIALES S A S | J52: =L52-K52 -> 2985120 | K52: 567173 | L52: 3552293 | M52: MANTENIMIENTO | N52: 46029 | O52: =IFERROR(IF(-_xlfn.DAYS(E52,N52)<0,0,-_xlfn.DAYS(E52,N52)), " - ") -> 2 | P52: YENIFER PARRA | U52: 46044 | V52: NO | X52: 0 a 5
A53: Factura electrónica | B53: 67445a41000fa4a8f32963425c8d2c9211e9926b8d028c9be32126d5e5de78fab7b68b7e9fb1c15ad92f06ec9d950767 | C53: 103217 | D53: FAE | E53: 46027 | F53: 46027.616 | G53: =UPPER(TEXT(E53, "MMMM")) -> ENERO | H53: 830120839 | I53: MULTISUMINISTROS INDUSTRIALES S A S | J53: =L53-K53 -> 898000 | K53: 170620 | L53: 1068620 | M53: MANTENIMIENTO | N53: 46028 | O53: =IFERROR(IF(-_xlfn.DAYS(E53,N53)<0,0,-_xlfn.DAYS(E53,N53)), " - ") -> 1 | P53: YENIFER PARRA | U53: 46036 | V53: NO | X53: 0 a 5
A54: Factura electrónica | B54: a8c8ad23fd3545bbae6f8b85aeca5e085072343578d1afc3df30d841f9d675172cadcc8bee7508f0ad0d7e69d95b3c85 | C54: 8557 | D54: FVEC | E54: 46027 | F54: 46027.53 | G54: =UPPER(TEXT(E54, "MMMM")) -> ENERO | H54: 900614579 | I54: ANTIOQUEÑA DE EMPAQUES S.A.S | J54: =L54-K54 -> 758310 | K54: 144078.9 | L54: 902388.9 | M54: COMPRAS | N54: 46028 | O54: =IFERROR(IF(-_xlfn.DAYS(E54,N54)<0,0,-_xlfn.DAYS(E54,N54)), " - ") -> 1 | P54: YENIFER PARRA | U54: 46044 | V54: NO | X54: 0 a 5
... A59: Factura electrónica | B59: 5113492341e92d5f4f2557dfbfea371033b83444150d8c75b41fe29b14c6b3f269e3337315e9107d514c7ad49b90f245 | C59: 9147795 | D59: FLYP | E59: 46027 | F59: 46027.674 | G59: =UPPER(TEXT(E59, "MMMM")) -> ENERO | H59: 900219834 | I59: F2X S.A.S. | J59: =L59-K59 -> 8823.6 | K59: 1676.4 | L59: 10500 | M59: COMPRAS | N59: 46028 | O59: =IFERROR(IF(-_xlfn.DAYS(E59,N59)<0,0,-_xlfn.DAYS(E59,N59)), " - ") -> 1 | P59: YENIFER PARRA | U59: 46035 | V59: NO | X59: 0 a 5
A60: Nota de crédito electrónica | B60: d4b2ee0f3e4e0bde8fc1ea90693dc601648e6612d3d1b25d3233b6c67cda67781b535b72dd886838792ccbd3f4856f1d | C60: 4520 | D60: DMCE | E60: 46027 | F60: 46027.642 | G60: =UPPER(TEXT(E60, "MMMM")) -> ENERO | H60: 830120839 | I60: MULTISUMINISTROS INDUSTRIALES S A S | J60: =L60-K60 -> 3054080 | K60: 580275 | L60: 3634355 | M60: CRUZA | N60: 46031 | O60: =IFERROR(IF(-_xlfn.DAYS(E60,N60)<0,0,-_xlfn.DAYS(E60,N60)), " - ") -> 4
A61: Factura electrónica | B61: a2d2186166e11b7569881fb4fd5a238b02cab73c0e880b0408db59142ccb3b0b38324d636bf73f975cfa29b9ba5edd75 | C61: 151202046 | D61: 9903 | E61: 46027 | F61: 46027.642 | G61: =UPPER(TEXT(E61, "MMMM")) -> ENERO | H61: 800242106 | I61: SODIMAC COLOMBIA S.A. | J61: =L61-K61 -> 201596.64 | K61: 38303.36 | L61: 239900 | M61: COMPRAS | N61: 46029 | O61: =IFERROR(IF(-_xlfn.DAYS(E61,N61)<0,0,-_xlfn.DAYS(E61,N61)), " - ") -> 2 | P61: YENIFER PARRA | U61: 46044 | V61: NO | X61: 0 a 5
A62: Nota de crédito electrónica | B62: 21c087320c3d04c559adebdbadf75c8249dda523f4fdc4578b5d654db51ebc6cdb557a40fc7018b5521f03f719799578 | C62: 4519 | D62: DMCE | E62: 46027 | F62: 46027.64 | G62: =UPPER(TEXT(E62, "MMMM")) -> ENERO | H62: 830120839 | I62: MULTISUMINISTROS INDUSTRIALES S A S | J62: =L62-K62 -> 2985120 | K62: 567173 | L62: 3552293 | M62: CRUZA | N62: 46031 | O62: =IFERROR(IF(-_xlfn.DAYS(E62,N62)<0,0,-_xlfn.DAYS(E62,N62)), " - ") -> 4
A63: Documento equivalente - Cobro de peajes | B63: c934ad11084e0611a76b162ca94a12b31fb9a3c0d769c4b882bcb01ded8806e6ed92343b7010ef2865c99e59db78ec11 | C63: 78109273 | D63: DEFL | E63: 46027 | F63: 46027.639 | G63: =UPPER(TEXT(E63, "MMMM")) -> ENERO | H63: 900219834 | I63: F2X S.A.S. | J63: =L63-K63 -> 13600 | K63: 0 | L63: 13600 | M63: COMPRAS | N63: 46028 | O63: =IFERROR(IF(-_xlfn.DAYS(E63,N63)<0,0,-_xlfn.DAYS(E63,N63)), " - ") -> 1 | P63: YENIFER PARRA | U63: 46036 | V63: NO | X63: 0 a 5
A64: Nota de crédito electrónica | B64: 8a2cba08dcf1b1134016f57a0548b698435e6c371ba38725c39e3608517fcde38f8e14c95585758d1de6cb618139953f | C64: 4518 | D64: DMCE | E64: 46027 | F64: 46027.637 | G64: =UPPER(TEXT(E64, "MMMM")) -> ENERO | H64: 830120839 | I64: MULTISUMINISTROS INDUSTRIALES S A S | J64: =L64-K64 -> 898000 | K64: 170620 | L64: 1068620 | M64: CRUZA | N64: 46031 | O64: =IFERROR(IF(-_xlfn.DAYS(E64,N64)<0,0,-_xlfn.DAYS(E64,N64)), " - ") -> 4
A65: Factura electrónica | B65: 8163be16190992e866b7dd67eeb412281a4d4aaa71752b1e47c9518f266ebae23d5625b406a96858581c9ab41c0e5637 | C65: 99 | D65: FEKE | E65: 46027 | F65: 46027.593 | G65: =UPPER(TEXT(E65, "MMMM")) -> ENERO | H65: 901693444 | I65: KEYSTONE INVERSIONES SAS | J65: =L65-K65 -> 33661928 | K65: 6395766.3 | L65: 40057694 | M65: CONTABILIDAD | N65: 46028 | O65: =IFERROR(IF(-_xlfn.DAYS(E65,N65)<0,0,-_xlfn.DAYS(E65,N65)), " - ") -> 1 | P65: NATALIA BERNAZA | U65: 46028 | V65: SI | X65: 0 a 5
A66: Factura electrónica | B66: 26d44f9d370b38645d7641af9ba09aecd25967de70b54ca2161c64dd07e41dc3bb8d920b467d9572b922d124c0ed0d13 | C66: 11715 | D66: FV | E66: 46027 | F66: 46027.588 | G66: =UPPER(TEXT(E66, "MMMM")) -> ENERO | H66: 1036929757 | I66: SANDRA MILENA MORALES OSPINA | J66: =L66-K66 -> 44000 | K66: 0 | L66: 44000 | M66: CAJA MENOR | O66: =IFERROR(IF(-_xlfn.DAYS(E66,N66)<0,0,-_xlfn.DAYS(E66,N66)), " - ") -> 0
A67: Documento equivalente - Cobro de peajes | B67: 016c97745b8a5752f346f06f481765597d7ab53405beb59055da9004ea95343bb79b8980a0fae5497e8953059341b34a | C67: 78050211 | D67: DEFL | E67: 46027 | F67: 46027.405 | G67: =UPPER(TEXT(E67, "MMMM")) -> ENERO | H67: 900219834 | I67: F2X S.A.S. | J67: =L67-K67 -> 13600 | K67: 0 | L67: 13600 | M67: COMPRAS | N67: 46028 | O67: =IFERROR(IF(-_xlfn.DAYS(E67,N67)<0,0,-_xlfn.DAYS(E67,N67)), " - ") -> 1 | P67: YENIFER PARRA | U67: 46036 | V67: NO | X67: 0 a 5
A68: Factura electrónica | B68: 951ef9533aca1876dc395a47c99f8a1923b0ccf40f6cce061fd7de518e448089d741f33ae171eb82f80b62c3eb564472 | C68: 90706950 | D68: SD | E68: 46027 | F68: 46027.272 | G68: =UPPER(TEXT(E68, "MMMM")) -> ENERO | H68: 890900841 | I68: Caja de Compensación Familiar de Antioquia Comfama | J68: =L68-K68 -> 248600 | K68: 0 | L68: 248600 | M68: BIENESTAR | N68: 46028 | O68: =IFERROR(IF(-_xlfn.DAYS(E68,N68)<0,0,-_xlfn.DAYS(E68,N68)), " - ") -> 1 | P68: ELIANA GOMEZ | U68: 46044 | V68: NO | X68: 0 a 5
A69: Factura electrónica | B69: a7709c95186f873e2222cd16b0be72062207b9e23c8dc19c8a15a3cd08bc27b123fc380e8c1bfd93f8aeb895d5d979cc | C69: 21575 | D69: ALE | E69: 46027 | F69: 46027.255 | G69: =UPPER(TEXT(E69, "MMMM")) -> ENERO | H69: 900377874 | I69: ALEGORIA EVENTOS & B.T.L S.A.S. | J69: =L69-K69 -> 2559700 | K69: 486343 | L69: 3046043 | M69: OPERACIONES | N69: 46035 | O69: =IFERROR(IF(-_xlfn.DAYS(E69,N69)<0,0,-_xlfn.DAYS(E69,N69)), " - ") -> 8 | P69: FRANCY SALAS | U69: 46036 | V69: NO | X69: 6 a 10
A70: Factura electrónica | B70: 9ee895e9568475eadbca13249b5d9014b2895c3a69c788769a2d10d6be585179bde53545ad5fd99a3dbfcd8cea54788f | C70: 718324 | D70: FMED | E70: 46027 | F70: 46027.259 | G70: =UPPER(TEXT(E70, "MMMM")) -> ENERO | H70: 890915475 | I70: EMPAQUETADURAS Y EMPAQUES S.A. | J70: =L70-K70 -> 119576 | K70: 22719.44 | L70: 142295.44 | M70: COMPRAS | N70: 46028 | O70: =IFERROR(IF(-_xlfn.DAYS(E70,N70)<0,0,-_xlfn.DAYS(E70,N70)), " - ") -> 1 | P70: YENIFER PARRA | U70: 46036 | V70: NO | X70: 0 a 5
A71: Factura electrónica | B71: c5ac88b049b7d8d8dd7fef8a962dcebc9ef725f197d99da6c2a696aed3007522c7c8f8221a4215a82596035713d6fc75 | C71: 30354 | D71: AER1 | E71: 46027 | F71: 46027.348 | G71: =UPPER(TEXT(E71, "MMMM")) -> ENERO | H71: 900659583 | I71: INVERSIONES RCP S.A.S | J71: =L71-K71 -> 27226.891 | K71: 5173.1092 | L71: 32400 | M71: CAJA MENOR | O71: =IFERROR(IF(-_xlfn.DAYS(E71,N71)<0,0,-_xlfn.DAYS(E71,N71)), " - ") -> 0 | U71: 46044 | V71: NO
A72: Factura electrónica | B72: 855e30eb0d277a2c88f7798681807f82369b822c5e62971604179852975acb16bfd80fb71a4c8a9a54bed4b72c6e0659 | C72: 194973 | D72: FETN | E72: 46027 | F72: 46027.323 | G72: =UPPER(TEXT(E72, "MMMM")) -> ENERO | H72: 890903229 | I72: TRANSPORTES CHACHAFRUTO S.A. | J72: =L72-K72 -> 23000 | K72: 0 | L72: 23000 | M72: CAJA MENOR | O72: =IFERROR(IF(-_xlfn.DAYS(E72,N72)<0,0,-_xlfn.DAYS(E72,N72)), " - ") -> 0
A73: Factura electrónica | B73: ebda5ec9764cb2693402bb69529ec8d0e02044b3f75bc02c7507cfd4b3431abe104d99bc38eaaaf4ce63383351aad064 | C73: 5492 | E73: 46028 | F73: 46028.94 | G73: =UPPER(TEXT(E73, "MMMM")) -> ENERO | H73: 32150739 | I73: NATALIA ANDREA ACOSTA COLORADO | J73: =L73-K73 -> 657000 | K73: 0 | L73: 657000 | M73: GESTION HUMANA | N73: 46041 | O73: =IFERROR(IF(-_xlfn.DAYS(E73,N73)<0,0,-_xlfn.DAYS(E73,N73)), " - ") -> 13 | P73: YENIFER PARRA | U73: 46042 | V73: NO | X73: Más de 10
A74: Factura electrónica | B74: e19a155a90b793b91be3542d9a010f3420db282ee75f7584134eb96bd29690d21824eb3cc144c81bb0a1a913216ddf7f | C74: 485 | D74: WC | E74: 46028 | F74: 46028.845 | G74: =UPPER(TEXT(E74, "MMMM")) -> ENERO | H74: 901741749 | I74: WORLD CRANES SAS | J74: =L74-K74 -> 8450000 | K74: 1605500 | L74: 10055500 | M74: ACERIAS | N74: 46030 | O74: =IFERROR(IF(-_xlfn.DAYS(E74,N74)<0,0,-_xlfn.DAYS(E74,N74)), " - ") -> 2 | P74: YENIFER PARRA | U74: 46044 | V74: NO | X74: 0 a 5
A75: Factura electrónica | B75: a319413cfca4be3cbb807d668f8bbcc4081fa5a7b2a9189702953776be28702f89a255c150d976de0618cbfb473a49d1 | C75: 2863 | D75: EOV1 | E75: 46028 | F75: 46028.831 | G75: =UPPER(TEXT(E75, "MMMM")) -> ENERO | H75: 901563450 | I75: BACO FOODS COLOMBIA S.A.S | J75: =L75-K75 -> 41300 | K75: 0 | L75: 41300 | M75: CAJA MENOR | O75: =IFERROR(IF(-_xlfn.DAYS(E75,N75)<0,0,-_xlfn.DAYS(E75,N75)), " - ") -> 0 | U75: 46044 | V75: NO
A76: Documento equivalente - Cobro de peajes | B76: bca1036eadfbeb66d9296a843b66e5fdc7e057fc57c700c7964f29ef4a053f1acbad86321f9f45b4de7bf9c4ad3458ad | C76: 78362686 | D76: DEFL | E76: 46028 | F76: 46028.734 | G76: =UPPER(TEXT(E76, "MMMM")) -> ENERO | H76: 900219834 | I76: F2X S.A.S. | J76: =L76-K76 -> 18600 | K76: 0 | L76: 18600 | M76: COMPRAS | N76: 46029 | O76: =IFERROR(IF(-_xlfn.DAYS(E76,N76)<0,0,-_xlfn.DAYS(E76,N76)), " - ") -> 1 | P76: YENIFER PARRA | U76: 46035 | V76: NO | X76: 0 a 5
A77: Factura electrónica | B77: c3dc2a03405cf029fb48fa2da4e1d8e947de081eed0130790b04f8b377a8034b25dcdf448ab24670ae9137969b8b4b4e | C77: 55316 | D77: FVE | E77: 46028 | F77: 46028.711 | G77: =UPPER(TEXT(E77, "MMMM")) -> ENERO | H77: 900650486 | I77: DISTRIBUIDORA DE SOFTWARE Y MOVILIDAD S.A.S | J77: =L77-K77 -> 117646.22 | K77: 22352.78 | L77: 139999 | M77: TI | N77: 46028 | O77: =IFERROR(IF(-_xlfn.DAYS(E77,N77)<0,0,-_xlfn.DAYS(E77,N77)), " - ") -> 0 | P77: JAIME GARCIA | U77: 46036 | V77: NO | X77: 0 a 5
A78: Factura electrónica | B78: fd5864849a505056b51d45996aba092783653f7c23e5da0fce7f126af3ddc1b708867852d56069eb22ad8bfa08e13870 | C78: 16663 | D78: MEDN | E78: 46028 | F78: 46028.635 | G78: =UPPER(TEXT(E78, "MMMM")) -> ENERO | H78: 900075456 | I78: Asignar S.A.S | J78: =L78-K78 -> 293617040 | K78: 5181844 | L78: 2.9879888e+08 | M78: NOMINA | N78: 46029 | O78: =IFERROR(IF(-_xlfn.DAYS(E78,N78)<0,0,-_xlfn.DAYS(E78,N78)), " - ") -> 1 | P78: MAURICIO ARBOOLEDA | U78: 46036 | V78: SI | X78: 0 a 5
A79: Factura electrónica | B79: 2529447fbc363c096e240f8dce97eb38bd324c199d4321f90fcc9f2d8587040926bda4d87e8c6c38a09a8b3144a258a9 | C79: 150 | D79: PROS | E79: 46028 | F79: 46028.677 | G79: =UPPER(TEXT(E79, "MMMM")) -> ENERO | H79: 901797186 | I79: PROTON S SAS | J79: =L79-K79 -> 3159460 | K79: 600297.4 | L79: 3759757.4 | M79: ACERIAS | N79: 46029 | O79: =IFERROR(IF(-_xlfn.DAYS(E79,N79)<0,0,-_xlfn.DAYS(E79,N79)), " - ") -> 1 | P79: YENIFER PARRA | U79: 46044 | V79: NO | X79: 0 a 5
A80: Factura electrónica | B80: b28b5d1a4dde53e235ac92262a876bd4e6b5fb1d4810676187c46d2a04abde59432ac1143185eaf6852123b316217305 | C80: 16665 | D80: MEDN | E80: 46028 | F80: 46028.635 | G80: =UPPER(TEXT(E80, "MMMM")) -> ENERO | H80: 900075456 | I80: Asignar S.A.S | J80: =L80-K80 -> 830611 | K80: 0 | L80: 830611 | M80: NOMINA | N80: 46029 | O80: =IFERROR(IF(-_xlfn.DAYS(E80,N80)<0,0,-_xlfn.DAYS(E80,N80)), " - ") -> 1 | P80: MAURICIO ARBOOLEDA | U80: 46035 | V80: NO | X80: 0 a 5
A81: Factura electrónica | B81: 61d6436475738fb735d53960a7e2abff11295408df2e1391ee3301077ce2d1e2ad335b2850bd1f638c7c091560a6caaa | C81: 16664 | D81: MEDN | E81: 46028 | F81: 46028.635 | G81: =UPPER(TEXT(E81, "MMMM")) -> ENERO | H81: 900075456 | I81: Asignar S.A.S | J81: =L81-K81 -> 5491294 | K81: 0 | L81: 5491294 | M81: NOMINA | N81: 46029 | O81: =IFERROR(IF(-_xlfn.DAYS(E81,N81)<0,0,-_xlfn.DAYS(E81,N81)), " - ") -> 1 | P81: MAURICIO ARBOOLEDA | U81: 46035 | V81: NO | X81: 0 a 5
A82: Factura electrónica | B82: 971c4397b0c7a0e7cbe69f99692ed033cc48228682612d510d3940d35b99804592bd687aec6b039ac62880dba125a7f2 | C82: 9874 | D82: FEC | E82: 46028 | F82: 46028.442 | G82: =UPPER(TEXT(E82, "MMMM")) -> ENERO | H82: 891800044 | I82: COOPERATIVA DE TRANSPORTADORES RAPIDO CHICAMOCHA | J82: =L82-K82 -> 1512000 | K82: 0 | L82: 1512000 | M82: OPERACIONES | N82: 46036 | O82: =IFERROR(IF(-_xlfn.DAYS(E82,N82)<0,0,-_xlfn.DAYS(E82,N82)), " - ") -> 8 | P82: YENIFER PARRA | U82: 46041 | V82: NO | X82: 6 a 10
A83: Factura electrónica | B83: 177166b32fe40e7929fac9f1ef4632be7101b736c8e11d4c6dcc007a93238101d0b7431152a355b5469a056df985d150 | C83: 3397 | D83: FDR | E83: 46028 | F83: 46028.697 | G83: =UPPER(TEXT(E83, "MMMM")) -> ENERO | H83: 70907060 | I83: WILINTON DUQUE GONZALEZ | J83: =L83-K83 -> 123100 | K83: 0 | L83: 123100 | M83: CAJA MENOR | O83: =IFERROR(IF(-_xlfn.DAYS(E83,N83)<0,0,-_xlfn.DAYS(E83,N83)), " - ") -> 0
A84: Factura electrónica | B84: 33e44237e0b5d8901ad163f491958259968bb7c26d90ff90d26261aa5a3cba2a09dcffb4a7a11c879798fa326cb9b7d7 | C84: 223 | D84: ARB | E84: 46028 | F84: 46028.628 | G84: =UPPER(TEXT(E84, "MMMM")) -> ENERO | H84: 900654063 | I84: ARBELAEZ ASOCIADOS SAS | J84: =L84-K84 -> 3075000 | K84: 584250 | L84: 3659250 | M84: CRUZA | N84: 46032 | O84: =IFERROR(IF(-_xlfn.DAYS(E84,N84)<0,0,-_xlfn.DAYS(E84,N84)), " - ") -> 4 | P84: NATALIA BERNAZA | Q84: YENIFER PARRA | R84: 46042 | X84: 0 a 5
A85: Factura electrónica | B85: d079cd9580a2c200d679fdb709fc40d884c6cdc9b38a4b618063e03570bf6a198adab7e54a9c4ce138bc5d065b2f3d86 | C85: 1507091 | D85: 9911 | E85: 46028 | F85: 46028.619 | G85: =UPPER(TEXT(E85, "MMMM")) -> ENERO | H85: 800242106 | I85: SODIMAC COLOMBIA S.A. | J85: =L85-K85 -> 4900 | K85: 0 | L85: 4900 | M85: COMPRAS | N85: 46029 | O85: =IFERROR(IF(-_xlfn.DAYS(E85,N85)<0,0,-_xlfn.DAYS(E85,N85)), " - ") -> 1 | P85: YENIFER PARRA | U85: 46036 | V85: NO | X85: 0 a 5
A86: Factura electrónica | B86: fb8a36de79ca4bad9e712b9bf80bb5101c908137247d65425a7f169dd079983f8b066eeeda3d9f6ebe8f13723bd225bc | C86: 65029227 | D86: 61 | E86: 46028 | F86: 46028.607 | G86: =UPPER(TEXT(E86, "MMMM")) -> ENERO | H86: 800230447 | I86: SODEXO S A S | J86: =L86-K86 -> 4634284 | K86: 880513.96 | L86: 5514798 | M86: OPERACIONES | N86: 46035 | O86: =IFERROR(IF(-_xlfn.DAYS(E86,N86)<0,0,-_xlfn.DAYS(E86,N86)), " - ") -> 7 | P86: FRANCY SALAS | U86: 46036 | V86: NO | X86: 6 a 10
A87: Factura electrónica | B87: a57ced29f23b8fb661f8109f02d09c90fd397103e7bed445fa05c81c44a6f150f7bb8952ba7eae33df116ccfd85d1cb8 | C87: 916098 | D87: FEFL | E87: 46028 | F87: 46028.487 | G87: =UPPER(TEXT(E87, "MMMM")) -> ENERO | H87: 900219834 | I87: F2X S.A.S. | J87: =L87-K87 -> 3781.51 | K87: 718.49 | L87: 4500 | M87: COMPRAS | N87: 46029 | O87: =IFERROR(IF(-_xlfn.DAYS(E87,N87)<0,0,-_xlfn.DAYS(E87,N87)), " - ") -> 1 | P87: YENIFER PARRA | U87: 46036 | V87: NO | X87: 0 a 5
A88: Factura electrónica | B88: 9ddaab4bdbcc6537f7960d2ab2404bcd144dc155cb27672ead93a95189c5a4f69a0757141ea6cb8d3cf850c0785aeff2 | C88: 226919 | D88: FE | E88: 46028 | F88: 46028.399 | G88: =UPPER(TEXT(E88, "MMMM")) -> ENERO | H88: 890937070 | I88: TIEMPOS S.A.S. | J88: =L88-K88 -> 9595380 | K88: 182312 | L88: 9777692 | M88: NOMINA | N88: 46029 | O88: =IFERROR(IF(-_xlfn.DAYS(E88,N88)<0,0,-_xlfn.DAYS(E88,N88)), " - ") -> 1 | P88: MAURICIO ARBOOLEDA | U88: 46036 | V88: NO | X88: 0 a 5
A89: Factura electrónica | B89: 8d7d370117cb54230e4d252a7e6ef96197686543d1bc229b379f5ceb207f2257b408b553e32aabf1a339440fe4fbde17 | C89: 914923 | D89: FEFL | E89: 46028 | F89: 46028.43 | G89: =UPPER(TEXT(E89, "MMMM")) -> ENERO | H89: 900219834 | I89: F2X S.A.S. | J89: =L89-K89 -> 2436.98 | K89: 463.02 | L89: 2900 | M89: COMPRAS | N89: 46029 | O89: =IFERROR(IF(-_xlfn.DAYS(E89,N89)<0,0,-_xlfn.DAYS(E89,N89)), " - ") -> 1 | P89: YENIFER PARRA | U89: 46036 | V89: NO | X89: 0 a 5
A90: Nota de crédito electrónica | B90: e90e7c75ea22d343336d66618be3e4956c2fb205e5a3f8420cbf547d03fb552f02fd3ac0c9d5180ad1b0e407fd6a328c | C90: 13399 | D90: NCE | E90: 46028 | F90: 46028.421 | G90: =UPPER(TEXT(E90, "MMMM")) -> ENERO | H90: 890937070 | I90: TIEMPOS S.A.S. | J90: =L90-K90 -> 50772 | K90: 965 | L90: 51737 | M90: NOMINA | N90: 46029 | O90: =IFERROR(IF(-_xlfn.DAYS(E90,N90)<0,0,-_xlfn.DAYS(E90,N90)), " - ") -> 1 | P90: MAURICIO ARBOOLEDA | U90: 46035 | V90: NO | X90: 0 a 5
A91: Documento equivalente - Cobro de peajes | B91: 5fd9748bc492c8e7c6848384df2632a9e35e76c433c2101df771634cef91e1c62836ab7c345eb936c0afac8a24fd1833 | C91: 78262839 | D91: DEFL | E91: 46028 | F91: 46028.396 | G91: =UPPER(TEXT(E91, "MMMM")) -> ENERO | H91: 900219834 | I91: F2X S.A.S. | J91: =L91-K91 -> 18600 | K91: 0 | L91: 18600 | M91: COMPRAS | N91: 46029 | O91: =IFERROR(IF(-_xlfn.DAYS(E91,N91)<0,0,-_xlfn.DAYS(E91,N91)), " - ") -> 1 | P91: YENIFER PARRA | U91: 46035 | V91: NO | X91: 0 a 5
A92: Factura electrónica | B92: 31fc6d66b637333a4d52e6ec95fee02b1d70674ad8308954c7e3366391724e9c779b091c193bb769e9c875950c817c8c | C92: 4433 | D92: TAX | E92: 46028 | F92: 46028.392 | G92: =UPPER(TEXT(E92, "MMMM")) -> ENERO | H92: 901417727 | I92: B2B TAX & LEGAL S.A.S. BIC | J92: =L92-K92 -> 1806750 | K92: 343282.5 | L92: 2150032.5 | M92: CONTABILIDAD | N92: 46028 | O92: =IFERROR(IF(-_xlfn.DAYS(E92,N92)<0,0,-_xlfn.DAYS(E92,N92)), " - ") -> 0 | P92: NATALIA BERNAZA | U92: 46028 | V92: NO | X92: 0 a 5
A93: Factura electrónica | B93: 805ed1715ce29da77f76103bb881483d101febfedb3dfd95043170e98b6452d053b1dd70004c1f688a86c618413c09c9 | C93: 562702 | D93: AH | E93: 46028 | F93: 46028.311 | G93: =UPPER(TEXT(E93, "MMMM")) -> ENERO | H93: 890800788 | I93: SUMATEC S.A.S BIC | J93: =L93-K93 -> 69000 | K93: 13110 | L93: 82110 | M93: COMPRAS | N93: 46028 | O93: =IFERROR(IF(-_xlfn.DAYS(E93,N93)<0,0,-_xlfn.DAYS(E93,N93)), " - ") -> 0 | P93: YENIFER PARRA | U93: 46037 | V93: NO | X93: 0 a 5
A94: Factura electrónica | B94: 005e60e60c014da4cda5534f27682a0e4ffe69d6df5d99fb8bc4a9b3cbac8fbeee4297f57cf5d16654af9cd653eccfd2 | C94: 29213 | D94: FEV | E94: 46028 | F94: 46028.326 | G94: =UPPER(TEXT(E94, "MMMM")) -> ENERO | H94: 900636260 | I94: ASOCIACION DE COPROPIETARIOS DE CELTA TRADE PARK UNO | J94: =L94-K94 -> 1587829 | K94: 0 | L94: 1587829 | M94: CONTABILIDAD | N94: 46028 | O94: =IFERROR(IF(-_xlfn.DAYS(E94,N94)<0,0,-_xlfn.DAYS(E94,N94)), " - ") -> 0 | P94: NATALIA BERNAZA | U94: 46029 | V94: SI | X94: 0 a 5
A95: Factura electrónica | B95: 34df2e1c8ef9eb978cab2ba8f367b8c3091f48f3bc1ddc9e7743019d5aa12d537c16e0f0282b73cbbc5c638e2cd7bf8d | C95: 29212 | D95: FEV | E95: 46028 | F95: 46028.325 | G95: =UPPER(TEXT(E95, "MMMM")) -> ENERO | H95: 900636260 | I95: ASOCIACION DE COPROPIETARIOS DE CELTA TRADE PARK UNO | J95: =L95-K95 -> 1588305 | K95: 0 | L95: 1588305 | M95: CONTABILIDAD | N95: 46028 | O95: =IFERROR(IF(-_xlfn.DAYS(E95,N95)<0,0,-_xlfn.DAYS(E95,N95)), " - ") -> 0 | P95: NATALIA BERNAZA | U95: 46028 | V95: SI | X95: 0 a 5
A96: Factura electrónica | B96: 7ee8f358f66f19e0aea0a6a3720fa1ba1bce4b433eb0520bb5d54427b634142e196b67f48d869ddc10bc371edecd4980 | C96: 13725 | D96: FEPF | E96: 46028 | F96: 46028.323 | G96: =UPPER(TEXT(E96, "MMMM")) -> ENERO | H96: 71951636 | I96: TABORDA GONZALEZ JESUS ANIBAL | J96: =L96-K96 -> 30336.13 | K96: 5763.87 | L96: 36100 | M96: CAJA MENOR | O96: =IFERROR(IF(-_xlfn.DAYS(E96,N96)<0,0,-_xlfn.DAYS(E96,N96)), " - ") -> 0
A97: Factura electrónica | B97: 072c4dced2517a540936951ecb7708c9046d5eb574a7fcdd8f063bc44c8677ac2e28a4068b9089f08e8625f549022f2d | C97: 2668726 | D97: CL07 | E97: 46028 | F97: 46028.069 | G97: =UPPER(TEXT(E97, "MMMM")) -> ENERO | H97: 860001697 | I97: GASEOSAS LUX S.A.S. | J97: =L97-K97 -> 93450 | K97: 0 | L97: 93450 | M97: COMPRAS | N97: 46029 | O97: =IFERROR(IF(-_xlfn.DAYS(E97,N97)<0,0,-_xlfn.DAYS(E97,N97)), " - ") -> 1 | P97: YENIFER PARRA | U97: 46035 | V97: NO | X97: 0 a 5
A98: Factura electrónica | B98: 8ccabfe8b7408be45c7031e69a446ccdfd88883ca42cb6f4c4d7a606a5e3fead21ab03ccba2611bd604a41531d8296b2 | C98: 90707765 | D98: SD | E98: 46029 | F98: 46029.711 | G98: =UPPER(TEXT(E98, "MMMM")) -> ENERO | H98: 890900841 | I98: Caja de Compensación Familiar de Antioquia Comfama | J98: =L98-K98 -> 300400 | K98: 0 | L98: 300400 | M98: BIENESTAR | N98: 46030 | O98: =IFERROR(IF(-_xlfn.DAYS(E98,N98)<0,0,-_xlfn.DAYS(E98,N98)), " - ") -> 1 | P98: ELIANA GOMEZ | U98: 46044 | V98: NO | X98: 0 a 5
A99: Factura electrónica | B99: a555e1729354dc226125cfc86d44a69fac519593a75fc9d6b5528f80065d51165fdeb0f50f07162b9b3ace9f47244683 | C99: 5507 | E99: 46029 | F99: 46029.879 | G99: =UPPER(TEXT(E99, "MMMM")) -> ENERO | H99: 32150739 | I99: NATALIA ANDREA ACOSTA COLORADO | J99: =L99-K99 -> 683500 | K99: 0 | L99: 683500 | M99: GESTION HUMANA | N99: 46030 | O99: =IFERROR(IF(-_xlfn.DAYS(E99,N99)<0,0,-_xlfn.DAYS(E99,N99)), " - ") -> 1 | P99: YENIFER PARRA | U99: 46036 | V99: NO | X99: 0 a 5
A100: Factura electrónica | B100: f1ddd3270daebdfcff1428c7638f6de9c8f56869a744cb2eb458965830b8bdc3f69135d698624f07117b33a4520bc92d | C100: 61 | D100: FEBU | E100: 46029 | F100: 46029.819 | G100: =UPPER(TEXT(E100, "MMMM")) -> ENERO | H100: 901404801 | I100: BUTTERMILK S.A.S. | J100: =L100-K100 -> 33661928 | K100: 6395766.3 | L100: 40057694 | M100: CONTABILIDAD | N100: 46030 | O100: =IFERROR(IF(-_xlfn.DAYS(E100,N100)<0,0,-_xlfn.DAYS(E100,N100)), " - ") -> 1 | P100: NATALIA BERNAZA | U100: 46030 | V100: NO | X100: 0 a 5
A101: Factura electrónica | B101: efecc087df975e962aa1d0c45b2a8747e656b06b82d7a476bd1b9b1546ffd74ec5153c2b2598cc191220d21e1ce3abf5 | C101: 339593 | D101: FFEE | E101: 46029 | F101: 46029.667 | G101: =UPPER(TEXT(E101, "MMMM")) -> ENERO | H101: 800049074 | I101: PAPELERIA Y SERVICIOS SAS | J101: =L101-K101 -> 6458 | K101: 1227 | L101: 7685 | M101: COMPRAS | N101: 46037 | O101: =IFERROR(IF(-_xlfn.DAYS(E101,N101)<0,0,-_xlfn.DAYS(E101,N101)), " - ") -> 8 | P101: YENIFER PARRA | U101: 46041 | V101: NO | X101: 6 a 10
A102: Factura electrónica | B102: 6c4665fedfc31fde9c123800bacbbe4d6b11981a7707554c3bc8f8e0789f819375405fa93bb90a189c3e12b37620954c | C102: 41188 | D102: FESA | E102: 46029 | F102: 46029.711 | G102: =UPPER(TEXT(E102, "MMMM")) -> ENERO | H102: 890938952 | I102: SALAMANCA ALIMENTACION INDUSTRIAL S.A.S. | J102: =L102-K102 -> 13016250 | K102: 2473087.5 | L102: 15489338 | M102: OPERACIONES | N102: 46035 | O102: =IFERROR(IF(-_xlfn.DAYS(E102,N102)<0,0,-_xlfn.DAYS(E102,N102)), " - ") -> 6 | P102: FRANCY SALAS | U102: 46036 | V102: NO | X102: 6 a 10
A103: Factura electrónica | B103: bfe94184cbdca321da5910f427f79343442509239159968735629437c4af445b03d0a0d367dcd740e90c071e4cbe755e | C103: 718882 | D103: FMED | E103: 46029 | F103: 46029.685 | G103: =UPPER(TEXT(E103, "MMMM")) -> ENERO | H103: 890915475 | I103: EMPAQUETADURAS Y EMPAQUES S.A. | J103: =L103-K103 -> 93730 | K103: 17808.7 | L103: 111538.7 | M103: COMPRAS | N103: 46030 | O103: =IFERROR(IF(-_xlfn.DAYS(E103,N103)<0,0,-_xlfn.DAYS(E103,N103)), " - ") -> 1 | P103: YENIFER PARRA | U103: 46036 | V103: NO | X103: 0 a 5
A104: Factura electrónica | B104: f880e2292f8ce366fe430b483f142ae6f7f56bac28fa4fcf31b33cd3fcabaaaa25d7be86dd9e1555936c58f23b75a68b | C104: 339592 | D104: FFEE | E104: 46029 | F104: 46029.667 | G104: =UPPER(TEXT(E104, "MMMM")) -> ENERO | H104: 800049074 | I104: PAPELERIA Y SERVICIOS SAS | J104: =L104-K104 -> 673965 | K104: 46814 | L104: 720779 | M104: COMPRAS | N104: 46030 | O104: =IFERROR(IF(-_xlfn.DAYS(E104,N104)<0,0,-_xlfn.DAYS(E104,N104)), " - ") -> 1 | P104: YENIFER PARRA | U104: 46036 | V104: NO | X104: 0 a 5
...

Sheet Hoja3
A1: NIT | B1: Nombre Emisor
A2: 890331634 | B2: IMPORTACION TECNICA ESTUDIOS Y COMERCIALIZACION S.A.
A3: 900933624 | B3: MECANIZADOS Y SERVICIOS MAYROP SAS
A4: 900168538 | B4: MAQUINADOS Y REPUESTOS BETANCUR E.U
A5: 890907841 | B5: ALMACEN RODAMIENTOS S.A
A6: 901950863 | B6: INVERSIONES TORNIILLOS Y MANGUERAS SAS
A7: 830085391 | B7: KIMIK S.A.S.
A8: 900420442 | B8: INSTRUMENTOS Y PARTES S.A.S
A9: 811011781 | B9: UMP DE COLOMBIA
A10: 42889142 | B10: HERNANDEZ CORREA DORA INES
A11: 9522660 | B11: TORRES GUEVARA OCTAVIANO
A12: 901478945 | B12: TREFLINE Y ASOCIADOS SAS
A13: 900563128 | B13: SOLUCIONES SIMMAC SAS
... A49: 830107115 | B49: TURNPIKE COLOMBIA SAS

Sheet Hoja2
H3: 56000 | I3: 1.284
H4: =H3/I3 -> 43613.707 | I4: 0.19 | J4: 0.094
I5: =H4*19% -> 8286.6044 | J5: =H4*9.4% -> 4099.6885
